Workbook

Sheet 2014 - 2015
B1: MARÇO 2014
E2: OC | F2: DATA | I2: PREÇO | J2: CODIGO | K2: DATA | L2: DATA | Q2: DATA | R2: VALOR DA
B3: CLIENTE | C3: PRODUTO | D3: PEDIDO | E3: DO | F3: DO | G3: QUANT | H3: UND | I3: POR | J3: DO | K3: DE | L3: DE | M3: N F | N3: QUANT | O3: SALDO | P3: VALOR | Q3: COMISSÃO | R3: COMISSÃO | S3: OBSERVAÇÃO | V3: AGC - BOM BLISTER | W3: VITOR (27) 99608-1521 ELIJOICE (27) 99754-4214 | AD3: ALTENIS (27) 99984-3055 | AH3: (27) 3371-3138 | AJ3: ERMERLANDO | AN3: MÊS | AO3: COMISSÃO | AP3: PAGAMENTO | AQ3: DATA | AR3: SALDO
E4: CLIENTE | F4: PEDIDO | I4: UND | J4: CLIENTE | K4: ENTREGA | L4: FATURA | Q4: 30 DD | R4: R$ | X4: OC | Y4: DATA | AB4: PREÇO | AC4: CODIGO | AD4: DATA | AE4: DATA | AJ4: DATA | AK4: VALOR DA | AN4: 41334 | AO4: 5402.32 | AP4: 5402.32 | AQ4: 06/06/2013 | AR4: =(AP4-AO4) -> 0
B5: DOCE MEL | C5: =IF(J5=1473,"BANDEJA PAPAYA PET - GF 15",IF(J5=0," ")) -> BANDEJA PAPAYA PET - GF 15 | D5: 12 | E5: 2666 | F5: 41600 | G5: 60.3 | H5: MIL | I5: 498 | J5: 1473 | K5: 41696 | L5: 41703 | M5: 2003 | N5: 60300 | O5: =(N5-G5*1000) -> 0 | P5: =(N5*I5/1000) -> 30029.4 | Q5: =(L5+30) -> 41733 | R5: =(P5*0.05) -> 1501.47 | V5: PRODUTO | W5: PEDIDO | X5: DO | Y5: DO | Z5: QUANT | AA5: UND | AB5: POR | AC5: DO | AD5: DE | AE5: DE | AF5: N F | AG5: QUANT | AH5: SALDO | AI5: VALOR | AJ5: COMISSÃO | AK5: COMISSÃO | AL5: OBSERVAÇÃO | AN5: 41365 | AO5: 6542.42 | AP5: 6542.42 | AQ5: 27/06/2013 | AR5: =(AP5-AO5) -> 0
B6: FRUT MEL | C6: BAND BLIS MAMÃO PAPAYA 4 UND | D6: 1 | E6: E-MAIL | F6: 41695 | G6: 15 | H6: MIL | I6: 470 | K6: 41688 | L6: 41712 | M6: 2010 | N6: 15200 | O6: =(N6-G6*1000) -> 200 | P6: =(N6*I6/1000) -> 7144 | Q6: =(L6+28) -> 41740 | R6: =(P6*0.05) -> 357.2 | S6: ITAU R$ 178,60 05/08/2014 | X6: CLIENTE | Y6: PEDIDO | AB6: UND | AC6: CLIENTE | AD6: ENTREGA | AE6: FATURA | AJ6: 35 DD | AK6: R$ | AN6: 41395 | AO6: 6284.78 | AP6: 4500 | AQ6: 01/08/2013 | AR6: =(AP6-AO6) -> -1784.78
B7: CALIMAN AGRICOLA | C7: BANDEJA TRANSP-04 CAV "OVO" | D7: 3 | E7: 005749/1 | F7: 41704 | G7: 25.2 | H7: MIL | I7: 470 | K7: 41717 | L7: 41710 | M7: 2008 | N7: 25200 | O7: =(N7-G7*1000) -> 0 | P7: =(N7*I7/1000) -> 11844 | Q7: =(L7+28) -> 41738 | R7: =(P7*0.05) -> 592.2 | AP7: 1784.78 | AQ7: 09/08/2013 | AR7: 0
B8: FRUTAS SOLO | C8: BANDEJA PAPAYA C/ 400 UND | D8: 1 | E8: 9140 | F8: 41709 | G8: 40 | H8: MIL | I8: 470 | J8: 8490 | K8: 41711 | L8: 41717 | M8: 2013 | N8: 40000 | O8: =(N8-G8*1000) -> 0 | P8: =(N8*I8/1000) -> 18800 | Q8: =(L8+35) -> 41752 | R8: =(P8*0.05) -> 940 | S8: ITAU R$ 470,00 05/08/2014 | V8: BANDEJAS MAMÃO PAPAYA 4 UND | W8: 1 | X8: e-mail | Y8: 41781 | Z8: 20 | AA8: MIL | AB8: 590 | AD8: 41800 | AE8: 41817 | AF8: 2083 | AG8: 21350 | AH8: =(AG8-Z8*1000) -> 1350 | AI8: =(AG8*AB8/1000) -> 12596.5 | AJ8: =(AE8+35) -> 41852 | AK8: =(AI8*0.05) -> 629.825 | AN8: 41426 | AO8: 6461.29 | AP8: 3461.29 | AQ8: 30/08/2013 | AR8: -3000
B9: DOCE MEL | C9: =IF(J9=1473,"BANDEJA PAPAYA PET - GF 15",IF(J9=0," ")) -> BANDEJA PAPAYA PET - GF 15 | D9: 13 | E9: 3133 | F9: 41712 | G9: 80 | H9: MIL | I9: 498 | J9: 1473 | K9: 41716 | L9: =(K9) -> 41716 | M9: 2016 | N9: 30000 | O9: =(N9-G9*1000) -> -50000 | P9: =(N9*I9/1000) -> 14940 | Q9: =(L9+30) -> 41746 | R9: =(P9*0.05) -> 747 | V9: BANDEJAS MAMÃO PAPAYA 4 UND | W9: 2 | X9: e-mail | Y9: 41893 | Z9: 40 | AA9: MIL | AB9: 570 | AD9: 41908 | AE9: 41913 | AF9: 2187 | AG9: 40000 | AH9: =(AG9-Z9*1000) -> 0 | AI9: =(AG9*AB9/1000) -> 22800 | AJ9: =(AE9+35) -> 41948 | AK9: =(AI9*0.05) -> 1140 | AP9: 3000 | AQ9: 41547 | AR9: 0
P10: =SUM(P5:P9) -> 82757.4 | R10: =SUM(R5:R9) -> 4137.87 | S10: PAGO | V10: BANDEJAS MAMÃO PAPAYA 4 UND | W10: 3 | X10: e-mail | Y10: 41914 | Z10: 40 | AA10: MIL | AB10: 570 | AD10: 41967 | AE10: 41969 | AF10: 2263 | AG10: 40000 | AH10: =(AG10-Z10*1000) -> 0 | AI10: =(AG10*AB10/1000) -> 22800 | AJ10: =(AE10+35) -> 42004 | AK10: =(AI10*0.05) -> 1140 | AN10: 41456 | AO10: 5559.2 | AP10: 2700 | AQ10: 17/10/2013 | AR10: -2859.2
AP11: 3500 | AQ11: 05/11/2013 | AR11: 640.8
B12: ABRIL 2014 | AN12: 41487 | AO12: 5249.16 | AP12: 640.8 | AQ12: 41583 | AR12: -4608.36
E13: OC | F13: DATA | I13: PREÇO | J13: CODIGO | K13: DATA | L13: DATA | Q13: DATA | R13: VALOR DA | AP13: 6000 | AQ13: 26/12/2013 | AR13: 1391.64
B14: CLIENTE | C14: PRODUTO | D14: PEDIDO | E14: DO | F14: DO | G14: QUANT | H14: UND | I14: POR | J14: DO | K14: DE | L14: DE | M14: N F | N14: QUANT | O14: SALDO | P14: VALOR | Q14: COMISSÃO | R14: COMISSÃO | S14: OBSERVAÇÃO | V14: AGC - VIDEPLAST | W14: VITOR (27) 99608-1521 ELIJOICE (27) 99754-4214 | AD14: somente mamão | AF14: (27) 3371-3138 | AH14: LIGAR JULHO | AN14: 41518 | AO14: 2876.79 | AP14: 1391.64 | AQ14: 26/12/2013 | AR14: -1485.15
E15: CLIENTE | F15: PEDIDO | I15: UND | J15: CLIENTE | K15: ENTREGA | L15: FATURA | Q15: 30 DD | R15: R$ | X15: OC | Y15: DATA | AB15: PREÇO | AC15: CODIGO | AD15: DATA | AE15: DATA | AJ15: DATA | AK15: VALOR DA | AP15: 2465.6 | AQ15: 21/02/2014 | AR15: 980.45
B16: DOCE MEL | C16: =IF(J16=1473,"BANDEJA PAPAYA PET - GF 15",IF(J16=0," ")) -> BANDEJA PAPAYA PET - GF 15 | D16: 13 | E16: 3133 | F16: 41712 | G16: 50 | H16: MIL | I16: 498 | J16: 1473 | K16: 41726 | L16: 41726 | M16: 2023 | N16: 50000 | O16: =(N16-G16*1000) -> 0 | P16: =(N16*I16/1000) -> 24900 | Q16: =(L16+30) -> 41756 | R16: =(P16*0.05) -> 1245 | V16: PRODUTO | W16: PEDIDO | X16: DO | Y16: DO | Z16: QUANT | AA16: UND | AB16: POR | AC16: DO | AD16: DE | AE16: DE | AF16: N F | AG16: QUANT | AH16: SALDO | AI16: VALOR | AJ16: COMISSÃO | AK16: COMISSÃO | AL16: OBSERVAÇÃO | AN16: 41548 | AO16: 2980.45 | AP16: 980.45 | AQ16: 41691 | AR16: -2000
B17: CALIMAN AGRICOLA | C17: BANDEJA TRANSP-04 CAV "OVO" | D17: 4 | E17: 005828/1 | F17: 41724 | G17: 25.2 | H17: MIL | I17: 470 | K17: 41726 | L17: =(K17) -> 41726 | M17: 2024 | N17: 25200 | O17: =(N17-G17*1000) -> 0 | P17: =(N17*I17/1000) -> 11844 | Q17: =(L17+28) -> 41754 | R17: =(P17*0.05) -> 592.2 | X17: CLIENTE | Y17: PEDIDO | AB17: UND | AC17: CLIENTE | AD17: ENTREGA | AE17: FATURA | AJ17: 35 DD | AK17: R$ | AP17: 2000 | AQ17: 07/03/2014 | AR17: 0
B18: DOCE MEL | C18: =IF(J18=1473,"BANDEJA PAPAYA PET - GF 15",IF(J18=0," ")) -> BANDEJA PAPAYA PET - GF 15 | D18: 14 | E18: 3134 | F18: 41712 | G18: 60 | H18: MIL | I18: 498 | J18: 1473 | K18: 41737 | L18: 41733 | M18: 2027 | N18: 60000 | O18: =(N18-G18*1000) -> 0 | P18: =(N18*I18/1000) -> 29880 | Q18: =(L18+30) -> 41763 | R18: =(P18*0.05) -> 1494 | AN18: 41579 | AO18: 0 | AP18: 0 | AR18: 0
B19: CALIMAN AGRICOLA | C19: BANDEJA TRANSP-04 CAV "OVO" | D19: 5 | E19: 005828/1 | F19: 41724 | G19: 25.2 | H19: MIL | I19: 470 | K19: 41733 | L19: 41740 | M19: 2031 | N19: 25200 | O19: =(N19-G19*1000) -> 0 | P19: =(N19*I19/1000) -> 11844 | Q19: =(L19+28) -> 41768 | R19: =(P19*0.05) -> 592.2 | V19: BANDEJAS MAMÃO PAPAYA 4 UND | W19: 1 | X19: e-mail | Y19: 41781 | Z19: 20 | AA19: MIL | AB19: 590 | AD19: 41800 | AE19: 41817 | AF19: 2083 | AG19: 21350 | AH19: =(AG19-Z19*1000) -> 1350 | AI19: =(AG19*AB19/1000) -> 12596.5 | AJ19: =(AE19+35) -> 41852 | AK19: =(AI19*0.05) -> 629.825 | AN19: 41609 | AO19: 2701.45 | AP19: 2701.45 | AQ19: 03/04/2014 | AR19: 0
B20: CASA SUIÇA | C20: BANDEJA RETANGULAR - JANDIRA | D20: 226 | E20: E-MAIL | F20: 41723 | G20: 100 | H20: MIL | I20: 60 | J20: 9124 | K20: 41745 | L20: 41745 | M20: 2036 | N20: 102000 | O20: =(N20-G20*1000) -> 2000 | P20: =(N20*I20/1000) -> 6120 | Q20: =(L20+35) -> 41780 | R20: =(P20*0.05) -> 306 | V20: BANDEJAS MAMÃO PAPAYA 4 UND | W20: 2 | X20: e-mail | Y20: 41893 | Z20: 40 | AA20: MIL | AB20: 570 | AD20: 41908 | AE20: 41913 | AF20: 2187 | AG20: 40000 | AH20: =(AG20-Z20*1000) -> 0 | AI20: =(AG20*AB20/1000) -> 22800 | AJ20: =(AE20+35) -> 41948 | AK20: =(AI20*0.05) -> 1140 | AN20: 41640 | AO20: 2689.47 | AP20: 2689.47 | AQ20: 41754 | AR20: 0
P21: =SUM(P16:P20) -> 84588 | R21: =(P21*0.05) -> 4229.4 | S21: PAGO | V21: BANDEJAS MAMÃO PAPAYA 4 UND | W21: 3 | X21: e-mail | Y21: 41914 | Z21: 40 | AA21: MIL | AB21: 570 | AD21: 41967 | AE21: 41969 | AF21: 2263 | AG21: 40000 | AH21: =(AG21-Z21*1000) -> 0 | AI21: =(AG21*AB21/1000) -> 22800 | AJ21: =(AE21+35) -> 42004 | AK21: =(AI21*0.05) -> 1140 | AN21: 41671 | AO21: 1738.8 | AP21: 1738.8 | AQ21: 08/05/2014 | AR21: 0
AN22: 41699 | AO22: 4137.87 | AP22: 2137.87 | AQ22: 23/05/2014 | AR22: -2000
B23: MAIO 2014 | AP23: 2000 | AQ23: 20/06/2014 | AR23: 0
E24: OC | F24: DATA | I24: PREÇO | J24: CODIGO | K24: DATA | L24: DATA | Q24: DATA | R24: VALOR DA | AN24: 41730 | AO24: 4229.4 | AP24: 2000 | AQ24: 41834 | AR24: -2229.4
B25: CLIENTE | C25: PRODUTO | D25: PEDIDO | E25: DO | F25: DO | G25: QUANT | H25: UND | I25: POR | J25: DO | K25: DE | L25: DE | M25: N F | N25: QUANT | O25: SALDO | P25: VALOR | Q25: COMISSÃO | R25: COMISSÃO | S25: OBSERVAÇÃO | AP25: 2229.4 | AQ25: 18/07/2014 | AR25: 0
E26: CLIENTE | F26: PEDIDO | I26: UND | J26: CLIENTE | K26: ENTREGA | L26: FATURA | Q26: 30 DD | R26: R$ | V26: AGRICOLA Q.DELICIA | W26: URBANO (81) 99946-3622 | Z26: (81) 3252-1132 | AC26: DA PAZ | AD26: CARINE | AE26: UVA MAMÃO | AG26: RENATA | AH26: ligar amanhã | AN26: 41760 | AO26: 3332.1 | AP26: 2000 | AQ26: 41859 | AR26: =(AP26-AO26) -> -1332.1
B27: CALIMAN AGRICOLA | C27: BANDEJA TRANSP-04 CAV "OVO" | D27: 6 | E27: 005828/1 | F27: 41724 | G27: 25.2 | H27: MIL | I27: 470 | K27: 41743 | L27: 41752 | M27: 2040 | N27: 25200 | O27: =(N27-G27*1000) -> 0 | P27: =(N27*I27/1000) -> 11844 | Q27: =(L27+28) -> 41780 | R27: =(P27*0.05) -> 592.2 | X27: OC | Y27: DATA | AB27: PREÇO | AC27: CODIGO | AD27: DATA | AE27: DATA | AJ27: DATA | AK27: VALOR DA | AP27: 1332.1 | AQ27: 27/08/2014 | AR27: 0
B28: FRUT MEL | C28: BAND BLIS MAMÃO PAPAYA 4 UND | D28: 2 | E28: E-MAIL | F28: 41737 | G28: 15 | H28: MIL | I28: 470 | K28: 41745 | L28: 41754 | M28: 2045 | N28: 15200 | O28: =(N28-G28*1000) -> 200 | P28: =(N28*I28/1000) -> 7144 | Q28: =(L28+28) -> 41782 | R28: =(P28*0.05) -> 357.2 | S28: BB R$ 178,60 08/08/2014 | V28: PRODUTO | W28: PEDIDO | X28: DO | Y28: DO | Z28: QUANT | AA28: UND | AB28: POR | AC28: DO | AD28: DE | AE28: DE | AF28: N F | AG28: QUANT | AH28: SALDO | AI28: VALOR | AJ28: COMISSÃO | AK28: COMISSÃO | AL28: OBSERVAÇÃO | AN28: 41791 | AO28: 4538.6 | AP28: 2000 | AQ28: 04/09/2014 | AR28: =(AP28-AO28) -> -2538.6
B29: CASA SUIÇA | C29: BANDEJA RETANGULAR - JANDIRA | D29: 227 | E29: E-MAIL | F29: 41723 | G29: 100 | H29: MIL | I29: 60 | J29: 9124 | K29: 41759 | L29: 41754 | M29: 2044 | N29: 99000 | O29: =(N29-G29*1000) -> -1000 | P29: =(N29*I29/1000) -> 5940 | Q29: =(L29+35) -> 41789 | R29: =(P29*0.05) -> 297 | X29: CLIENTE | Y29: PEDIDO | AB29: UND | AC29: CLIENTE | AD29: ENTREGA | AE29: FATURA | AJ29: 35 DD | AK29: R$ | AP29: 2358.6 | AQ29: 18/09/2014 | AR29: =(AP29+AR28) -> -180
B30: FRUTAS SOLO | C30: BANDEJA PAPAYA C/ 400 UND | D30: 2 | E30: 9724 | F30: 41754 | G30: 40 | H30: MIL | I30: 470 | J30: 8490 | K30: 41754 | L30: 41772 | M30: 2053 | N30: 40000 | O30: =(N30-G30*1000) -> 0 | P30: =(N30*I30/1000) -> 18800 | Q30: =(L30+35) -> 41807 | R30: =(P30*0.05) -> 940 | S30: BB R$ 470,00 08/08/2014 | AP30: 3000 | AQ30: 41927 | AR30: =(AP30+AR29) -> 2820
B31: CALIMAN AGRICOLA | C31: BANDEJA TRANSP-04 CAV "OVO" | D31: 9 | E31: 005828/1 | F31: 41724 | G31: 25.2 | H31: MIL | I31: 470 | K31: 41771 | L31: 41772 | M31: 2054 | N31: 25200 | O31: =(N31-G31*1000) -> 0 | P31: =(N31*I31/1000) -> 11844 | Q31: =(L31+35) -> 41807 | R31: =(P31*0.05) -> 592.2 | V31: BANDEJAS MAMÃO PAPAYA 4 UND | W31: 1 | X31: E-MAIL | Y31: 41824 | Z31: 10 | AA31: MIL | AB31: 470 | AD31: 41827 | AE31: 41827 | AF31: 2092 | AG31: 10000 | AH31: =(AG31-Z31*1000) -> 0 | AI31: =(AG31*AB31/1000) -> 4700 | AJ31: =(AE31+35) -> 41862 | AK31: =(AI31*0.05) -> 235 | AN31: 41821 | AO31: 4997.93 | AP31: 2820 | AQ31: 15/10/2014 | AR31: =(AP31-AO31) -> -2177.93
B32: CASA SUIÇA | C32: BANDEJA RETANGULAR - JANDIRA | D32: 228 | E32: E-MAIL | F32: 41723 | G32: 100 | H32: MIL | I32: 60 | J32: 9124 | K32: 41773 | L32: 41775 | M32: 2056 | N32: 102000 | O32: =(N32-G32*1000) -> 2000 | P32: =(N32*I32/1000) -> 6120 | Q32: =(L32+35) -> 41810 | R32: =(P32*0.05) -> 306 | S32: 21/05 20/06 | V32: BANDEJAS MAMÃO PAPAYA 4 UND | W32: 2 | X32: E-MAIL | Y32: 41971 | Z32: 5 | AA32: MIL | AB32: 470 | AD32: 41976 | AE32: 41977 | AF32: 2270 | AG32: 5200 | AH32: =(AG32-Z32*1000) -> 200 | AI32: =(AG32*AB32/1000) -> 2444 | AJ32: =(AE32+35) -> 42012 | AK32: =(AI32*0.05) -> 122.2 | AP32: 4044.9 | AQ32: 30/10/2014 | AR32: =(AP32+AR31) -> 1866.97
B33: CASA SUIÇA | C33: BERÇO AMANTEIGADOS | D33: 225 | E33: E-MAIL | F33: 41723 | G33: 25 | H33: MIL | I33: 198 | J33: 13822 | K33: 41773 | L33: 41761 | M33: 2049 | N33: 1000 | O33: =(N33-G33*1000) -> -24000 | P33: =(N33*I33/1000) -> 198 | Q33: =(L33+35) -> 41796 | R33: =(P33*0.05) -> 9.9 | V33: BANDEJAS MAMÃO PAPAYA 2 UND | W33: 3 | X33: E-MAIL | Y33: 41971 | Z33: 10 | AA33: MIL | AB33: 280 | AD33: 41976 | AE33: 41977 | AF33: 2270 | AG33: 10400 | AH33: =(AG33-Z33*1000) -> 400 | AI33: =(AG33*AB33/1000) -> 2912 | AJ33: =(AE33+35) -> 42012 | AK33: =(AI33*0.05) -> 145.6 | AN33: 41852 | AO33: 2584.4 | AP33: 2584.4 | AQ33: 03/10/2014 | AR33: =(AP33-AO33) -> 0
B34: CASA SUIÇA | C34: BERÇO AMANTEIGADOS | D34: 225 | E34: E-MAIL | F34: 41723 | G34: 24 | H34: MIL | I34: 198 | J34: 13822 | K34: 41773 | L34: 41775 | M34: 2056 | N34: 24000 | O34: =(N34-G34*1000) -> 0 | P34: =(N34*I34/1000) -> 4752 | Q34: =(L34+35) -> 41810 | R34: =(P34*0.05) -> 237.6 | V34: BANDEJAS MAMÃO PAPAYA 4 UND | W34: 4 | X34: E-MAIL | Y34: 42059 | Z34: 5 | AA34: MIL | AB34: 470 | AD34: 42061 | AE34: 42061 | AF34: 2358 | AG34: 5000 | AH34: =(AG34-Z34*1000) -> 0 | AI34: =(AG34*AB34/1000) -> 2350 | AJ34: =(AE34+35) -> 42096 | AK34: =(AI34*0.05) -> 117.5 | AN34: 41883 | AO34: 5896.64 | AP34: 1866.97 | AQ34: 30/10/2014 | AR34: =(AP34-AO34) -> -4029.67
P35: =SUM(P27:P34) -> 66642 | R35: =(P35*0.05) -> 3332.1 | S35: PAGO | V35: BANDEJAS MAMÃO PAPAYA 2 UND | W35: 5 | X35: E-MAIL | Y35: 42059 | Z35: 10 | AA35: MIL | AB35: 280 | AD35: 42061 | AE35: 42061 | AF35: 2358 | AG35: 10000 | AH35: =(AG35-Z35*1000) -> 0 | AI35: =(AG35*AB35/1000) -> 2800 | AJ35: =(AE35+35) -> 42096 | AK35: =(AI35*0.05) -> 140 | AP35: 3896.64 | AQ35: 18/11/2014 | AR35: =(AP35+AR34) -> -133.03
V36: BANDEJAS MAMÃO PAPAYA 2 UND | W36: 6 | X36: E-MAIL | Y36: 42173 | Z36: 3 | AA36: MIL | AB36: 280 | AD36: 42174 | AE36: 42179 | AF36: 2485 | AG36: 3000 | AH36: =(AG36-Z36*1000) -> 0 | AI36: =(AG36*AB36/1000) -> 840 | AJ36: =(AE36+35) -> 42214 | AK36: =(AI36*0.05) -> 42 | AP36: 2000 | AQ36: 41976 | AR36: =(AP36+AR35) -> 1866.97
B37: JUNHO 2014 | V37: BANDEJAS MAMÃO PAPAYA 4 UND | W37: 7 | X37: E-MAIL | Y37: 42173 | Z37: 3 | AA37: MIL | AB37: 470 | AD37: 42174 | AE37: 42179 | AF37: 2485 | AG37: 3200 | AH37: =(AG37-Z37*1000) -> 200 | AI37: =(AG37*AB37/1000) -> 1504 | AJ37: =(AE37+35) -> 42214 | AK37: =(AI37*0.05) -> 75.2 | AN37: 41913 | AO37: 9827.6 | AP37: 1866.97 | AQ37: 41976 | AR37: =(AP37-AO37) -> -7960.63
E38: OC | F38: DATA | I38: PREÇO | J38: CODIGO | K38: DATA | L38: DATA | Q38: DATA | R38: VALOR DA | V38: CUMBUCA 500G | W38: 8 | X38: E-MAIL | Y38: 42173 | Z38: 10 | AA38: MIL | AB38: 300 | AD38: 42174 | AE38: 42179 | AF38: 2485 | AG38: 10000 | AH38: =(AG38-Z38*1000) -> 0 | AI38: =(AG38*AB38/1000) -> 3000 | AJ38: =(AE38+35) -> 42214 | AK38: =(AI38*0.05) -> 150 | AP38: 3000 | AQ38: 12/12/2014 | AR38: =(AP38+AR37) -> -4960.63
B39: CLIENTE | C39: PRODUTO | D39: PEDIDO | E39: DO | F39: DO | G39: QUANT | H39: UND | I39: POR | J39: DO | K39: DE | L39: DE | M39: N F | N39: QUANT | O39: SALDO | P39: VALOR | Q39: COMISSÃO | R39: COMISSÃO | S39: OBSERVAÇÃO | V39: CUMBUCA 500G | W39: 10 | X39: E-MAIL | Y39: 42214 | Z39: 10 | AA39: MIL | AB39: 300 | AD39: 42215 | AE39: 42215 | AF39: 2520 | AG39: 10000 | AH39: =(AG39-Z39*1000) -> 0 | AI39: =(AG39*AB39/1000) -> 3000 | AJ39: =(AE39+35) -> 42250 | AK39: =(AI39*0.05) -> 150 | AP39: 2500 | AQ39: 05/01/2015 | AR39: =(AP39+AR38) -> -2460.63
E40: CLIENTE | F40: PEDIDO | I40: UND | J40: CLIENTE | K40: ENTREGA | L40: FATURA | Q40: 30 DD | R40: R$ | V40: BANDEJAS MAMÃO PAPAYA 4 UND | W40: 11 | X40: E-MAIL | Y40: 42173 | Z40: 3 | AA40: MIL | AB40: 470 | AD40: 42215 | AE40: 42215 | AF40: 2520 | AG40: 3200 | AH40: =(AG40-Z40*1000) -> 200 | AI40: =(AG40*AB40/1000) -> 1504 | AJ40: =(AE40+35) -> 42250 | AK40: =(AI40*0.05) -> 75.2 | AP40: 2327.6 | AQ40: 05/01/2015 | AR40: =(AP40+AR39) -> -133.03
B41: CALIMAN AGRICOLA | C41: BANDEJA TRANSP-04 CAV "OVO" | D41: 10 | E41: 005828/1 | F41: 41724 | G41: 25.2 | H41: MIL | I41: 470 | K41: 41778 | L41: 41781 | M41: 2058 | N41: 25200 | O41: =(N41-G31*1000) -> 0 | P41: =(N41*I31/1000) -> 11844 | Q41: =(L41+28) -> 41809 | R41: =(P41*0.05) -> 592.2 | V41: BANDEJAS MAMÃO PAPAYA 4 UND | W41: 12 | X41: E-MAIL | Y41: 42277 | Z41: 5 | AA41: MIL | AB41: 449.5 | AD41: 42279 | AE41: 42279 | AF41: 2569 | AG41: 5200 | AH41: =(AG41-Z41*1000) -> 200 | AI41: =(AG41*AB41/1000) -> 2337.4 | AJ41: =(AE41+35) -> 42314 | AK41: =(AI41*0.05) -> 116.87 | AP41: 289.97 | AQ41: 42009 | AR41: =(AP41+AR40) -> 156.94
B42: UGBP | C42: BAND BLIS MAMÃO PAPAYA 4 UND | D42: 1 | E42: E-MAIL | F42: 41746 | G42: 25 | H42: MIL | I42: 480 | K42: 41800 | L42: 41807 | M42: 2074 | N42: 25200 | O42: =(N42-G42*1000) -> 200 | P42: =(N42*I42/1000) -> 12096 | Q42: =(L42+28) -> 41835 | R42: =(P42*0.05) -> 604.8 | V42: CUMBUCA 500G | W42: 13 | X42: E-MAIL | Y42: 42277 | Z42: 5 | AA42: MIL | AB42: 300 | AD42: 42279 | AE42: 42279 | AF42: 2569 | AG42: 5000 | AH42: =(AG42-Z42*1000) -> 0 | AI42: =(AG42*AB42/1000) -> 1500 | AJ42: =(AE42+35) -> 42314 | AK42: =(AI42*0.05) -> 75 | AN42: 41944 | AO42: 12252.06 | AP42: 156.94 | AQ42: 05/01/2015 | AR42: =(AP42-AO42) -> -12095.12
B43: DOCE MEL | C43: =IF(J43=1473,"BANDEJA PAPAYA PET - GF 15",IF(J43=0," ")) -> BANDEJA PAPAYA PET - GF 15 | D43: 15 | E43: 4734 | F43: 41775 | G43: 60 | H43: MIL | I43: 498 | J43: 1473 | K43: 41800 | L43: =(K43) -> 41800 | M43: 2070 | N43: 60000 | O43: =(N43-G43*1000) -> 0 | P43: =(N43*I43/1000) -> 29880 | Q43: =(L43+30) -> 41830 | R43: =(P43*0.05) -> 1494 | V43: BANDEJAS MAMÃO PAPAYA 2 UND | W43: 14 | X43: E-MAIL | Y43: 42277 | Z43: 3 | AA43: MIL | AB43: 320 | AD43: 42279 | AE43: 42279 | AF43: 2569 | AG43: 3000 | AH43: =(AG43-Z43*1000) -> 0 | AI43: =(AG43*AB43/1000) -> 960 | AJ43: =(AE43+35) -> 42314 | AK43: =(AI43*0.05) -> 48 | AP43: 2972.4 | AQ43: 42009 | AR43: =(AP43+AR42) -> -9122.72
B44: FRUT MEL | C44: BAND BLIS MAMÃO PAPAYA 4 UND | D44: 3 | E44: E-MAIL | F44: 41788 | G44: 15 | H44: MIL | I44: 470 | K44: 41800 | L44: 41803 | M44: 2073 | N44: 15200 | O44: =(N44-G44*1000) -> 200 | P44: =(N44*I44/1000) -> 7144 | Q44: =(L44+28) -> 41831 | R44: =(P44*0.05) -> 357.2 | S44: BB R$ 178,00 10/09/2014 | V44: BANDEJAS MAMÃO PAPAYA 2 UND | W44: 15 | X44: E-MAIL | Y44: 42311 | Z44: 5 | AA44: MIL | AB44: 320 | AD44: 42314 | AE44: 42314 | AF44: 2598 | AG44: 5600 | AH44: =(AG44-Z44*1000) -> 600 | AI44: =(AG44*AB44/1000) -> 1792 | AJ44: =(AE44+35) -> 42349 | AK44: =(AI44*0.05) -> 89.6 | AP44: 4000 | AQ44: 42060 | AR44: =(AP44+AR43) -> -5122.72
B45: CALIMAN AGRICOLA | C45: BANDEJA TRANSP-04 CAV "OVO" | D45: 11 | E45: 005828/1 | F45: 41724 | G45: 25.2 | H45: MIL | I45: 470 | K45: 41785 | L45: 41796 | M45: 2069 | N45: 25200 | O45: =(N45-G45*1000) -> 0 | P45: =(N45*I45/1000) -> 11844 | Q45: =(L45+28) -> 41824 | R45: =(P45*0.05) -> 592.2 | V45: CUMBUCA 500G | W45: 16 | X45: E-MAIL | Y45: 42311 | Z45: 5 | AA45: MIL | AB45: 300 | AD45: 42314 | AE45: 42314 | AF45: 2598 | AG45: 5000 | AH45: =(AG45-Z45*1000) -> 0 | AI45: =(AG45*AB45/1000) -> 1500 | AJ45: =(AE45+35) -> 42349 | AK45: =(AI45*0.05) -> 75 | AP45: 5279.65 | AQ45: 42083 | AR45: =(AP45+AR44) -> 156.93
B46: CALIMAN AGRICOLA | C46: BANDEJA TRANSP-04 CAV "OVO" | D46: 12 | E46: 005828/1 | F46: 41724 | G46: 25.2 | H46: MIL | I46: 470 | K46: 41792 | L46: 41796 | M46: 2069 | N46: 25200 | O46: =(N46-G46*1000) -> 0 | P46: =(N46*I46/1000) -> 11844 | Q46: =(L46+28) -> 41824 | R46: =(P46*0.05) -> 592.2 | S46: 21/06 20/07 | V46: BANDEJAS MAMÃO PAPAYA 4 UND | W46: 17 | X46: E-MAIL | Y46: 42311 | Z46: 3 | AA46: MIL | AB46: 449.5 | AD46: 42314 | AE46: 42314 | AF46: 2598 | AG46: 3200 | AH46: =(AG46-Z46*1000) -> 200 | AI46: =(AG46*AB46/1000) -> 1438.4 | AJ46: =(AE46+35) -> 42349 | AK46: =(AI46*0.05) -> 71.92 | AN46: 41974 | AO46: 8375.4 | AP46: 156.93 | AQ46: 42083 | AR46: =(AP46-AO46) -> -8218.47
B47: CASA SUIÇA | C47: BANDEJA RETANGULAR - JANDIRA | D47: 229 | E47: E-MAIL | F47: 41723 | G47: 100 | H47: MIL | I47: 60 | J47: 9124 | K47: 41787 | L47: 41788 | M47: 2063 | N47: 102000 | O47: =(N47-G47*1000) -> 2000 | P47: =(N47*I47/1000) -> 6120 | Q47: =(L47+35) -> 41823 | R47: =(P47*0.05) -> 306 | AP47: 6149.9 | AQ47: 42094 | AR47: =(AP47+AR46) -> -2068.57
P48: =SUM(P41:P47) -> 90772 | R48: =SUM(R41:R47) -> 4538.6 | S48: PAGO | AP48: 3000 | AQ48: 42129 | AR48: =(AP48+AR47) -> 931.43
AN49: 42005 | AO49: 6149.9 | AP49: 931.43 | AQ49: 42129 | AR49: =(AP49-AO49) -> -5218.47
B50: JULHO 2014 | V50: ALLCAB FIOS E CABOS | W50: CAIO G. PAVANELLI (11) 2455-2011 | AP50: 3000 | AQ50: 42149 | AR50: =(AP50+AR49) -> -2218.47
E51: OC | F51: DATA | I51: PREÇO | J51: CODIGO | K51: DATA | L51: DATA | Q51: DATA | R51: VALOR DA | X51: OC | Y51: DATA | AB51: PREÇO | AC51: CODIGO | AD51: DATA | AE51: DATA | AJ51: DATA | AK51: VALOR DA | AP51: 960 | AQ51: 42170 | AR51: =(AP51+AR50) -> -1258.47
B52: CLIENTE | C52: PRODUTO | D52: PEDIDO | E52: DO | F52: DO | G52: QUANT | H52: UND | I52: POR | J52: DO | K52: DE | L52: DE | M52: N F | N52: QUANT | O52: SALDO | P52: VALOR | Q52: COMISSÃO | R52: COMISSÃO | S52: OBSERVAÇÃO | V52: PRODUTO | W52: PEDIDO | X52: DO | Y52: DO | Z52: QUANT | AA52: UND | AB52: POR | AC52: DO | AD52: DE | AE52: DE | AF52: N F | AG52: QUANT | AH52: SALDO | AI52: VALOR | AJ52: COMISSÃO | AK52: COMISSÃO | AL52: OBSERVAÇÃO | AP52: 3365.4 | AQ52: 42174 | AR52: =(AP52+AR51) -> 2106.93
E53: CLIENTE | F53: PEDIDO | I53: UND | J53: CLIENTE | K53: ENTREGA | L53: FATURA | Q53: 30 DD | R53: R$ | X53: CLIENTE | Y53: PEDIDO | AB53: UND | AC53: CLIENTE | AD53: ENTREGA | AE53: FATURA | AJ53: 35 DD | AK53: R$ | AN53: 42036 | AO53: 4727.2 | AP53: 2106.93 | AQ53: 42174 | AR53: =(AP53-AO53) -> -2620.27
B54: CALIMAN AGRICOLA | C54: BANDEJA TRANSP-04 CAV "OVO" | D54: 13 | E54: verbal | F54: 41814 | G54: 25.2 | H54: MIL | I54: 470 | K54: 41822 | L54: 41831 | M54: 2099 | N54: 25200 | O54: =(N54-G54*1000) -> 0 | P54: =(N54*I54/1000) -> 11844 | Q54: =(L54+28) -> 41859 | R54: =(P54*0.05) -> 592.2 | AP54: 2700 | AQ54: 42184 | AR54: =(AP54+AR53) -> 79.73
B55: CASASUIÇA | C55: BANDEJA RETANGULAR - JANDIRA | D55: 230 | E55: E-MAIL | F55: 41810 | G55: 100 | H55: MIL | I55: 60 | J55: 9124 | K55: 41824 | L55: 41823 | M55: 2087 | N55: 102000 | O55: =(N55-G55*1000) -> 2000 | P55: =(N55*I55/1000) -> 6120 | Q55: =(L55+35) -> 41858 | R55: =(P55*0.05) -> 306 | V55: FILME PVC EST. 60 MM X 40 MICRA | W55: 1 | X55: VERBAL | Y55: 42208 | Z55: 50 | AA55: KG | AB55: 9.5 | AD55: 42208 | AE55: 42208 | AF55: x | AG55: 55.4 | AH55: =(AG55-Z55) -> 5.4 | AI55: =(AG55*AB55) -> 526.3 | AJ55: =(AE55+28) -> 42236 | AK55: =(AI55*0.06) -> 31.578 | AN55: 42064 | AO55: 4105.29 | AP55: 79.73 | AQ55: 42184 | AR55: =(AP55-AO55) -> -4025.56
B56: CASASUIÇA | C56: BANDEJA RETANGULAR - JANDIRA | D56: 231 | E56: E-MAIL | F56: 41810 | G56: 100 | H56: MIL | I56: 60 | J56: 9124 | K56: 41831 | L56: =(K56) -> 41831 | M56: 2102 | N56: 99000 | O56: =(N56-G56*1000) -> -1000 | P56: =(N56*I56/1000) -> 5940 | Q56: =(L56+35) -> 41866 | R56: =(P56*0.05) -> 297 | V56: FILME PVC EST. 60 MM X 40 MICRA | W56: 2 | X56: VERBAL | Y56: 42213 | Z56: 200 | AA56: KG | AB56: 9.5 | AD56: 42219 | AE56: 42219 | AF56: x | AG56: 249.5 | AH56: =(AG56-Z56) -> 49.5 | AI56: =(AG56*AB56) -> 2370.25 | AJ56: =(AE56+28) -> 42247 | AK56: =(AI56*0.06) -> 142.215 | AP56: 3000 | AQ56: 42212 | AR56: =(AP56+AR55) -> -1025.56
B57: DOCE MEL | C57: =IF(J57=1473,"BANDEJA PAPAYA PET - GF 15",IF(J57=0," ")) -> BANDEJA PAPAYA PET - GF 15 | D57: 16 | E57: 4735 | F57: 41775 | G57: 60 | H57: MIL | I57: 498 | J57: 1473 | K57: 41828 | L57: 41824 | M57: 2089 | N57: 60000 | O57: =(N57-G57*1000) -> 0 | P57: =(N57*I57/1000) -> 29880 | Q57: =(L57+30) -> 41854 | R57: =(P57*0.05) -> 1494 | V57: FILME PVC EST. 60 MM X 40 MICRA | W57: 3 | X57: e-mail | Y57: 42270 | Z57: 300 | AA57: KG | AB57: 9.5 | AD57: 42275 | AE57: 42279 | AF57: x | AG57: 43.1 | AH57: =(AG57-Z57) -> -256.9 | AI57: =(AG57*AB57) -> 409.45 | AJ57: =(AE57+28) -> 42307 | AK57: =(AI57*0.06) -> 24.567 | AP57: 279 | AQ57: 42213 | AR57: =(AP57+AR56) -> -746.56
B58: NORTEFRUT | C58: BANDEJA PAPAYA PET 4 UND | D58: 1 | E58: E-MAIL | F58: 41821 | G58: 10 | H58: MIL | I58: 470 | K58: 41830 | L58: =(K58) -> 41830 | M58: 2097 | N58: 10000 | O58: =(N58-G58*1000) -> 0 | P58: =(N58*I58/1000) -> 4700 | Q58: =(L58+28) -> 41858 | R58: =(P58*0.05) -> 235 | S58: BB R$ 117,50 31/10/2014 | Z58: 256.9 | AA58: KG | AB58: 9.5 | AD58: 42275 | AE58: 42279 | AF58: x | AG58: 185.4 | AH58: =(AG58-Z58) -> -71.5 | AI58: =(AG58*AB58) -> 1761.3 | AJ58: =(AE58+28) -> 42307 | AK58: =(AI58*0.06) -> 105.678 | AP58: 5685.08 | AQ58: 42216 | AR58: =(AP58+AR57) -> 4938.52
B59: FRUTAS SOLO | C59: BANDEJA PAPAYA C/ 400 UND | D59: 3 | E59: 10288 | F59: 41803 | G59: 40 | H59: MIL | I59: 470 | J59: 8490 | K59: 41810 | L59: =(K59) -> 41810 | M59: 2080 | N59: 38000 | O59: =(N59-G59*1000) -> -2000 | P59: =(N59*I59/1000) -> 17860 | Q59: =(L59+35) -> 41845 | R59: =(P59*0.05) -> 893 | S59: BB R$ 446,50 31/10/2014 | Z59: 71.5 | AA59: KG | AB59: 9.5 | AD59: 42275 | AE59: 42279 | AF59: x | AG59: 137.9 | AH59: =(AG59-Z59) -> 66.4 | AI59: =(AG59*AB59) -> 1310.05 | AJ59: =(AE59+28) -> 42307 | AK59: =(AI59*0.06) -> 78.603 | AN59: 42095 | AO59: 6270.2 | AP59: 4938.52 | AQ59: 42216 | AR59: =(AP59-AO59) -> -1331.68
B60: DUCHACORONA | C60: MEGA BANHO | D60: 398 | E60: 137278 | F60: 41796 | G60: 0.9 | H60: MIL | I60: 4110 | J60: 1444 | K60: 41808 | L60: 41808 | M60: 2078 | N60: 1000 | O60: =(G60*1000-N60) -> -100 | P60: =(N60*I60/1000) -> 4110 | Q60: =(L60+42) -> 41850 | R60: =(P60*0.05) -> 205.5 | AP60: 2500 | AQ60: 42240 | AR60: =(AP60+AR59) -> 1168.32
B61: DUCHACORONA | C61: HANDCONTROL | D61: 399 | E61: 137278 | F61: 41796 | G61: 1.5 | H61: MIL | I61: 2110 | J61: 4003 | K61: 41808 | L61: 41808 | M61: 2078 | N61: 2300 | O61: =(G61*1000-N61) -> -800 | P61: =(N61*I61/1000) -> 4853 | Q61: =(L61+42) -> 41850 | R61: =(P61*0.05) -> 242.65 | AN61: 42125 | AO61: 4858.83 | AP61: 1168.32 | AQ61: 42240 | AR61: =(AP61-AO61) -> -3690.51
B62: AGC | C62: BANDEJAS MAMÃO PAPAYA 4 UND | D62: 1 | E62: e-mail | F62: 41781 | G62: 20 | H62: MIL | I62: 590 | K62: 41800 | L62: 41817 | M62: 2083 | N62: 21350 | O62: =(N62-G62*1000) -> 1350 | P62: =(N62*I62/1000) -> 12596.5 | Q62: =(L62+35) -> 41852 | R62: =(P62*0.05) -> 629.825 | S62: 21/07 20/08 | AP62: 3000 | AQ62: 42269 | AR62: =(AP62+AR61) -> -690.51
B63: DUCHACORONA | C63: MEGA BANHO | D63: 400 | E63: 138407 | F63: 41807 | G63: 0.5 | H63: MIL | I63: 4110 | J63: 1444 | K63: 41821 | L63: 41821 | M63: 2095 | N63: 500 | O63: =(G63*1000-N63) -> 0 | P63: =(N63*I63/1000) -> 2055 | Q63: =(L63+42) -> 41863 | R63: =(P63*0.05) -> 102.75 | V63: BELLO FRUIT | W63: LUCIANA COLODETTI GIACOMIN (73) 3605-4850 suprimentos@bellopapaya.com.br | AH63: amostra cumbuca e 2und | AP63: 3991.2 | AQ63: 42290 | AR63: =(AP63+AR62) -> 3300.69
P64: =SUM(P54:P63) -> 99958.5 | R64: =SUM(R54:R63) -> 4997.925 | S64: PAGO | X64: OC | Y64: DATA | AB64: PREÇO | AC64: CODIGO | AD64: DATA | AE64: DATA | AJ64: DATA | AK64: VALOR DA | AN64: 42156 | AO64: 5483.78 | AP64: 3300.69 | AQ64: 42290 | AR64: =(AP64-AO64) -> -2183.09
V65: PRODUTO | W65: PEDIDO | X65: DO | Y65: DO | Z65: QUANT | AA65: UND | AB65: POR | AC65: DO | AD65: DE | AE65: DE | AF65: N F | AG65: QUANT | AH65: SALDO | AI65: VALOR | AJ65: COMISSÃO | AK65: COMISSÃO | AL65: OBSERVAÇÃO | AP65: 4700 | AQ65: 42318 | AR65: =(AP65+AR64) -> 2516.91
B66: AGOSTO 2014 | X66: CLIENTE | Y66: PEDIDO | AB66: UND | AC66: CLIENTE | AD66: ENTREGA | AE66: FATURA | AJ66: 35 DD | AK66: R$ | AN66: 42186 | AO66: 4477.2 | AP66: 2516.91 | AQ66: 42318 | AR66: =(AP66-AO66) -> -1960.29
E67: OC | F67: DATA | I67: PREÇO | J67: CODIGO | K67: DATA | L67: DATA | Q67: DATA | R67: VALOR DA
B68: CLIENTE | C68: PRODUTO | D68: PEDIDO | E68: DO | F68: DO | G68: QUANT | H68: UND | I68: POR | J68: DO | K68: DE | L68: DE | M68: N F | N68: QUANT | O68: SALDO | P68: VALOR | Q68: COMISSÃO | R68: COMISSÃO | S68: OBSERVAÇÃO | V68: BANDEJA CLAIM SHELL PAPAYA 4 UND | W68: 1 | X68: E-MAIL | Y68: 41919 | Z68: 12 | AA68: MIL | AB68: 500 | AD68: 41925 | AE68: =(AD68) -> 41925 | AF68: 2200 | AG68: 12000 | AH68: =(AG68-Z68*1000) -> 0 | AI68: =(AG68*AB68/1000) -> 6000 | AJ68: =(AE68+35) -> 41960 | AK68: =(AI68*0.05) -> 300 | AN68: 42217 | AO68: 5822.55 | AR68: =(AP68-AO68) -> -5822.55
E69: CLIENTE | F69: PEDIDO | I69: UND | J69: CLIENTE | K69: ENTREGA | L69: FATURA | Q69: 30 DD | R69: R$ | V69: BANDEJA CLAIM SHELL PAPAYA 4 UND | W69: 2 | X69: E-MAIL | Y69: 41983 | Z69: 12 | AA69: MIL | AB69: 495 | AD69: 41983 | AE69: 41984 | AF69: 2282 | AG69: 12000 | AH69: =(AG69-Z69*1000) -> 0 | AI69: =(AG69*AB69/1000) -> 5940 | AJ69: =(AE69+35) -> 42019 | AK69: =(AI69*0.05) -> 297
V70: BANDEJA CLAIM SHELL PAPAYA 4 UND | W70: 3 | X70: skype | Y70: 42023 | Z70: 12 | AA70: MIL | AB70: 495 | AD70: 42026 | AE70: 42027 | AF70: 2319 | AG70: 12000 | AH70: =(AG70-Z70*1000) -> 0 | AI70: =(AG70*AB70/1000) -> 5940 | AJ70: =(AE70+35) -> 42062 | AK70: =(AI70*0.05) -> 297 | AN70: 42248 | AO70: 3674.25 | AR70: =(AP70-AO70) -> -3674.25
B71: DUCHACORONA | C71: MEGA BANHO | D71: 401 | E71: 139066 | F71: 41832 | G71: 0.5 | H71: MIL | I71: 4110 | J71: 1444 | K71: 41835 | L71: 41843 | M71: 2106 | N71: 500 | O71: =(G71*1000-N71) -> 0 | P71: =(N71*I71/1000) -> 2055 | Q71: =(L71+42) -> 41885 | R71: =(P71*0.05) -> 102.75 | S71: 21/08 20/09 | V71: BANDEJA CLAIM SHELL PAPAYA 4 UND | W71: 4 | X71: E-MAIL | Y71: 42074 | Z71: 12 | AA71: MIL | AB71: 495 | AD71: 42081 | AE71: 42080 | AF71: 2383 | AG71: 12000 | AH71: =(AG71-Z71*1000) -> 0 | AI71: =(AG71*AB71/1000) -> 5940 | AJ71: =(AE71+35) -> 42115 | AK71: =(AI71*0.05) -> 297
B72: DUCHACORONA | C72: MEGA BANHO | D72: 402 | E72: 139066 | F72: 41832 | G72: 0.5 | H72: MIL | I72: 4110 | J72: 1444 | K72: 41842 | L72: 41843 | M72: 2106 | N72: 500 | O72: =(G72*1000-N72) -> 0 | P72: =(N72*I72/1000) -> 2055 | Q72: =(L72+42) -> 41885 | R72: =(P72*0.05) -> 102.75 | V72: BANDEJA CLAIM SHELL PAPAYA 4 UND | W72: 5 | X72: E-MAIL | Y72: 42110 | Z72: 12 | AA72: MIL | AB72: 495 | AD72: 42117 | AE72: 42118 | AF72: 2428 | AG72: 12000 | AH72: =(AG72-Z72*1000) -> 0 | AI72: =(AG72*AB72/1000) -> 5940 | AJ72: =(AE72+35) -> 42153 | AK72: =(AI72*0.05) -> 297 | AN72: 42278 | AO72: 5556.87 | AR72: =(AP72-AO72) -> -5556.87
B73: CASASUIÇA | C73: BANDEJA RETANGULAR - JANDIRA | D73: 232 | E73: E-MAIL | F73: 41810 | G73: 100 | H73: MIL | I73: 60 | J73: 9124 | K73: 41845 | L73: =(K73) -> 41845 | M73: 2109 | N73: 102000 | O73: =(N73-G73*1000) -> 2000 | P73: =(N73*I73/1000) -> 6120 | Q73: =(L73+35) -> 41880 | R73: =(P73*0.05) -> 306 | V73: BANDEJA CLAIM SHELL PAPAYA 4 UND | W73: 6 | X73: SKIPE | Y73: 42170 | Z73: 12 | AA73: MIL | AB73: 495 | AD73: 42171 | AE73: 42171 | AF73: 2475 | AG73: 12000 | AH73: =(AG73-Z73*1000) -> 0 | AI73: =(AG73*AB73/1000) -> 5940 | AJ73: =(AE73+35) -> 42206 | AK73: =(AI73*0.05) -> 297
B74: CASA SUIÇA | C74: BANDEJA RETANGULAR - JANDIRA | D74: 233 | E74: E-MAIL | F74: 41810 | G74: 100 | H74: MIL | I74: 60 | J74: 9124 | K74: 41852 | L74: 41858 | M74: 2116 | N74: 99000 | O74: =(N74-G74*1000) -> -1000 | P74: =(N74*I74/1000) -> 5940 | Q74: =(L74+35) -> 41893 | R74: =(P74*0.05) -> 297 | V74: BANDEJA CLAIM SHELL PAPAYA 4 UND | W74: 7 | X74: SKIPE | Y74: 42338 | Z74: 20 | AA74: MIL | AB74: 449.5 | AD74: 42346 | AE74: 42346 | AG74: 20000 | AH74: =(AG74-Z74*1000) -> 0 | AI74: =(AG74*AB74/1000) -> 8990 | AJ74: =(AE74+35) -> 42381 | AK74: =(AI74*0.05) -> 449.5 | AN74: 42309 | AO74: 4016.12 | AR74: =(AP74-AO74) -> -4016.12
B75: CASA SUIÇA | C75: BANDEJA REDONDA - JANDIRA | D75: 234 | E75: E-MAIL | F75: 41810 | G75: 100 | H75: MIL | I75: 110 | K75: 41852 | L75: 41858 | M75: 2116 | N75: 99000 | O75: =(N75-G75*1000) -> -1000 | P75: =(N75*I75/1000) -> 10890 | Q75: =(L75+35) -> 41893 | R75: =(P75*0.05) -> 544.5
B76: CALIMAN | C76: BANDEJA TRANSP-04 CAV "OVO" | D76: 14 | E76: 005828/1 | F76: 41724 | G76: 25.2 | H76: MIL | I76: 470 | K76: 41859 | L76: 41865 | M76: 2123 | N76: 25200 | O76: =(N76-G76*1000) -> 0 | P76: =(N76*I76/1000) -> 11844 | Q76: =(L76+28) -> 41893 | R76: =(P76*0.05) -> 592.2 | V76: BENASSI CAMPINAS (SP) | W76: BOM BLISTER | Z76: MARCELO/WILLIAN | AD76: CAMILA ARAUJO (19) 3037-5526 | AN76: 42339 | AO76: 3870 | AR76: =(AP76-AO76) -> -3870
B77: FRUT MEL | C77: BAND BLIS MAMÃO PAPAYA 4 UND | D77: 4 | E77: E-MAIL | F77: 41844 | G77: 15 | H77: MIL | I77: 470 | K77: 41850 | L77: 41859 | M77: 2119 | N77: 15200 | O77: =(N77-G77*1000) -> 200 | P77: =(N77*I77/1000) -> 7144 | Q77: =(L77+28) -> 41887 | R77: =(P77*0.05) -> 357.2 | S77: BB R$ 178,60 22/10/2014 | X77: OC | Y77: DATA | AB77: PREÇO | AC77: CODIGO | AD77: DATA | AE77: DATA | AJ77: DATA | AK77: VALOR DA
B78: AGRICOLA QDELICIA | C78: BANDEJAS MAMÃO PAPAYA 4 UND | D78: 1 | E78: E-MAIL | F78: 41824 | G78: 10 | H78: MIL | I78: 470 | K78: 41827 | L78: 41827 | M78: 2092 | N78: 10000 | O78: =(N78-G78*1000) -> 0 | P78: =(N78*I78/1000) -> 4700 | Q78: =(L78+35) -> 41862 | R78: =(P78*0.05) -> 235 | V78: PRODUTO | W78: PEDIDO | X78: DO | Y78: DO | Z78: QUANT | AA78: UND | AB78: POR | AC78: DO | AD78: DE | AE78: DE | AF78: N F | AG78: QUANT | AH78: SALDO | AI78: VALOR | AJ78: COMISSÃO | AK78: COMISSÃO | AL78: OBSERVAÇÃO
B79: H SHIMIZU | C79: BANDEJA PAPAYA - 4 UND | D79: 1 | E79: VERBAL | F79: 41893 | G79: 4 | H79: MIL | I79: 470 | K79: 41894 | L79: =(K79) -> 41894 | M79: 2161 | N79: 4000 | O79: =(N79-G79*1000) -> 0 | P79: =(N79*I79/1000) -> 1880 | Q79: =(L79+28) -> 41922 | R79: =(P79*0.05) -> 94 | S79: BB R$ 47,00 22/10/2014 | X79: CLIENTE | Y79: PEDIDO | AB79: UND | AC79: CLIENTE | AD79: ENTREGA | AE79: FATURA | AJ79: 35 DD | AK79: R$
P80: =SUM(P70:P79) -> 52628 | R80: =(P80*0.05) -> 2631.4 | S80: PAGO
V81: BLISTER CUMBUCA 500 G | W81: 1 | X81: E-MAIL | Y81: 42092 | Z81: 32.85 | AA81: MIL | AB81: 196 | AD81: 42093 | AE81: 42095 | AF81: 2399 | AG81: 32850 | AH81: =(AG81-Z81*1000) -> 0 | AI81: =(AG81*AB81/1000) -> 6438.6 | AJ81: =(AE81+35) -> 42130 | AK81: =(AI81*0.05) -> 321.93
B82: SETEMBRO 2014
E83: OC | F83: DATA | I83: PREÇO | J83: CODIGO | K83: DATA | L83: DATA | Q83: DATA | R83: VALOR DA
B84: CLIENTE | C84: PRODUTO | D84: PEDIDO | E84: DO | F84: DO | G84: QUANT | H84: UND | I84: POR | J84: DO | K84: DE | L84: DE | M84: N F | N84: QUANT | O84: SALDO | P84: VALOR | Q84: COMISSÃO | R84: COMISSÃO | S84: OBSERVAÇÃO
E85: CLIENTE | F85: PEDIDO | I85: UND | J85: CLIENTE | K85: ENTREGA | L85: FATURA | Q85: 30 DD | R85: R$
B86: CASA SUIÇA | C86: BANDEJA REDONDA - JANDIRA | D86: 235 | E86: E-MAIL | F86: 41841 | G86: 200 | H86: MIL | I86: 110 | K86: 41881 | L86: 41869 | M86: 2125 | N86: 99000 | O86: =(N86-G86*1000) -> -101000 | P86: =(N86*I86/1000) -> 10890 | Q86: =(L86+35) -> 41904 | R86: =(P86*0.05) -> 544.5 | S86: 21/09 20/10
B87: CASA SUIÇA | G87: 101 | H87: MIL | I87: 110 | K87: 41881 | L87: 41876 | M87: 2134 | N87: 100500 | O87: =(N87-G87*1000) -> -500 | P87: =(N87*I87/1000) -> 11055 | Q87: =(L87+35) -> 41911 | R87: =(P87*0.05) -> 552.75 | S87: 15/08 a 14/09
B88: CASA SUIÇA | C88: BANDEJA RETANGULAR - JANDIRA | D88: 238 | E88: E-MAIL | F88: 41841 | G88: 100 | H88: MIL | I88: 60 | J88: 9124 | K88: 41881 | L88: 41876 | M88: 2134 | N88: 45000 | O88: =(N88-G88*1000) -> -55000 | P88: =(N88*I88/1000) -> 2700 | Q88: =(L88+35) -> 41911 | R88: =(P88*0.05) -> 135
B89: CASA SUIÇA | G89: 55 | H89: MIL | I89: 60 | J89: 9124 | K89: 41881 | L89: 41879 | M89: 2139 | N89: 60000 | O89: =(N89-G89*1000) -> 5000 | P89: =(N89*I89/1000) -> 3600 | Q89: =(L89+35) -> 41914 | R89: =(P89*0.05) -> 180 | V89: BENASSI CAMPINAS (SP) | W89: PAULISTA PACKING | AD89: CAMILA ARAUJO (19) 3037-5526
B90: CASA SUIÇA | C90: BANDEJA RETANGULAR - JANDIRA | D90: 239 | E90: E-MAIL | F90: 41841 | G90: 200 | H90: MIL | I90: 60 | J90: 9124 | K90: 41891 | L90: 41886 | M90: 2153 | N90: 198000 | O90: =(N90-G90*1000) -> -2000 | P90: =(N90*I90/1000) -> 11880 | Q90: =(L90+35) -> 41921 | R90: =(P90*0.05) -> 594 | X90: OC | Y90: DATA | AB90: PREÇO | AC90: CODIGO | AD90: DATA | AE90: DATA | AJ90: DATA | AK90: VALOR DA
B91: CALIMAN | C91: BANDEJA TRANSP-04 CAV "OVO" | D91: 15 | E91: 005828/1 | F91: 41724 | G91: 25.2 | H91: MIL | I91: 470 | K91: 41876 | L91: 41875 | M91: 2124 | N91: 25200 | O91: =(N91-G91*1000) -> 0 | P91: =(N91*I91/1000) -> 11844 | Q91: =(L91+28) -> 41903 | R91: =(P91*0.05) -> 592.2 | V91: PRODUTO | W91: PEDIDO | X91: DO | Y91: DO | Z91: QUANT | AA91: UND | AB91: POR | AC91: DO | AD91: DE | AE91: DE | AF91: N F | AG91: QUANT | AH91: SALDO | AI91: VALOR | AJ91: COMISSÃO | AK91: COMISSÃO | AL91: OBSERVAÇÃO
B92: FRUTAS SOLO | C92: BANDEJA PAPAYA C/ 400 UND | D92: 4 | E92: e-mail | F92: 41864 | G92: 40 | H92: MIL | I92: 470 | J92: 8490 | K92: 41871 | L92: 41886 | M92: 2152 | N92: 40000 | O92: =(N92-G92*1000) -> 0 | P92: =(N92*I92/1000) -> 18800 | Q92: =(L92+35) -> 41921 | R92: =(P92*0.05) -> 940 | S92: BB R$ 470,00 03/12/2014 | X92: CLIENTE | Y92: PEDIDO | AB92: UND | AC92: CLIENTE | AD92: ENTREGA | AE92: FATURA | AJ92: 35 DD | AK92: R$
B93: CASA SUIÇA | C93: BANDEJAS BOLO COBERTO/ZERO | D93: 241 | E93: E-MAIL | F93: 41866 | G93: 100 | H93: MIL | I93: 60 | K93: 41887 | L93: 41886 | M93: 2153 | N93: 102000 | O93: =(N93-G93*1000) -> 2000 | P93: =(N93*I93/1000) -> 6120 | Q93: =(L93+35) -> 41921 | R93: =(P93*0.05) -> 306
B94: FRUT MEL | C94: BAND BLIS MAMÃO PAPAYA 4 UND | D94: 5 | E94: E-MAIL | F94: 41877 | G94: 15 | H94: MIL | I94: 470 | K94: 41879 | L94: 41884 | M94: 2149 | N94: 15200 | O94: =(N94-G94*1000) -> 200 | P94: =(N94*I94/1000) -> 7144 | Q94: =(L94+28) -> 41912 | R94: =(P94*0.05) -> 357.2 | S94: BB R$ 178,60 01/12/2014 | V94: FILME PVC GA 380 MM X 10 MICRA | W94: 1 | X94: E-MAIL | Y94: 42292 | Z94: 200 | AA94: KG | AB94: 10.8 | AD94: 42296 | AE94: 42296 | AG94: 46 | AH94: =(AG94-Z94) -> -154 | AI94: =(AG94*AB94) -> 496.8 | AJ94: =(AE94+28) -> 42324 | AK94: =(AI94*0.06) -> 29.808
B95: FRUTAS LIDER | C95: BANDEJA PAPAYA C/ 400 UND | D95: 1 | E95: E-MAIL | F95: 41864 | G95: 20 | H95: MIL | I95: 570 | K95: 41865 | L95: 41871 | M95: 2128 | N95: 20000 | O95: =(N95-G95*1000) -> 0 | P95: =(N95*I95/1000) -> 11400 | Q95: =(L95+35) -> 41906 | R95: =(P95*0.05) -> 570 | Z95: 200 | AA95: KG | AB95: 10.8 | AD95: 42296 | AE95: 42296 | AG95: 178.4 | AH95: =(AG95-Z95) -> -21.6 | AI95: =(AG95*AB95) -> 1926.72 | AJ95: =(AE95+28) -> 42324 | AK95: =(AI95*0.06) -> 115.6032
B96: NORTEFRUT | C96: BANDEJA PAPAYA PET 4 UND | D96: 2 | E96: E-MAIL | F96: 41879 | G96: 12 | H96: MIL | I96: 470 | K96: 41885 | L96: 41894 | M96: 2159 | N96: 12000 | O96: =(N96-G96*1000) -> 0 | P96: =(N96*I96/1000) -> 5640 | Q96: =(L96+28) -> 41922 | R96: =(P96*0.05) -> 282 | S96: BB R$ 141,00 01/12/2014 | Z96: 33.4 | AA96: KG | AB96: 10.8 | AD96: 42296 | AE96: 42304 | AG96: 33.4 | AH96: =(AG96-Z96) -> 0 | AI96: =(AG96*AB96) -> 360.72 | AJ96: =(AE96+28) -> 42332 | AK96: =(AI96*0.06) -> 21.6432
B97: TERRA | C97: BANDEJA CUMBUCA UVA 500 G | D97: 1 | E97: E-MAIL | F97: 41879 | G97: 5 | H97: MIL | I97: 250 | K97: 41885 | L97: =(K97) -> 41885 | M97: 2155 | N97: 5000 | O97: =(N97-G97*1000) -> 0 | P97: =(N97*I97/1000) -> 1250 | Q97: =(L97+28) -> 41913 | R97: =(P97*0.05) -> 62.5 | S97: BB R$ 31,25 01/12/2014 | V97: FILME PVC GA 380 MM X 10 MICRA | W97: 2 | X97: verbal | Y97: 42304 | Z97: 400 | AA97: KG | AB97: 10.8 | AD97: 42311 | AE97: 42319 | AG97: 395.9 | AH97: =(AG97-Z97) -> -4.1 | AI97: =(AG97*AB97) -> 4275.72 | AJ97: =(AE97+28) -> 42347 | AK97: =(AI97*0.06) -> 256.5432
B98: H SHIMIZU | C98: BANDEJA AVOCADO - 4 UND | D98: 2 | E98: E-MAIL | F98: 41838 | G98: 4 | H98: MIL | I98: 389 | K98: 41848 | L98: 41878 | M98: 2136 | N98: 4200 | O98: =(N98-G98*1000) -> 200 | P98: =(N98*I98/1000) -> 1633.8 | Q98: =(L98+28) -> 41906 | R98: =(P98*0.05) -> 81.69 | S98: BB R$ 40,84 01/12/2014
B99: UGBP | C99: BAND BLIS MAMÃO PAPAYA 4 UND | D99: 2 | E99: E-MAIL | F99: 41856 | G99: 25 | H99: MIL | I99: 480 | K99: 41871 | L99: 41878 | M99: 2137 | N99: 25200 | O99: =(N99-G99*1000) -> 200 | P99: =(N99*I99/1000) -> 12096 | Q99: =(L99+28) -> 41906 | R99: =(P99*0.05) -> 604.8
B100: H SHIMIZU | C100: BANDEJA PAPAYA - 4 UND | D100: 4 | E100: VERBAL | F100: 41893 | G100: 4 | H100: MIL | I100: 470 | K100: 41894 | L100: =(K100) -> 41894 | M100: 2161 | N100: 4000 | O100: =(N100-G100*1000) -> 0 | P100: =(N100*I100/1000) -> 1880 | Q100: =(L100+28) -> 41922 | R100: =(P100*0.05) -> 94 | S100: BB R$ 47,00 03/12/2014
...

Sheet 2017
B3: JANEIRO 2016 | Y3: ermerlando 27 997544214 | AC3: ALTENIS (27) 99984-3055 | AF3: JUNIOR
E4: OC | F4: DATA | I4: PREÇO | J4: CODIGO | K4: DATA | L4: DATA | Q4: DATA | R4: VALOR DA | V4: AGC | W4: VITOR (27) 99608-1521 ELIJOICE (27) 99713-8956 | AD4: somente mamão | AF4: (27) 3371-3138 | AH4: 27 99754-4214 JUNIOR/JOÃO PAULO | AN4: MÊS | AO4: COMISSÃO | AP4: PAGAMENTO | AQ4: DATA | AR4: SALDO
B5: CLIENTE | C5: PRODUTO | D5: PEDIDO | E5: DO | F5: DO | G5: QUANT | H5: UND | I5: POR | J5: DO | K5: DE | L5: DE | M5: N F | N5: QUANT | O5: SALDO | P5: VALOR | Q5: COMISSÃO | R5: COMISSÃO | S5: OBSERVAÇÃO | X5: OC | Y5: DATA | AB5: PREÇO | AC5: CODIGO | AD5: DATA | AE5: DATA | AJ5: DATA | AK5: VALOR DA | AN5: 41334 | AO5: 5402.32 | AP5: 5402.32 | AQ5: 06/06/2013 | AR5: =(AP5-AO5) -> 0
E6: CLIENTE | F6: PEDIDO | I6: UND | J6: CLIENTE | K6: ENTREGA | L6: FATURA | Q6: 30 DD | R6: R$ | V6: PRODUTO | W6: PEDIDO | X6: DO | Y6: DO | Z6: QUANT | AA6: UND | AB6: POR | AC6: DO | AD6: DE | AE6: DE | AF6: N F | AG6: QUANT | AH6: SALDO | AI6: VALOR | AJ6: COMISSÃO | AK6: COMISSÃO | AL6: OBSERVAÇÃO | AN6: 41365 | AO6: 6542.42 | AP6: 6542.42 | AQ6: 27/06/2013 | AR6: =(AP6-AO6) -> 0
B7: DOCE MEL | C7: =IF(J7=1473,"BANDEJA PAPAYA PET - GF 15",IF(J7=0," ")) -> BANDEJA PAPAYA PET - GF 15 | D7: 29 | E7: 20387 | F7: 42332 | G7: 50 | H7: MIL | I7: 449.5 | J7: 1473 | K7: 42335 | L7: 42339 | M7: 2618 | N7: 50000 | O7: =(N7-G7*1000) -> 0 | P7: =(N7*I7/1000) -> 22475 | Q7: =(L7+30) -> 42369 | R7: =(P7*0.05) -> 1123.75 | X7: CLIENTE | Y7: PEDIDO | AB7: UND | AC7: CLIENTE | AD7: ENTREGA | AE7: FATURA | AJ7: 35 DD | AK7: R$ | AN7: 41395 | AO7: 6284.78 | AP7: 4500 | AQ7: 01/08/2013 | AR7: =(AP7-AO7) -> -1784.78
B8: DOCE MEL | C8: =IF(J8=1473,"BANDEJA PAPAYA PET - GF 15",IF(J8=0," ")) -> BANDEJA PAPAYA PET - GF 15 | D8: 30 | E8: 20387 | F8: 42332 | G8: 40 | H8: MIL | I8: 449.5 | J8: 1473 | K8: 42365 | L8: 42359 | M8: 2637 | N8: 40000 | O8: =(N8-G8*1000) -> 0 | P8: =(N8*I8/1000) -> 17980 | Q8: =(L8+30) -> 42389 | R8: =(P8*0.05) -> 899 | AP8: 1784.78 | AQ8: 09/08/2013 | AR8: 0
B9: FRUTAS SOLO | C9: BANDEJA PAPAYA C/ 400 UND | D9: 12 | E9: e-mail | F9: 42337 | G9: 40 | H9: MIL | I9: 449.5 | J9: 8490 | K9: 42341 | L9: 42348 | M9: 2627 | N9: 40000 | O9: =(N9-G9*1000) -> 0 | P9: =(N9*I9/1000) -> 17980 | Q9: =(L9+35) -> 42383 | R9: =(P9*0.05) -> 899 | AN9: 41426 | AO9: 6461.29 | AP9: 3461.29 | AQ9: 30/08/2013 | AR9: -3000
B10: BELLO FRUIT | C10: BANDEJA CLAIM SHELL PAPAYA 4 UND | D10: 7 | E10: SKIPE | F10: 42338 | G10: 20 | H10: MIL | I10: 449.5 | K10: 42346 | L10: 42342 | M10: 2623 | N10: 20000 | O10: =(N10-G10*1000) -> 0 | P10: =(N10*I10/1000) -> 8990 | Q10: =(L10+35) -> 42377 | R10: =(P10*0.05) -> 449.5 | AP10: 3000 | AQ10: 41547 | AR10: 0
B11: Q'DELICIA | C11: BANDEJAS MAMÃO PAPAYA 4 UND | D11: 18 | E11: E-MAIL | F11: 42342 | G11: 3 | H11: MIL | I11: 449.5 | K11: 42346 | L11: 42347 | M11: 2626 | N11: 3200 | O11: =(N11-G11*1000) -> 200 | P11: =(N11*I11/1000) -> 1438.4 | Q11: =(L11+35) -> 42382 | R11: =(P11*0.05) -> 71.92 | AN11: 41456 | AO11: 5559.2 | AP11: 2700 | AQ11: 17/10/2013 | AR11: -2859.2
B12: Q'DELICIA | C12: CUMBUCA 500 G 35 | D12: 19 | E12: E-MAIL | F12: 42342 | G12: 5 | H12: MIL | I12: 300 | K12: 42346 | L12: 42347 | M12: 2626 | N12: 5000 | O12: =(N12-G12*1000) -> 0 | P12: =(N12*I12/1000) -> 1500 | Q12: =(L12+35) -> 42382 | R12: =(P12*0.05) -> 75 | AP12: 3500 | AQ12: 05/11/2013 | AR12: 640.8
B13: Q'DELICIA | C13: BANDEJAS MAMÃO PAPAYA 2 UND | D13: 20 | E13: E-MAIL | F13: 42342 | G13: 5 | H13: MIL | I13: 320 | K13: 42346 | L13: 42347 | M13: 2626 | N13: 5600 | O13: =(N13-G13*1000) -> 600 | P13: =(N13*I13/1000) -> 1792 | Q13: =(L13+35) -> 42382 | R13: =(P13*0.05) -> 89.6 | AN13: 41487 | AO13: 5249.16 | AP13: 640.8 | AQ13: 41583 | AR13: -4608.36
B14: DE MARCHI | C14: CUMBUCA 500 - G 35 | D14: 1 | E14: VERBAL | F14: 42348 | G14: 10 | H14: MIL | I14: 300 | K14: 42353 | L14: 42353 | M14: 2632 | N14: 10350 | O14: =(N14-G14*1000) -> 350 | P14: =(N14*I14/1000) -> 3105 | Q14: =(L14+30) -> 42383 | R14: =(P14*0.05) -> 155.25 | AP14: 6000 | AQ14: 26/12/2013 | AR14: 1391.64
B15: NORTE FRUIT | C15: BANDEJA PAPAYA PET 2 UND | D15: 44 | E15: e-mail | F15: 42332 | G15: 10 | H15: MIL | I15: 300 | K15: 42335 | L15: 42349 | M15: 2628 | N15: 10000 | O15: =(N15-G15*1000) -> 0 | P15: =(N15*I15/1000) -> 3000 | Q15: =(L15+28) -> 42377 | R15: =(P15*0.05) -> 150 | V15: AGRICOLA Q.DELICIA - SERRAPLAST | W15: URBANO (81) 99946-3622 | Z15: (81) 3252-1132 | AC15: DA PAZ | AD15: CARINE | AE15: UVA MAMÃO | AG15: RENATA | AN15: 41518 | AO15: 2876.79 | AP15: 1391.64 | AQ15: 26/12/2013 | AR15: -1485.15
B16: NORTE FRUIT | C16: BANDEJA PAPAYA PET 4 UND | D16: 45 | E16: e-mail | F16: 42332 | G16: 10 | H16: MIL | I16: 449.5 | K16: 42335 | L16: 42349 | M16: 2628 | N16: 10000 | O16: =(N16-G16*1000) -> 0 | P16: =(N16*I16/1000) -> 4495 | Q16: =(L16+28) -> 42377 | R16: =(P16*0.05) -> 224.75 | X16: OC | Y16: DATA | AB16: PREÇO | AC16: CODIGO | AD16: DATA | AE16: DATA | AJ16: DATA | AK16: VALOR DA | AP16: 2465.6 | AQ16: 21/02/2014 | AR16: 980.45
B17: CASA DA UVA | C17: CUMBUCA 500 - G 35 | D17: 5 | E17: E-MAIL | F17: 42342 | G17: 12 | H17: MIL | I17: 300 | K17: 42346 | L17: 42349 | M17: 2629 | N17: 12000 | O17: =(N17-G17*1000) -> 0 | P17: =(N17*I17/1000) -> 3600 | Q17: =(L17+35) -> 42384 | R17: =(P17*0.05) -> 180 | V17: PRODUTO | W17: PEDIDO | X17: DO | Y17: DO | Z17: QUANT | AA17: UND | AB17: POR | AC17: DO | AD17: DE | AE17: DE | AF17: N F | AG17: QUANT | AH17: SALDO | AI17: VALOR | AJ17: COMISSÃO | AK17: COMISSÃO | AL17: OBSERVAÇÃO | AN17: 41548 | AO17: 2980.45 | AP17: 980.45 | AQ17: 41691 | AR17: -2000
X18: CLIENTE | Y18: PEDIDO | AB18: UND | AC18: CLIENTE | AD18: ENTREGA | AE18: FATURA | AJ18: 35 DD | AK18: R$ | AP18: 2000 | AQ18: 07/03/2014 | AR18: 0
P19: =SUM(P7:P18) -> 86355.4 | R19: =(P19*0.05) -> 4317.77 | S19: OK | AN19: 41579 | AO19: 0 | AP19: 0 | AR19: 0
V20: CUMBUCA 500 - MA 15 | W20: 1 | X20: E-MAIL | Y20: 42672 | Z20: 5 | AA20: MIL | AB20: 305 | AD20: 42683 | AE20: 42674 | AF20: 1462 | AG20: 5000 | AH20: =(AG20-Z20*1000) -> 0 | AI20: =(AG20*AB20/1000) -> 1525 | AJ20: =(AE20+35) -> 42709 | AK20: =(AI20*0.05) -> 76.25 | AN20: 41609 | AO20: 2701.45 | AP20: 2701.45 | AQ20: 03/04/2014 | AR20: 0
B21: FEVEREIRO 2016 | AN21: 41640 | AO21: 2689.47 | AP21: 2689.47 | AQ21: 41754 | AR21: 0
E22: OC | F22: DATA | I22: PREÇO | J22: CODIGO | K22: DATA | L22: DATA | Q22: DATA | R22: VALOR DA | AN22: 41671 | AO22: 1738.8 | AP22: 1738.8 | AQ22: 08/05/2014 | AR22: 0
B23: CLIENTE | C23: PRODUTO | D23: PEDIDO | E23: DO | F23: DO | G23: QUANT | H23: UND | I23: POR | J23: DO | K23: DE | L23: DE | M23: N F | N23: QUANT | O23: SALDO | P23: VALOR | Q23: COMISSÃO | R23: COMISSÃO | S23: OBSERVAÇÃO | AN23: 41699 | AO23: 4137.87 | AP23: 2137.87 | AQ23: 23/05/2014 | AR23: -2000
E24: CLIENTE | F24: PEDIDO | I24: UND | J24: CLIENTE | K24: ENTREGA | L24: FATURA | Q24: 30 DD | R24: R$ | AP24: 2000 | AQ24: 20/06/2014 | AR24: 0
B25: NORTEFRUT | C25: BANDEJA PAPAYA PET 4 UND | D25: 46 | E25: e-mail | F25: 42384 | G25: 20 | H25: MIL | I25: 449.5 | K25: 42373 | L25: 42376 | M25: 2641 | N25: 20000 | O25: =(N25-G25*1000) -> 0 | P25: =(N25*I25/1000) -> 8990 | Q25: =(L25+28) -> 42404 | R25: =(P25*0.05) -> 449.5 | AN25: 41730 | AO25: 4229.4 | AP25: 2000 | AQ25: 41834 | AR25: -2229.4
B26: FF MAGALHÃES | C26: BANDEJA PET PAPAYA 4 UND. | D26: 5 | E26: E-MAIL | F26: 42271 | G26: 10 | H26: MIL | I26: 449.5 | K26: 42384 | L26: 42384 | M26: 2646 | N26: 10000 | O26: =(N26-G26*1000) -> 0 | P26: =(N26*I26/1000) -> 4495 | Q26: =(L26+10) -> 42394 | R26: =(P26*0.05) -> 224.75 | AP26: 2229.4 | AQ26: 18/07/2014 | AR26: 0
B27: TERRA | C27: CUMBUCA 500 G - 35 | D27: 11 | E27: verbal | F27: 42381 | G27: 5 | H27: MIL | I27: 279 | K27: 42381 | L27: 42381 | M27: 2645 | N27: 5000 | O27: =(N27-G27*1000) -> 0 | P27: =(N27*I27/1000) -> 1395 | Q27: =(L27+28) -> 42409 | R27: =(P27*0.05) -> 69.75 | AN27: 41760 | AO27: 3332.1 | AP27: 2000 | AQ27: 41859 | AR27: =(AP27-AO27) -> -1332.1
B28: Q'DELICIA | C28: BANDEJAS MAMÃO PAPAYA 4 UND | D28: 21 | E28: E-MAIL | F28: 42389 | G28: 3 | H28: MIL | I28: 449.5 | K28: 42390 | L28: 42389 | M28: 2652 | N28: 3200 | O28: =(N28-G28*1000) -> 200 | P28: =(N28*I28/1000) -> 1438.4 | Q28: =(L28+35) -> 42424 | R28: =(P28*0.05) -> 71.92 | V28: ALLCAB FIOS E CABOS - BRASIL SUL | W28: CAIO G. PAVANELLI (11) 2455-2011 | AP28: 1332.1 | AQ28: 27/08/2014 | AR28: 0
B29: Q'DELICIA | C29: CUMBUCA 500 G 35 | D29: 22 | E29: E-MAIL | F29: 42389 | G29: 5 | H29: MIL | I29: 300 | K29: 42390 | L29: 42389 | M29: 2652 | N29: 5000 | O29: =(N29-G29*1000) -> 0 | P29: =(N29*I29/1000) -> 1500 | Q29: =(L29+35) -> 42424 | R29: =(P29*0.05) -> 75 | X29: OC | Y29: DATA | AB29: PREÇO | AC29: CODIGO | AD29: DATA | AE29: DATA | AJ29: DATA | AK29: VALOR DA | AN29: 41791 | AO29: 4538.6 | AP29: 2000 | AQ29: 04/09/2014 | AR29: =(AP29-AO29) -> -2538.6
B30: Q'DELICIA | C30: BANDEJAS MAMÃO PAPAYA 2 UND | D30: 23 | E30: E-MAIL | F30: 42389 | G30: 5 | H30: MIL | I30: 320 | K30: 42390 | L30: 42389 | M30: 2652 | N30: 5000 | O30: =(N30-G30*1000) -> 0 | P30: =(N30*I30/1000) -> 1600 | Q30: =(L30+35) -> 42424 | R30: =(P30*0.05) -> 80 | V30: PRODUTO | W30: PEDIDO | X30: DO | Y30: DO | Z30: QUANT | AA30: UND | AB30: POR | AC30: DO | AD30: DE | AE30: DE | AF30: N F | AG30: QUANT | AH30: SALDO | AI30: VALOR | AJ30: COMISSÃO | AK30: COMISSÃO | AL30: OBSERVAÇÃO | AP30: 2358.6 | AQ30: 18/09/2014 | AR30: =(AP30+AR29) -> -180
B31: DOCE MEL | C31: =IF(J31=1473,"BANDEJA PAPAYA PET - GF 15",IF(J31=0," ")) -> BANDEJA PAPAYA PET - GF 15 | D31: 31 | E31: 22007 | F31: 42391 | G31: 50 | H31: MIL | I31: 449.5 | J31: 1473 | K31: 42399 | L31: 42397 | M31: 2658 | N31: 50000 | O31: =(N31-G31*1000) -> 0 | P31: =(N31*I31/1000) -> 22475 | Q31: =(L31+30) -> 42427 | R31: =(P31*0.05) -> 1123.75 | X31: CLIENTE | Y31: PEDIDO | AB31: UND | AC31: CLIENTE | AD31: ENTREGA | AE31: FATURA | AJ31: 35 DD | AK31: R$ | AP31: 3000 | AQ31: 41927 | AR31: =(AP31+AR30) -> 2820
B32: BELLO FRUIT | C32: BANDEJA CLAIM SHELL PAPAYA 4 UND | D32: 8 | E32: e-mail | F32: 42384 | G32: 12 | H32: MIL | I32: 449.5 | K32: 42387 | L32: 42391 | M32: 2653 | N32: 12000 | O32: =(N32-G32*1000) -> 0 | P32: =(N32*I32/1000) -> 5394 | Q32: =(L32+35) -> 42426 | R32: =(P32*0.05) -> 269.7 | AN32: 41821 | AO32: 4997.93 | AP32: 2820 | AQ32: 15/10/2014 | AR32: =(AP32-AO32) -> -2177.93
V33: FILME PVC EST. 60 MM X 40 MICRA | W33: 1 | X33: E-MAIL | Y33: 42782 | Z33: 300 | AA33: KG | AB33: 9.7 | AD33: 42788 | AE33: 42794 | AF33: 46329 | AG33: 310 | AH33: =(AG33-Z33) -> 10 | AI33: =(AG33*AB33) -> 3007 | AJ33: =(AE33+28) -> 42822 | AK33: =(AI33*0.05) -> 150.35 | AP33: 4044.9 | AQ33: 30/10/2014 | AR33: =(AP33+AR32) -> 1866.97
P34: =SUM(P25:P33) -> 47287.4 | R34: =(P34*0.05) -> 2364.37 | S34: OK | AN34: 41852 | AO34: 2584.4 | AP34: 2584.4 | AQ34: 03/10/2014 | AR34: =(AP34-AO34) -> 0
AN35: 41883 | AO35: 5896.64 | AP35: 1866.97 | AQ35: 30/10/2014 | AR35: =(AP35-AO35) -> -4029.67
B36: MARÇO 2016 | AP36: 3896.64 | AQ36: 18/11/2014 | AR36: =(AP36+AR35) -> -133.03
E37: OC | F37: DATA | I37: PREÇO | J37: CODIGO | K37: DATA | L37: DATA | Q37: DATA | R37: VALOR DA | AP37: 2000 | AQ37: 41976 | AR37: =(AP37+AR36) -> 1866.97
B38: CLIENTE | C38: PRODUTO | D38: PEDIDO | E38: DO | F38: DO | G38: QUANT | H38: UND | I38: POR | J38: DO | K38: DE | L38: DE | M38: N F | N38: QUANT | O38: SALDO | P38: VALOR | Q38: COMISSÃO | R38: COMISSÃO | S38: OBSERVAÇÃO | AN38: 41913 | AO38: 9827.6 | AP38: 1866.97 | AQ38: 41976 | AR38: =(AP38-AO38) -> -7960.63
E39: CLIENTE | F39: PEDIDO | I39: UND | J39: CLIENTE | K39: ENTREGA | L39: FATURA | Q39: 30 DD | R39: R$ | AP39: 3000 | AQ39: 12/12/2014 | AR39: =(AP39+AR38) -> -4960.63
B40: CASA DA UVA | C40: CUMBUCA 500 - G 35 | D40: 6 | E40: E-MAIL | F40: 42398 | G40: 12 | H40: MIL | I40: 300 | K40: 42402 | L40: 42403 | M40: 2663 | N40: 12000 | O40: =(N40-G40*1000) -> 0 | P40: =(N40*I40/1000) -> 3600 | Q40: =(L40+35) -> 42438 | R40: =(P40*0.05) -> 180 | AP40: 2500 | AQ40: 05/01/2015 | AR40: =(AP40+AR39) -> -2460.63
B41: CASA SUIÇA | C41: BANDEJAS BOLO COBERTO/ZERO | D41: 280 | E41: E-MAIL | F41: 42383 | G41: 100 | H41: MIL | I41: 66 | J41: 13383 | K41: 42402 | L41: 42401 | M41: 2660 | N41: 102000 | O41: =(N41-G41*1000) -> 2000 | P41: =(N41*I41/1000) -> 6732 | Q41: =(L41+35) -> 42436 | R41: =(P41*0.05) -> 336.6 | AP41: 2327.6 | AQ41: 05/01/2015 | AR41: =(AP41+AR40) -> -133.03
B42: CASA SUIÇA | C42: BANDEJA RETANGULAR - JANDIRA | D42: 281 | E42: E-MAIL | F42: 42383 | G42: 200 | H42: MIL | I42: 66 | J42: 9124 | K42: 42402 | L42: 42401 | M42: 2660 | N42: 201000 | O42: =(N42-G42*1000) -> 1000 | P42: =(N42*I42/1000) -> 13266 | Q42: =(L42+35) -> 42436 | R42: =(P42*0.05) -> 663.3 | AP42: 289.97 | AQ42: 42009 | AR42: =(AP42+AR41) -> 156.94
B43: DE MARCHI | C43: CUMBUCA 500 - G 35 | D43: 2 | E43: VERBAL | F43: 42412 | G43: 10 | H43: MIL | I43: 300 | K43: 42415 | L43: 42415 | M43: 2667 | N43: 10000 | O43: =(N43-G43*1000) -> 0 | P43: =(N43*I43/1000) -> 3000 | Q43: =(L43+30) -> 42445 | R43: =(P43*0.05) -> 150 | AN43: 41944 | AO43: 12252.06 | AP43: 156.94 | AQ43: 05/01/2015 | AR43: =(AP43-AO43) -> -12095.12
B44: Q'DELICIA | C44: BANDEJAS MAMÃO PAPAYA 4 UND | D44: 24 | E44: E-MAIL | F44: 42416 | G44: 3 | H44: MIL | I44: 449.5 | K44: 42422 | L44: 42418 | M44: 2669 | N44: 3000 | O44: =(N44-G44*1000) -> 0 | P44: =(N44*I44/1000) -> 1348.5 | Q44: =(L44+35) -> 42453 | R44: =(P44*0.05) -> 67.425 | AP44: 2972.4 | AQ44: 42009 | AR44: =(AP44+AR43) -> -9122.72
B45: Q'DELICIA | C45: CUMBUCA 500 G 35 | D45: 25 | E45: E-MAIL | F45: 42416 | G45: 5 | H45: MIL | I45: 300 | K45: 42422 | L45: 42418 | M45: 2669 | N45: 5000 | O45: =(N45-G45*1000) -> 0 | P45: =(N45*I45/1000) -> 1500 | Q45: =(L45+35) -> 42453 | R45: =(P45*0.05) -> 75 | V45: ALLCAB FIOS E CABOS | W45: CAIO G. PAVANELLI (11) 2455-2011 | AP45: 4000 | AQ45: 42060 | AR45: =(AP45+AR44) -> -5122.72
B46: Q'DELICIA | C46: BANDEJAS MAMÃO PAPAYA 2 UND | D46: 26 | E46: E-MAIL | F46: 42416 | G46: 5 | H46: MIL | I46: 320 | K46: 42422 | L46: 42418 | M46: 2669 | N46: 5600 | O46: =(N46-G46*1000) -> 600 | P46: =(N46*I46/1000) -> 1792 | Q46: =(L46+35) -> 42453 | R46: =(P46*0.05) -> 89.6 | X46: OC | Y46: DATA | AB46: PREÇO | AC46: CODIGO | AD46: DATA | AE46: DATA | AJ46: DATA | AK46: VALOR DA | AP46: 5279.65 | AQ46: 42083 | AR46: =(AP46+AR45) -> 156.93
V47: PRODUTO | W47: PEDIDO | X47: DO | Y47: DO | Z47: QUANT | AA47: UND | AB47: POR | AC47: DO | AD47: DE | AE47: DE | AF47: N F | AG47: QUANT | AH47: SALDO | AI47: VALOR | AJ47: COMISSÃO | AK47: COMISSÃO | AL47: OBSERVAÇÃO | AN47: 41974 | AO47: 8375.4 | AP47: 156.93 | AQ47: 42083 | AR47: =(AP47-AO47) -> -8218.47
P48: =SUM(P40:P47) -> 31238.5 | R48: =(P48*0.05) -> 1561.925 | S48: ok | X48: CLIENTE | Y48: PEDIDO | AB48: UND | AC48: CLIENTE | AD48: ENTREGA | AE48: FATURA | AJ48: 35 DD | AK48: R$ | AP48: 6149.9 | AQ48: 42094 | AR48: =(AP48+AR47) -> -2068.57
AP49: 3000 | AQ49: 42129 | AR49: =(AP49+AR48) -> 931.43
B50: ABRIL 2016 | V50: FILME PVC EST. 60 MM X 40 MICRA | W50: 4 | X50: VERBAL | Y50: 42384 | Z50: 250 | AA50: KG | AB50: 9.5 | AD50: 42384 | AE50: 42383 | AF50: x | AG50: 230 | AH50: =(AG50-Z50) -> -20 | AI50: =(AG50*AB50) -> 2185 | AJ50: =(AE50+28) -> 42411 | AK50: =(AI50*0.06) -> 131.1 | AN50: 42005 | AO50: 6149.9 | AP50: 931.43 | AQ50: 42129 | AR50: =(AP50-AO50) -> -5218.47
E51: OC | F51: DATA | I51: PREÇO | J51: CODIGO | K51: DATA | L51: DATA | Q51: DATA | R51: VALOR DA | V51: FILME PVC EST. 60 MM X 40 MICRA | W51: 5 | X51: VERBAL | Y51: 42438 | Z51: 250 | AA51: KG | AB51: 9.5 | AD51: 42445 | AE51: 42445 | AF51: x | AG51: 274 | AH51: =(AG51-Z51) -> 24 | AI51: =(AG51*AB51) -> 2603 | AJ51: =(AE51+28) -> 42473 | AK51: =(AI51*0.06) -> 156.18 | AP51: 3000 | AQ51: 42149 | AR51: =(AP51+AR50) -> -2218.47
B52: CLIENTE | C52: PRODUTO | D52: PEDIDO | E52: DO | F52: DO | G52: QUANT | H52: UND | I52: POR | J52: DO | K52: DE | L52: DE | M52: N F | N52: QUANT | O52: SALDO | P52: VALOR | Q52: COMISSÃO | R52: COMISSÃO | S52: OBSERVAÇÃO | V52: FILME PVC EST. 60 MM X 40 MICRA | W52: 6 | X52: E-MAIL | Y52: 42514 | Z52: 200 | AA52: KG | AB52: 10.3 | AD52: 42520 | AE52: 42527 | AG52: 237 | AH52: =(AG52-Z52) -> 37 | AI52: =(AG52*AB52) -> 2441.1 | AJ52: =(AE52+28) -> 42555 | AK52: =(AI52*0.06) -> 146.466 | AP52: 960 | AQ52: 42170 | AR52: =(AP52+AR51) -> -1258.47
E53: CLIENTE | F53: PEDIDO | I53: UND | J53: CLIENTE | K53: ENTREGA | L53: FATURA | Q53: 30 DD | R53: R$ | V53: FILME PVC EST. 60 MM X 40 MICRA | W53: 7 | X53: E-MAIL | Y53: 42514 | Z53: 200 | AA53: KG | AB53: 10.3 | AD53: 42548 | AE53: 42549 | AG53: 195.7 | AH53: =(AG53-Z53) -> -4.3 | AI53: =(AG53*AB53) -> 2015.71 | AJ53: =(AE53+28) -> 42577 | AK53: =(AI53*0.06) -> 120.9426 | AP53: 3365.4 | AQ53: 42174 | AR53: =(AP53+AR52) -> 2106.93
B54: SUPER LANCHE | C54: BANDEJA SANDUICHE TRIANGULAR | D54: 3 | E54: verbal | F54: 42422 | G54: 10 | H54: MIL | I54: 170 | K54: 42440 | L54: 42432 | M54: 2676 | N54: 10000 | O54: =(N54-G54*1000) -> 0 | P54: =(N54*I54/1000) -> 1700 | Q54: =(L54+28) -> 42460 | R54: =(P54*0.05) -> 85 | V54: FILME PVC EST. 60 MM X 40 MICRA | W54: 8 | X54: E-MAIL | Y54: 42618 | Z54: 200 | AA54: KG | AB54: 10.5 | AD54: 42619 | AE54: 42619 | AG54: 200 | AH54: =(AG54-Z54) -> 0 | AI54: =(AG54*AB54) -> 2100 | AJ54: =(AE54+28) -> 42647 | AK54: =(AI54*0.06) -> 126 | AN54: 42036 | AO54: 4727.2 | AP54: 2106.93 | AQ54: 42174 | AR54: =(AP54-AO54) -> -2620.27
B55: CASA SUIÇA | C55: BANDEJA RETANGULAR - JANDIRA | D55: 282 | E55: E-MAIL | F55: 42422 | G55: 100 | H55: MIL | I55: 66 | J55: 9124 | K55: 42448 | L55: 42446 | M55: 2688 | N55: 102000 | O55: =(N55-G55*1000) -> 2000 | P55: =(N55*I55/1000) -> 6732 | Q55: =(L55+35) -> 42481 | R55: =(P55*0.05) -> 336.6 | V55: FILME PVC EST. 60 MM X 40 MICRA | W55: 9 | X55: E-MAIL | Y55: 42677 | Z55: 100 | AA55: KG | AB55: 11.5 | AD55: 42678 | AE55: 42678 | AG55: 100 | AH55: =(AG55-Z55) -> 0 | AI55: =(AG55*AB55) -> 1150 | AJ55: =(AE55+28) -> 42706 | AK55: =(AI55*0.06) -> 69 | AP55: 2700 | AQ55: 42184 | AR55: =(AP55+AR54) -> 79.73
V56: FILME PVC EST. 60 MM X 40 MICRA | W56: 10 | X56: E-MAIL | Y56: 42677 | Z56: 100 | AA56: KG | AB56: 11.5 | AD56: 42688 | AE56: 42688 | AG56: 100 | AH56: =(AG56-Z56) -> 0 | AI56: =(AG56*AB56) -> 1150 | AJ56: =(AE56+28) -> 42716 | AK56: =(AI56*0.06) -> 69 | AN56: 42064 | AO56: 4105.29 | AP56: 79.73 | AQ56: 42184 | AR56: =(AP56-AO56) -> -4025.56
P57: =SUM(P54:P55) -> 8432 | R57: =(P57*0.05) -> 421.6 | S57: ok | V57: FILME PVC EST. 60 MM X 40 MICRA | W57: 11 | X57: verbal | Y57: 42717 | Z57: 200 | AA57: KG | AB57: 11.5 | AD57: 42720 | AE57: 42720 | AG57: 200 | AH57: =(AG57-Z57) -> 0 | AI57: =(AG57*AB57) -> 2300 | AJ57: =(AE57+28) -> 42748 | AK57: =(AI57*0.06) -> 138 | AP57: 3000 | AQ57: 42212 | AR57: =(AP57+AR56) -> -1025.56
AP58: 279 | AQ58: 42213 | AR58: =(AP58+AR57) -> -746.56
B59: MAIO 2016 | AP59: 5685.08 | AQ59: 42216 | AR59: =(AP59+AR58) -> 4938.52
E60: OC | F60: DATA | I60: PREÇO | J60: CODIGO | K60: DATA | L60: DATA | Q60: DATA | R60: VALOR DA | AN60: 42095 | AO60: 6270.2 | AP60: 4938.52 | AQ60: 42216 | AR60: =(AP60-AO60) -> -1331.68
B61: CLIENTE | C61: PRODUTO | D61: PEDIDO | E61: DO | F61: DO | G61: QUANT | H61: UND | I61: POR | J61: DO | K61: DE | L61: DE | M61: N F | N61: QUANT | O61: SALDO | P61: VALOR | Q61: COMISSÃO | R61: COMISSÃO | S61: OBSERVAÇÃO | AP61: 2500 | AQ61: 42240 | AR61: =(AP61+AR60) -> 1168.32
E62: CLIENTE | F62: PEDIDO | I62: UND | J62: CLIENTE | K62: ENTREGA | L62: FATURA | Q62: 30 DD | R62: R$ | V62: BELLO FRUIT | W62: ALEXANDRO NOVAIS (73) 3605-4850 suprimentos@bellopapaya.com.br | AN62: 42125 | AO62: 4858.83 | AP62: 1168.32 | AQ62: 42240 | AR62: =(AP62-AO62) -> -3690.51
B63: CASA SUIÇA | C63: BANDEJA RETANGULAR - JANDIRA | D63: 283 | E63: E-MAIL | F63: 42422 | G63: 100 | H63: MIL | I63: 66 | J63: 9124 | K63: 42461 | L63: 42461 | M63: 2705 | N63: 102000 | O63: =(N63-G63*1000) -> 2000 | P63: =(N63*I63/1000) -> 6732 | Q63: =(L63+35) -> 42496 | R63: =(P63*0.05) -> 336.6 | X63: OC | Y63: DATA | AB63: PREÇO | AC63: CODIGO | AD63: DATA | AE63: DATA | AJ63: DATA | AK63: VALOR DA | AP63: 3000 | AQ63: 42269 | AR63: =(AP63+AR62) -> -690.51
V64: PRODUTO | W64: PEDIDO | X64: DO | Y64: DO | Z64: QUANT | AA64: UND | AB64: POR | AC64: DO | AD64: DE | AE64: DE | AF64: N F | AG64: QUANT | AH64: SALDO | AI64: VALOR | AJ64: COMISSÃO | AK64: COMISSÃO | AL64: OBSERVAÇÃO | AP64: 3991.2 | AQ64: 42290 | AR64: =(AP64+AR63) -> 3300.69
P65: =SUM(P63:P64) -> 6732 | R65: =(P65*0.05) -> 336.6 | S65: ok | X65: CLIENTE | Y65: PEDIDO | AB65: UND | AC65: CLIENTE | AD65: ENTREGA | AE65: FATURA | AJ65: 35 DD | AK65: R$ | AN65: 42156 | AO65: 5483.78 | AP65: 3300.69 | AQ65: 42290 | AR65: =(AP65-AO65) -> -2183.09
AP66: 1000 | AQ66: 42403 | AR66: =(AP66+AR65) -> -1183.09
V67: BANDEJA CLAIM SHELL PAPAYA 4 UND | W67: 8 | X67: e-mail | Y67: 42384 | Z67: 12 | AA67: MIL | AB67: 449.5 | AD67: 42387 | AE67: 42391 | AF67: 2653 | AG67: 12000 | AH67: =(AG67-Z67*1000) -> 0 | AI67: =(AG67*AB67/1000) -> 5394 | AJ67: =(AE67+35) -> 42426 | AK67: =(AI67*0.05) -> 269.7 | AP67: 1500 | AQ67: 42457 | AR67: =(AP67+AR66) -> 316.91
B70: PAULISTA PACKING JANEIRO 2016 | V70: BENAFRUT - SERRAPLAST | W70: LUCÉLIA (11) 3659-7060
E71: OC | F71: DATA | I71: PREÇO | J71: CODIGO | K71: DATA | L71: DATA | Q71: DATA | R71: VALOR DA | X71: OC | Y71: DATA | AB71: PREÇO | AC71: CODIGO | AD71: DATA | AE71: DATA | AJ71: DATA | AK71: VALOR DA | AN71: MÊS | AO71: COMISSÃO | AP71: PAGAMENTO | AQ71: DATA | AR71: SALDO
B72: CLIENTE | C72: PRODUTO | D72: PEDIDO | E72: DO | F72: DO | G72: QUANT | H72: UND | I72: POR | J72: DO | K72: DE | L72: DE | M72: N F | N72: QUANT | O72: SALDO | P72: VALOR | Q72: COMISSÃO | R72: COMISSÃO | S72: OBSERVAÇÃO | V72: PRODUTO | W72: PEDIDO | X72: DO | Y72: DO | Z72: QUANT | AA72: UND | AB72: POR | AC72: DO | AD72: DE | AE72: DE | AF72: N F | AG72: QUANT | AH72: SALDO | AI72: VALOR | AJ72: COMISSÃO | AK72: COMISSÃO | AL72: OBSERVAÇÃO | AN72: 42186 | AO72: 3991.2 | AP72: 316.91 | AQ72: 42457 | AR72: =(AP72-AO72) -> -3674.29
E73: CLIENTE | F73: PEDIDO | I73: UND | J73: CLIENTE | K73: ENTREGA | L73: FATURA | Q73: 30 DD | R73: R$ | X73: CLIENTE | Y73: PEDIDO | AB73: UND | AC73: CLIENTE | AD73: ENTREGA | AE73: FATURA | AJ73: 35 DD | AK73: R$ | AP73: 1000 | AQ73: 42643 | AR73: -2674.29
B74: METALCAP | C74: FILME PVC EST. 60 MM X 40 MICRA | D74: 73 | E74: VERBAL | F74: 42270 | G74: 550 | H74: KG | I74: 9.8 | K74: 42356 | L74: 42374 | M74: x | N74: 559 | O74: =(N74-G74) -> 9 | P74: =(N74*I74) -> 5478.2 | Q74: =(L74+28) -> 42402 | R74: =(P74*0.04) -> 219.128 | AN74: 42217 | AO74: 5822.55 | AR74: =(AP74-AO74) -> -5822.55
B75: ALLCAB | C75: FILME PVC EST. 60 MM X 40 MICRA | D75: 4 | E75: VERBAL | F75: 42384 | G75: 250 | H75: KG | I75: 9.5 | K75: 42384 | L75: 42383 | M75: x | N75: 230 | O75: =(N75-G75) -> -20 | P75: =(N75*I75) -> 2185 | Q75: =(L75+28) -> 42411 | R75: =(P75*0.06) -> 131.1
B76: METALCAP | C76: FILME PVC EST. 60 MM X 40 MICRA | D76: 76 | E76: e-mail | F76: 42396 | G76: 400 | H76: KG | I76: 9.8 | K76: 42398 | L76: 42397 | M76: x | N76: 409.2 | O76: =(N76-G76) -> 9.2 | P76: =(N76*I76) -> 4010.16 | Q76: =(L76+28) -> 42425 | R76: =(P76*0.04) -> 160.4064 | AN76: 42248 | AO76: 3339.15 | AR76: =(AP76-AO76) -> -3339.15
S77: OK
P78: =SUM(P74:P77) -> 11673.36 | R78: =(P78*0.06) -> 700.4016 | AN78: 42278 | AO78: 4952.37 | AR78: =(AP78-AO78) -> -4952.37
B80: PAULISTA PACKING FEVEREIRO 2016 | V80: BENASSI CAMPINAS (SP) | W80: PAULISTA PACKING | AA80: (19) 3246-0366 | AD80: CAMILA ARAUJO (19) 3746-1218 | AN80: 42309 | AO80: 4016.12 | AR80: =(AP80-AO80) -> -4016.12
E81: OC | F81: DATA | I81: PREÇO | J81: CODIGO | K81: DATA | L81: DATA | Q81: DATA | R81: VALOR DA | X81: OC | Y81: DATA | AB81: PREÇO | AC81: CODIGO | AD81: DATA | AE81: DATA | AJ81: DATA | AK81: VALOR DA
B82: CLIENTE | C82: PRODUTO | D82: PEDIDO | E82: DO | F82: DO | G82: QUANT | H82: UND | I82: POR | J82: DO | K82: DE | L82: DE | M82: N F | N82: QUANT | O82: SALDO | P82: VALOR | Q82: COMISSÃO | R82: COMISSÃO | S82: OBSERVAÇÃO | V82: PRODUTO | W82: PEDIDO | X82: DO | Y82: DO | Z82: QUANT | AA82: UND | AB82: POR | AC82: DO | AD82: DE | AE82: DE | AF82: N F | AG82: QUANT | AH82: SALDO | AI82: VALOR | AJ82: COMISSÃO | AK82: COMISSÃO | AL82: OBSERVAÇÃO | AN82: 42339 | AO82: 4091.52 | AR82: =(AP82-AO82) -> -4091.52
E83: CLIENTE | F83: PEDIDO | I83: UND | J83: CLIENTE | K83: ENTREGA | L83: FATURA | Q83: 30 DD | R83: R$ | X83: CLIENTE | Y83: PEDIDO | AB83: UND | AC83: CLIENTE | AD83: ENTREGA | AE83: FATURA | AJ83: 35 DD | AK83: R$
B84: SHINDI UEMURA | C84: FILME PVC ENCOLHIVEL PD 400 X 15 - PERFURADO | D84: 1 | E84: verbal | F84: 42410 | G84: 150 | H84: KG | I84: 8.91 | K84: 42416 | L84: 42415 | M84: x | N84: 161.1 | O84: =(N84-G84) -> 11.1 | P84: =(N84*I84) -> 1435.401 | Q84: =(L84) -> 42415 | R84: =(P84*0.04) -> 57.41604 | AN84: 42370 | AO84: 4317.77 | AR84: =(AP84-AO84) -> -4317.77
B85: SHINDI UEMURA | C85: FILME PVC ENCOLHIVEL PD 400 X 20 - PERFURADO | D85: 2 | E85: verbal | F85: 42410 | G85: 150 | H85: KG | I85: 8.91 | K85: 42416 | L85: 42415 | M85: x | N85: 162.1 | O85: =(N85-G85) -> 12.1 | P85: =(N85*I85) -> 1444.311 | Q85: =(L85) -> 42415 | R85: =(P85*0.04) -> 57.77244 | V85: FILME PVC GA 380 MM X 10 MICRA | W85: 3 | X85: verbal | Y85: 42423 | Z85: 200 | AA85: KG | AB85: 10.8 | AD85: 42426 | AE85: 42432 | AF85: x | AG85: 202.4 | AH85: =(AG85-Z85) -> 2.4 | AI85: =(AG85*AB85) -> 2185.92 | AJ85: =(AE85+28) -> 42460 | AK85: =(AI85*0.06) -> 131.1552
B86: METALCAP | C86: FILME PVC EST. 60 MM X 40 MICRA | D86: 77 | E86: e-mail | F86: 42396 | G86: 500 | H86: KG | I86: 9.8 | K86: 42405 | L86: =(K86) -> 42405 | M86: x | N86: 511.9 | O86: =(N86-G86) -> 11.9 | P86: =(N86*I86) -> 5016.62 | Q86: =(L86+28) -> 42433 | R86: =(P86*0.06) -> 300.9972 | V86: FILME PVC GA 380 MM X 10 MICRA | W86: 4 | X86: verbal | Y86: 42473 | Z86: 300 | AA86: KG | AB86: 10.8 | AD86: 42479 | AE86: 42480 | AF86: x | AG86: 297 | AH86: =(AG86-Z86) -> -3 | AI86: =(AG86*AB86) -> 3207.6 | AJ86: =(AE86+28) -> 42508 | AK86: =(AI86*0.06) -> 192.456 | AN86: fev/16 | AO86: 2364.37 | AR86: =(AP86-AO86) -> -2364.37
B87: METALCAP | C87: FILME PVC EST. 60 MM X 40 MICRA | D87: 78 | E87: e-mail | F87: 42396 | G87: 500 | H87: KG | I87: 9.8 | K87: 42412 | L87: =(K87) -> 42412 | M87: x | N87: 418 | O87: =(N87-G87) -> -82 | P87: =(N87*I87) -> 4096.4 | Q87: =(L87+28) -> 42440 | R87: =(P87*0.06) -> 245.784
B88: METALCAP | C88: FILME PVC EST. 60 MM X 40 MICRA | D88: 79 | E88: e-mail | F88: 42396 | G88: 400 | H88: KG | I88: 9.8 | K88: 42419 | L88: =(K88) -> 42419 | M88: x | N88: 407.8 | O88: =(N88-G88) -> 7.8 | P88: =(N88*I88) -> 3996.44 | Q88: =(L88+28) -> 42447 | R88: =(P88*0.06) -> 239.7864 | AN88: mar/16 | AO88: 1561,93 | AR88: =(AP88-AO88) -> -1561.93
S89: OK
P90: =SUM(P84:P89) -> 15989.172 | R90: =SUM(R84:R89) -> 901.75608 | AN90: abr/16 | AO90: 421,60 | AR90: =(AP90-AO90) -> -421.6
B92: PAULISTA PACKING MARÇO 2016 | AN92: mai/16 | AO92: 336,00 | AR92: =(AP92-AO92) -> -336
E93: OC | F93: DATA | I93: PREÇO | J93: CODIGO | K93: DATA | L93: DATA | Q93: DATA | R93: VALOR DA | V93: BENASSI CAMPINAS - SERRAPLAST | AD93: CAMILA ARAUJO (19) 3246-0366
B94: CLIENTE | C94: PRODUTO | D94: PEDIDO | E94: DO | F94: DO | G94: QUANT | H94: UND | I94: POR | J94: DO | K94: DE | L94: DE | M94: N F | N94: QUANT | O94: SALDO | P94: VALOR | Q94: COMISSÃO | R94: COMISSÃO | S94: OBSERVAÇÃO | X94: OC | Y94: DATA | AB94: PREÇO | AC94: CODIGO | AD94: DATA | AE94: DATA | AJ94: DATA | AK94: VALOR DA
E95: CLIENTE | F95: PEDIDO | I95: UND | J95: CLIENTE | K95: ENTREGA | L95: FATURA | Q95: 30 DD | R95: R$ | V95: PRODUTO | W95: PEDIDO | X95: DO | Y95: DO | Z95: QUANT | AA95: UND | AB95: POR | AC95: DO | AD95: DE | AE95: DE | AF95: N F | AG95: QUANT | AH95: SALDO | AI95: VALOR | AJ95: COMISSÃO | AK95: COMISSÃO | AL95: OBSERVAÇÃO | AQ95: TOTAL | AR95: =SUM(AR73:AR94) -> -33897.67
B96: BENASSI CAMPINAS | C96: FILME PVC GA 380 MM X 10 MICRA | D96: 3 | E96: verbal | F96: 42423 | G96: 200 | H96: KG | I96: 10.8 | K96: 42426 | L96: 42432 | M96: x | N96: 202.4 | O96: =(N96-G96) -> 2.4 | P96: =(N96*I96) -> 2185.92 | Q96: =(L96+28) -> 42460 | R96: =(P96*0.06) -> 131.1552 | X96: CLIENTE | Y96: PEDIDO | AB96: UND | AC96: CLIENTE | AD96: ENTREGA | AE96: FATURA | AJ96: 35 DD | AK96: R$
B97: METALCAP | C97: FILME PVC EST. 60 MM X 40 MICRA | D97: 80 | E97: e-mail | F97: 42396 | G97: 400 | H97: KG | I97: 9.8 | K97: 42426 | L97: 42430 | M97: x | N97: 412.4 | O97: =(N97-G97) -> 12.4 | P97: =(N97*I97) -> 4041.52 | Q97: =(L97+28) -> 42458 | R97: =(P97*0.04) -> 161.6608
B98: METALCAP | C98: FILME PVC EST. 60 MM X 40 MICRA | D98: 81 | E98: e-mail | F98: 42396 | G98: 400 | H98: KG | I98: 9.8 | K98: 42433 | L98: =(K98) -> 42433 | M98: x | N98: 378.25 | O98: =(N98-G98) -> -21.75 | P98: =(N98*I98) -> 3706.85 | Q98: =(L98+28) -> 42461 | R98: =(P98*0.04) -> 148.274 | V98: CUMBUCA 500 G - MA15 | W98: 1 | X98: VERBAL | Y98: 42432 | Z98: 30 | AA98: MIL | AB98: 315 | AD98: 42437 | AE98: 42437 | AF98: 8396 | AG98: 30000 | AH98: =(AG98-Z98*1000) -> 0 | AI98: =(AG98*AB98/1000) -> 9450 | AJ98: =(AE98+35) -> 42472 | AK98: =(AI98*0.05) -> 472.5
B99: METALCAP | C99: FILME PVC EST. 60 MM X 40 MICRA | D99: 82 | E99: e-mail | F99: 42396 | G99: 400 | H99: KG | I99: 9.8 | K99: 42440 | L99: =(K99) -> 42440 | M99: x | N99: 378.25 | O99: =(N99-G99) -> -21.75 | P99: =(N99*I99) -> 3706.85 | Q99: =(L99+28) -> 42468 | R99: =(P99*0.04) -> 148.274 | V99: CUMBUCA 500 G - MA15 | W99: 2 | X99: VERBAL | Y99: 42503 | Z99: 50 | AA99: MIL | AB99: 315 | AD99: 42504 | AE99: 42504 | AF99: 8580 | AG99: 50000 | AH99: =(AG99-Z99*1000) -> 0 | AI99: =(AG99*AB99/1000) -> 15750 | AJ99: =(AE99+35) -> 42539 | AK99: =(AI99*0.05) -> 787.5
B100: METALCAP | C100: FILME PVC EST. 60 MM X 40 MICRA | D100: 83 | E100: e-mail | F100: 42396 | G100: 400 | H100: KG | I100: 9.8 | K100: 42447 | L100: 42452 | M100: x | N100: 438.8 | O100: =(N100-G100) -> 38.8 | P100: =(N100*I100) -> 4300.24 | Q100: =(L100+28) -> 42480 | R100: =(P100*0.04) -> 172.0096 | V100: CUMBUCA 500 G - MA15 | W100: 3 | X100: VERBAL | Y100: 42682 | Z100: 10 | AA100: MIL | AB100: 305 | AD100: 42685 | AE100: 42688 | AF100: 1476 | AG100: 10000 | AH100: =(AG100-Z100*1000) -> 0 | AI100: =(AG100*AB100/1000) -> 3050 | AJ100: =(AE100+35) -> 42723 | AK100: =(AI100*0.05) -> 152.5
B101: METALCAP | C101: FILME PVC EST. 60 MM X 40 MICRA | D101: 84 | E101: e-mail | F101: 42396 | G101: 400 | H101: KG | I101: 9.8 | K101: 42453 | L101: 42460 | M101: x | N101: 412.4 | O101: =(N101-G101) -> 12.4 | P101: =(N101*I101) -> 4041.52 | Q101: =(L101+28) -> 42488 | R101: =(P101*0.04) -> 161.6608 | V101: CUMBUCA 500 G - MA15 | W101: 4 | X101: E-MAIL | Y101: 42686 | Z101: 200 | AA101: MIL | AB101: 300 | AD101: 42691 | AE101: 42688 | AF101: 1467 | AG101: 200000 | AH101: =(AG101-Z101*1000) -> 0 | AI101: =(AG101*AB101/1000) -> 60000 | AJ101: =(AE101+35) -> 42723 | AK101: =(AI101*0.05) -> 3000
B102: ALL CAB | C102: FILME PVC EST. 60 MM X 40 MICRA | D102: 5 | E102: VERBAL | F102: 42438 | G102: 250 | H102: KG | I102: 9.5 | K102: 42445 | L102: 42445 | M102: x | N102: 274 | O102: =(N102-G102) -> 24 | P102: =(N102*I102) -> 2603 | Q102: =(L102+28) -> 42473 | R102: =(P102*0.06) -> 156.18
S103: OK
P104: =SUM(P96:P103) -> 24585.9 | R104: =(P104*0.06) -> 1475.154
B106: PAULISTA PACKING ABRIL 2016 | V106: BENASSI VIANA (ES) | W106: JOSE NILSON (27) 3216-3850 | AD106: TOBIAS ROSSETO (27) 99714-4658
E107: OC | F107: DATA | I107: PREÇO | J107: CODIGO | K107: DATA | L107: DATA | Q107: DATA | R107: VALOR DA | X107: OC | Y107: DATA | AB107: PREÇO | AC107: CODIGO | AD107: DATA | AE107: DATA | AJ107: DATA | AK107: VALOR DA
...

Sheet 2018
S2: MAPA DE COMISSÃO | AC2: SERRAPLAST TRANSFORMAÇÃO E COMERCIO DE PLASTICO LTDA. | AN2: MAPA DE ENTREGAS | BP2: BRASIL SUL EMBALAGENS LTDA. | CU2: CCS INDUSTRIA E COMERCIO DE EMBALAGENS PLASTICAS LTDA. | EG2: EDIPRINT INDUSTRIA GRAFICA LTDA.
F3: MAPA GERAL DE COMISSÕES
B4: 2017 | P4: SERRAPLAST JANEIRO 2017 | V4: COMISSÕES MENSAIS | BA4: BRASIL SUL MARÇO 2017 | BT4: ANA BEATRIZ S. BENTO | BU4: AILTON SOARES DE LIMA 11 96533-5312 | CK4: CCS MARÇO 2018 | DE4: SUPERBOM | DF4: MISAEL KAYSER/ELIZETE MELO 11 2842-1807 EVALDO 11 99864-9953 | DW4: EDIPRINT OUTUBRO 2021 | EP4: HORTA VITAE | EQ4: RENATO BOARO CAMILA 14 3812-7000
B5: REPRESENTADA | C5: JAN 12 | D5: FEV 01 | E5: MAR 02 | F5: ABR 03 | G5: MAI 04 | H5: JUN 05 | I5: JUL 06 | J5: AGO 07 | K5: SET 08 | L5: OUT 09 | M5: NOV 10 | N5: DEZ 11 | S5: OC | T5: DATA | W5: PREÇO | X5: CODIGO | Y5: DATA | Z5: DATA | AE5: VALOR DA | AJ5: BENASSI CAMPINAS | AK5: LUCIANA 19 3307-7843 RAMAL 218 | BD5: OC | BE5: DATA | BH5: PREÇO | BI5: CODIGO | BJ5: DATA | BK5: DATA | BP5: VALOR DA | BV5: OC | BW5: DATA | BZ5: PREÇO | CA5: CODIGO | CB5: DATA | CC5: DATA | CH5: VALOR DA | CN5: OC | CO5: DATA | CR5: PREÇO | CS5: CODIGO | CT5: DATA | CU5: DATA | CZ5: DATA | DA5: VALOR DA | DG5: OC | DH5: DATA | DK5: PREÇO | DL5: CODIGO | DM5: DATA | DN5: DATA | DS5: DATA | DT5: VALOR DA | DZ5: OC | EA5: DATA | ED5: PREÇO | EE5: CODIGO | EF5: DATA | EG5: DATA | EL5: DATA | EM5: VALOR DA | ER5: OC | ES5: DATA | EV5: PREÇO | EW5: CODIGO | EX5: DATA | EY5: DATA | FD5: DATA | FE5: VALOR DA
P6: CLIENTE | Q6: PRODUTO | R6: PEDIDO | S6: DO | T6: DO | U6: QUANT | V6: UND | W6: POR | X6: DO | Y6: DE | Z6: DE | AA6: N F | AB6: QUANT | AC6: SALDO | AD6: VALOR | AE6: COMISSÃO | AF6: OBSERVAÇÃO | AL6: OC | AM6: DATA | AP6: PREÇO | AQ6: CODIGO | AR6: DATA | AS6: DATA | AX6: VALOR DA | BA6: CLIENTE | BB6: PRODUTO | BC6: PEDIDO | BD6: DO | BE6: DO | BF6: QUANT | BG6: UND | BH6: POR | BI6: DO | BJ6: DE | BK6: DE | BL6: N F | BM6: QUANT | BN6: SALDO | BO6: VALOR | BP6: COMISSÃO | BQ6: OBSERVAÇÃO | BT6: PRODUTO | BU6: PEDIDO | BV6: DO | BW6: DO | BX6: QUANT | BY6: UND | BZ6: POR | CA6: DO | CB6: DE | CC6: DE | CD6: N F | CE6: QUANT | CF6: SALDO | CG6: VALOR | CH6: COMISSÃO | CI6: OBSERVAÇÃO | CK6: CLIENTE | CL6: PRODUTO | CM6: PEDIDO | CN6: DO | CO6: DO | CP6: QUANT | CQ6: UND | CR6: POR | CS6: DO | CT6: DE | CU6: DE | CV6: N F | CW6: QUANT | CX6: SALDO | CY6: VALOR | CZ6: COMISSÃO | DA6: COMISSÃO | DB6: OBSERVAÇÃO | DE6: PRODUTO | DF6: PEDIDO | DG6: DO | DH6: DO | DI6: QUANT | DJ6: UND | DK6: POR | DL6: DO | DM6: DE | DN6: DE | DO6: N F | DP6: QUANT | DQ6: SALDO | DR6: VALOR | DS6: COMISSÃO | DT6: COMISSÃO | DU6: OBSERVAÇÃO | DW6: CLIENTE | DX6: PRODUTO | DY6: PEDIDO | DZ6: DO | EA6: DO | EB6: QUANT | EC6: UND | ED6: POR | EE6: DO | EF6: DE | EG6: DE | EH6: N F | EI6: QUANT | EJ6: SALDO | EK6: VALOR | EL6: COMISSÃO | EM6: COMISSÃO | EN6: OBSERVAÇÃO | EP6: PRODUTO | EQ6: PEDIDO | ER6: DO | ES6: DO | ET6: QUANT | EU6: UND | EV6: POR | EW6: DO | EX6: DE | EY6: DE | EZ6: N F | FA6: QUANT | FB6: SALDO | FC6: VALOR | FD6: COMISSÃO | FE6: COMISSÃO | FF6: OBSERVAÇÃO
B7: SERRAPLAST | C7: =(AE17) -> 4385.6 | D7: =(AE28) -> 818.75 | E7: =(AE40) -> 1451.4 | F7: =(AE50) -> 1879 | G7: =(AE64) -> 4019.5 | H7: =(AE80) -> 3086.35 | I7: =(AE93) -> 1933 | J7: =(AE113) -> 3556.9 | K7: =(AE130) -> 5245 | L7: =(AE141) -> 232.75 | M7: =(AE162) -> 8301 | N7: =(AE181) -> 7359.5 | S7: CLIENTE | T7: PEDIDO | W7: UND | X7: CLIENTE | Y7: ENTREGA | Z7: FATURA | AE7: R$ | AJ7: PRODUTO | AK7: PEDIDO | AL7: DO | AM7: DO | AN7: QUANTIDADE | AO7: UND | AP7: POR | AQ7: DO | AR7: DE | AS7: DE | AT7: N F | AU7: QUANTIDADE | AV7: SALDO | AW7: VALOR | AX7: COMISSÃO | AY7: OBSERVAÇÃO | BD7: CLIENTE | BE7: PEDIDO | BH7: UND | BI7: CLIENTE | BJ7: ENTREGA | BK7: FATURA | BP7: R$ | BV7: CLIENTE | BW7: PEDIDO | BZ7: UND | CA7: CLIENTE | CB7: ENTREGA | CC7: FATURA | CH7: R$ | CN7: CLIENTE | CO7: PEDIDO | CR7: UND | CS7: CLIENTE | CT7: ENTREGA | CU7: FATURA | CZ7: 30 DD | DA7: R$ | DG7: CLIENTE | DH7: PEDIDO | DK7: UND | DL7: CLIENTE | DM7: ENTREGA | DN7: FATURA | DS7: 42 DD | DT7: R$ | DZ7: CLIENTE | EA7: PEDIDO | ED7: UND | EE7: CLIENTE | EF7: ENTREGA | EG7: FATURA | EL7: 30 DD | EM7: R$ | ER7: CLIENTE | ES7: PEDIDO | EV7: UND | EW7: CLIENTE | EX7: ENTREGA | EY7: FATURA | FD7: 42 DD | FE7: R$
P8: KORIN AGRO | Q8: EMB. OVO GALINHA 10 UND SRG - C10 | R8: 8 | S8: 31524 | T8: 42685 | U8: 120 | V8: MIL | W8: 255 | Y8: 42723 | Z8: 42714 | AA8: 1562 | AB8: 120000 | AC8: =(AB8-U8*1000) -> 0 | AD8: =(AB8*W8/1000) -> 30600 | AE8: =(AD8*0.05) -> 1530 | AF8: PAGO | AL8: CLIENTE | AM8: PEDIDO | AP8: UND | AQ8: CLIENTE | AR8: ENTREGA | AS8: FATURA | AX8: R$ | BA8: GO GREEN | BB8: FILME PVC GA 380 X 10 X 1200 | BC8: 1 | BD8: VERBAL | BE8: 42765 | BF8: 50 | BG8: BOB | BH8: 52.9 | BJ8: 42769 | BK8: 42773 | BL8: 46126 | BM8: 54 | BN8: =(BM8-BF8) -> 4 | BO8: =(BM8*BH8) -> 2856.6 | BP8: =(BO8*0.05) -> 142.83 | BQ8: PAGO | BT8: FILME PVC GA 380 X 9 X 1000 | BU8: 1 | BV8: VERBAL | BW8: 43733 | BX8: 10 | BY8: BOB | BZ8: 51.43 | CB8: 43749 | CC8: 43749 | CD8: 56395 | CE8: 12 | CF8: =(CE8-BX8) -> 2 | CG8: =(CE8*BZ8) -> 617.16 | CH8: =(CG8*0.05) -> 30.858 | CK8: SUPERBOM | CL8: CONJUNTO ENVASE MEL 200G | CM8: 131 | CO8: 43125 | CP8: 45 | CQ8: MIL | CR8: 868.82 | CT8: 43151 | CU8: =(CT8) -> 43151 | CV8: 13182/13191 | CW8: 45100 | CX8: =(CP8*1000-CW8) -> -100 | CY8: =(CR8*CW8/1000) -> 39183.782 | CZ8: =(CU8+42) -> 43193 | DA8: =(CY8*0.03) -> 1175.5135
B9: CHROMO | P9: CASA DA UVA | Q9: CUMBUCA 500 G - MA 15 | R9: 2 | S9: VERBAL | T9: 42709 | U9: 15 | V9: MIL | W9: 315 | Y9: 42714 | Z9: 42716 | AA9: 1564 | AB9: 15000 | AC9: =(AB9-U9*1000) -> 0 | AD9: =(AB9*W9/1000) -> 4725 | AE9: =(AD9*0.05) -> 236.25 | AF9: PAGO | AJ9: CUMBUCA 500 G - MA15 | AK9: 1 | AL9: VERBAL | AM9: 42432 | AN9: 30 | AO9: MIL | AP9: 315 | AR9: 42437 | AS9: 42437 | AT9: 8396 | AU9: 30000 | AV9: =(AU9-AN9*1000) -> 0 | AW9: =(AU9*AP9/1000) -> 9450 | AX9: =(AW9*0.05) -> 472.5 | BA9: ALL CAB | BB9: FILME PVC EST. 60 MM X 40 MICRA | BC9: 1 | BD9: E-MAIL | BE9: 42782 | BF9: 300 | BG9: KG | BH9: 9.7 | BJ9: 42788 | BK9: 42794 | BL9: 46329 | BM9: 310 | BN9: =(BM9-BF9) -> 10 | BO9: =(BM9*BH9) -> 3007 | BP9: =(BO9*0.05) -> 150.35 | BQ9: PAGO | BT9: FILME PVC GA 300 X 9 X 1000 | BU9: 1 | BV9: VERBAL | BW9: 43733 | BX9: 30 | BY9: BOB | BZ9: 40.65 | CB9: 43749 | CC9: 43749 | CD9: 56395 | CE9: 32 | CF9: =(CE9-BX9) -> 2 | CG9: =(CE9*BZ9) -> 1300.8 | CH9: =(CG9*0.05) -> 65.04 | DE9: CONJUNTO ENVASE MEL 200G | DF9: 125 | DH9: 42769 | DI9: 45 | DJ9: Mil | DK9: 842.76 | DM9: 42794 | DN9: 42793 | DO9: 12618 | DP9: 45000 | DQ9: =(DI9*1000-DP9) -> 0 | DR9: =(DK9*DP9/1000) -> 37924.2 | DS9: =(DN9+42) -> 42835 | DT9: =(DR9*0.03) -> 1137.726 | EP9: ETIQUETA ADESIVA OVO CAIPIRA TG 20 UND | EQ9: 1 | ER9: E-MAIL | ES9: 44469 | ET9: 30 | EU9: MIL | EV9: 145.65 | EX9: 44480 | EY9: 44480 | FA9: 30000 | FB9: =(FA9-ET9*1000) -> 0 | FC9: =(FA9*EV9/1000) -> 4369.5 | FE9: =(FC9*0.04) -> 174.78
P10: CASA DA UVA | Q10: EMBALAGEM TOMATINHO - SRT 08 | R10: 3 | S10: VERBAL | T10: 42709 | U10: 10 | V10: MIL | W10: 153.7 | Y10: 42714 | Z10: 42716 | AA10: 1564 | AB10: 10000 | AC10: =(AB10-U10*1000) -> 0 | AD10: =(AB10*W10/1000) -> 1537 | AE10: =(AD10*0.05) -> 76.85 | AF10: PAGO | AJ10: CUMBUCA 500 G - MA15 | AK10: 2 | AL10: VERBAL | AM10: 42503 | AN10: 50 | AO10: MIL | AP10: 315 | AR10: 42504 | AS10: 42504 | AT10: 8580 | AU10: 50000 | AV10: =(AU10-AN10*1000) -> 0 | AW10: =(AU10*AP10/1000) -> 15750 | AX10: =(AW10*0.05) -> 787.5 | BA10: LOSCHI & WATANABE | BB10: FILME PVC GA 380 X 10 X 1000 | BC10: 1 | BD10: VERBAL | BE10: 42787 | BF10: 50 | BG10: BOB | BH10: 45 | BJ10: 42790 | BK10: 42794 | BL10: 46332 | BM10: 54 | BN10: =(BM10-BF10) -> 4 | BO10: =(BM10*BH10) -> 2430 | BP10: =(BO10*0.05) -> 121.5 | BQ10: PAGO | BT10: FILME PVC GA 380 X 9 X 1000 | BU10: 2 | BV10: VERBAL | BW10: 44026 | BX10: 10 | BY10: BOB | BZ10: 53.48 | CB10: 44033 | CC10: 44040 | CD10: 59159 | CE10: 12 | CF10: =(CE10-BX10) -> 2 | CG10: =(CE10*BZ10) -> 641.76 | CH10: =(CG10*0.05) -> 32.088 | DE10: CONJUNTO ENVASE MEL 200G | DF10: 126 | DH10: 42769 | DI10: 45 | DJ10: Mil | DK10: 842.76 | DM10: 42828 | DN10: 42849 | DO10: 12801 | DP10: 45000 | DQ10: =(DI10*1000-DP10) -> 0 | DR10: =(DK10*DP10/1000) -> 37924.2 | DS10: =(DN10+42) -> 42891 | DT10: =(DR10*0.03) -> 1137.726
B11: CCS | E11: =(DA15) -> 1175.5135 | F11: =(DA28) -> 1210.7997 | G11: =(DA49) -> 1208.115 | H11: =(DA62) -> 0 | I11: =(DA75) -> 1245.375 | J11: 1140.27 | K11: =(DA103) -> 1245.375 | L11: =(DA117) -> 0 | M11: 1137.73 | N11: =(DA143) -> 1329.075 | P11: CACO | Q11: CUMBUCA 500 G - MA 15 | R11: 5 | S11: VERBAL | T11: 42709 | U11: 10 | V11: MIL | W11: 315 | Y11: 42716 | Z11: 42716 | AA11: 1566 | AB11: 10000 | AC11: =(AB11-U11*1000) -> 0 | AD11: =(AB11*W11/1000) -> 3150 | AE11: =(AD11*0.05) -> 157.5 | AF11: PAGO | AJ11: CUMBUCA 500 G - MA15 | AK11: 3 | AL11: VERBAL | AM11: 42682 | AN11: 10 | AO11: MIL | AP11: 305 | AR11: 42685 | AS11: 42688 | AT11: 1476 | AU11: 10000 | AV11: =(AU11-AN11*1000) -> 0 | AW11: =(AU11*AP11/1000) -> 3050 | AX11: =(AW11*0.05) -> 152.5 | BT11: FILME PVC GA 300 X 9 X 1000 | BU11: 2 | BV11: VERBAL | BW11: 44026 | BX11: 20 | BY11: BOB | BZ11: 42.27 | CB11: 44033 | CC11: 44040 | CD11: 59159 | CE11: 24 | CF11: =(CE11-BX11) -> 4 | CG11: =(CE11*BZ11) -> 1014.48 | CH11: =(CG11*0.05) -> 50.724 | DE11: CONJUNTO ENVASE MEL 200G | DF11: 127 | DH11: 42769 | DI11: 45 | DJ11: Mil | DK11: 842.76 | DM11: 42857 | DN11: 42857 | DP11: 45000 | DQ11: =(DI11*1000-DP11) -> 0 | DR11: =(DK11*DP11/1000) -> 37924.2 | DS11: =(DN11+42) -> 42899 | DT11: =(DR11*0.03) -> 1137.726
P12: AURORA | Q12: CUMBUCA 500 G - MA 15 | R12: 2 | S12: E-MAIL | T12: 42711 | U12: 10 | V12: MIL | W12: 335 | Y12: 42716 | Z12: 42716 | AA12: 1567 | AB12: 10000 | AC12: =(AB12-U12*1000) -> 0 | AD12: =(AB12*W12/1000) -> 3350 | AE12: =(AD12*0.05) -> 167.5 | AF12: PAGO | AJ12: CUMBUCA 500 G - MA15 | AK12: 4 | AL12: E-MAIL | AM12: 42686 | AN12: 200 | AO12: MIL | AP12: 300 | AR12: 42691 | AS12: 42688 | AT12: 1467 | AU12: 200000 | AV12: =(AU12-AN12*1000) -> 0 | AW12: =(AU12*AP12/1000) -> 60000 | AX12: =(AW12*0.05) -> 3000 | BO12: =SUM(BO8:BO10) -> 8293.6 | BP12: =(BO12*0.05) -> 414.68 | DE12: CONJUNTO ENVASE MEL 200G | DF12: 128 | DH12: 42769 | DI12: 45 | DJ12: MIL | DK12: 842.76 | DM12: 42892 | DN12: 42892 | DP12: 45000 | DQ12: =(DI12*1000-DP12) -> 0 | DR12: =(DK12*DP12/1000) -> 37924.2 | DS12: =(DN12+42) -> 42934 | DT12: =(DR12*0.03) -> 1137.726
B13: BRASIL SUL | E13: =(BP12) -> 414.68 | F13: 0 | G13: =(BP40) -> 1923.8459 | H13: =(BP51) -> 931.49976 | I13: =(BP59) -> 150.6666 | J13: =(BP70) -> 640.37392 | K13: =(BP80) -> 123.538 | L13: =(BP96) -> 1174.8885 | M13: =(BP106) -> 504.33 | N13: =(BP114) -> 217.5 | P13: BIANCHI | Q13: EMB. OVO GALINHA 10 UND SRG - C10 | R13: 4 | S13: verbal | T13: 42712 | U13: 20 | V13: MIL | W13: 255 | Y13: 42716 | Z13: 42714 | AA13: 1563 | AB13: 20000 | AC13: =(AB13-U13*1000) -> 0 | AD13: =(AB13*W13/1000) -> 5100 | AE13: =(AD13*0.05) -> 255 | AF13: PAGO | AJ13: CUMBUCA 500 G - MA15 | AK13: 5 | AL13: VERBAL | AM13: 42916 | AN13: 30 | AO13: MIL | AP13: 300 | AR13: 42922 | AS13: 42919 | AT13: 2066 | AU13: 30000 | AV13: =(AU13-AN13*1000) -> 0 | AW13: =(AU13*AP13/1000) -> 9000 | AX13: =(AW13*0.05) -> 450 | DE13: CONJUNTO ENVASE MEL 200G | DF13: 129 | DH13: 42971 | DI13: 45 | DJ13: MIL | DK13: 842.76 | DM13: 42975 | DN13: 42975 | DP13: 45000 | DQ13: =(DI13*1000-DP13) -> 0 | DR13: =(DK13*DP13/1000) -> 37924.2 | DS13: =(DN13+42) -> 43017 | DT13: =(DR13*0.03) -> 1137.726
P14: MAPE | Q14: CUMBUCA 500 G - MA15 | R14: 7 | S14: verbal | T14: 42718 | U14: 50 | V14: MIL | W14: 305 | Y14: 42725 | Z14: 42719 | AA14: 1593 | AB14: 50000 | AC14: =(AB14-U14*1000) -> 0 | AD14: =(AB14*W14/1000) -> 15250 | AE14: 750 | AF14: PAGO | AJ14: CUMBUCA 500 G - MA15 CRISTAL | AK14: 6 | AL14: VERBAL | AM14: 43392 | AN14: 100 | AO14: MIL | AP14: 290 | AR14: 43402 | AS14: 43399 | AT14: 3383 | AU14: 100000 | AV14: =(AU14-AN14*1000) -> 0 | AW14: =(AU14*AP14/1000) -> 29000 | AX14: =(AW14*0.05) -> 1450 | BA14: BRASIL SUL ABRIL 2017 | DE14: CONJUNTO ENVASE MEL 200G | DF14: 130 | DH14: 43019 | DI14: 45 | DJ14: MIL | DK14: 868.82 | DM14: 43056 | DN14: 43056 | DP14: 45000 | DQ14: =(DI14*1000-DP14) -> 0 | DR14: =(DK14*DP14/1000) -> 39096.9 | DS14: =(DN14+42) -> 43098 | DT14: =(DR14*0.03) -> 1172.907
P15: LOSCHI & WATANABE | Q15: CUMBUCA 500 G - MA 15 | R15: 2 | S15: verbal | T15: 42720 | U15: 80 | V15: MIL | W15: 300 | Y15: 42725 | Z15: 42723 | AA15: 1602 | AB15: 80000 | AC15: =(AB15-U15*1000) -> 0 | AD15: =(AB15*W15/1000) -> 24000 | AE15: =(AD15*0.05) -> 1200 | AF15: PAGO | AJ15: CUMBUCA 500 G - MA15 CRISTAL | AK15: 7 | AL15: VERBAL | AM15: 43392 | AN15: 100 | AO15: MIL | AP15: 290 | AR15: 43437 | AS15: 43438 | AT15: 10636 | AU15: 50000 | AV15: =(AU15-AN15*1000) -> -50000 | AW15: =(AU15*AP15/1000) -> 14500 | AX15: =(AW15*0.05) -> 725 | BD15: OC | BE15: DATA | BH15: PREÇO | BI15: CODIGO | BJ15: DATA | BK15: DATA | BP15: VALOR DA | CY15: =SUM(CY8:CY14) -> 39183.782 | DA15: =SUM(DA8:DA14) -> 1175.5135 | DE15: CONJUNTO ENVASE MEL 200G | DF15: 131 | DH15: 43125 | DI15: 45 | DJ15: MIL | DK15: 868.82 | DM15: 43151 | DN15: =(DM15) -> 43151 | DO15: 13182/13191 | DP15: 45100 | DQ15: =(DI15*1000-DP15) -> -100 | DR15: =(DK15*DP15/1000) -> 39183.782 | DS15: =(DN15+42) -> 43193 | DT15: =(DR15*0.03) -> 1175.5135
AJ16: CUMBUCA 500 G - MA15 CRISTAL | AK16: 7 | AL16: VERBAL | AM16: 43392 | AN16: 50 | AO16: MIL | AP16: 290 | AR16: 43437 | AS16: 43437 | AU16: 50000 | AV16: =(AU16-AN16*1000) -> 0 | AW16: =(AU16*AP16/1000) -> 14500 | AX16: =(AW16*0.05) -> 725 | AY16: CANCELADO | BA16: CLIENTE | BB16: PRODUTO | BC16: PEDIDO | BD16: DO | BE16: DO | BF16: QUANT | BG16: UND | BH16: POR | BI16: DO | BJ16: DE | BK16: DE | BL16: N F | BM16: QUANT | BN16: SALDO | BO16: VALOR | BP16: COMISSÃO | BQ16: OBSERVAÇÃO | DE16: CONJUNTO ENVASE MEL 200G | DF16: 132 | DH16: 43125 | DI16: 45 | DJ16: MIL | DK16: 894.9 | DM16: 43179 | DN16: 43182 | DO16: 13255 | DP16: 45000 | DQ16: =(DI16*1000-DP16) -> 0 | DR16: 40359.99 | DS16: =(DN16+42) -> 43224 | DT16: =(DR16*0.03) -> 1210.7997
AD17: =SUM(AD8:AD16) -> 87712 | AE17: =(AD17*0.05) -> 4385.6 | AJ17: CUMBUCA 500 G - MA15 CRISTAL | AK17: 8 | AL17: VERBAL | AM17: 43549 | AN17: 30 | AO17: MIL | AP17: 290 | AR17: 43556 | AS17: 43573 | AT17: 3749 | AU17: 30000 | AV17: =(AU17-AN17*1000) -> 0 | AW17: =(AU17*AP17/1000) -> 8700 | AX17: =(AW17*0.05) -> 435 | BD17: CLIENTE | BE17: PEDIDO | BH17: UND | BI17: CLIENTE | BJ17: ENTREGA | BK17: FATURA | BP17: R$ | CG17: =SUM(CG8:CG16) -> 3574.2 | CH17: =SUM(CH8:CH16) -> 178.71 | CK17: CCS ABRIL 2018 | DE17: CONJUNTO ENVASE MEL 200G | DF17: 133 | DH17: 43125 | DI17: 45 | DJ17: MIL | DK17: 894.9 | DM17: 43214 | DN17: 43217 | DO17: 13315 | DP17: 45000 | DQ17: =(DI17*1000-DP17) -> 0 | DR17: =(DK17*DP17/1000) -> 40270.5 | DS17: =(DN17+42) -> 43259 | DT17: =(DR17*0.03) -> 1208.115 | DW17: EDIPRINT NOVEMBRO 2021
B18: TOTAL | C18: =SUM(C7:C17) -> 4385.6 | D18: =SUM(D7:D17) -> 818.75 | E18: =SUM(E7:E17) -> 3041.5935 | F18: =SUM(F7:F17) -> 3089.7997 | G18: =SUM(G7:G17) -> 7151.4609 | H18: =(H7+H11+H13) -> 4017.8498 | I18: =SUM(I7:I17) -> 3329.0416 | J18: =SUM(J7:J17) -> 5337.5439 | K18: =SUM(K7:K17) -> 6613.913 | L18: =SUM(L7:L17) -> 1407.6385 | M18: =SUM(M7:M17) -> 9943.06 | N18: =SUM(N7:N17) -> 8906.075 | O18: =SUM(C18:N18) -> 58042.326 | AJ18: CUMBUCA 500 G - MA15 CRISTAL | AK18: 9 | AL18: VERBAL | AM18: 43621 | AN18: 40 | AO18: MIL | AP18: 276 | AR18: 43626 | AS18: 43623 | AT18: 3813 | AU18: 40000 | AV18: =(AU18-AN18*1000) -> 0 | AW18: =(AU18*AP18/1000) -> 11040 | AX18: =(AW18*0.05) -> 552 | BT18: CABELAUTO | BU18: THIAGO NUNES - 35 3629-2500 / 2544 | CA18: CAUÃ | CN18: OC | CO18: DATA | CR18: PREÇO | CS18: CODIGO | CT18: DATA | CU18: DATA | CZ18: DATA | DA18: VALOR DA | DE18: CONJUNTO ENVASE MEL 200G | DF18: 134 | DH18: 43125 | DI18: 45 | DJ18: MIL | DK18: 922.5 | DM18: 43255 | DN18: 43255 | DO18: 13367 | DP18: 45000 | DQ18: =(DI18*1000-DP18) -> 0 | DR18: =(DK18*DP18/1000) -> 41512.5 | DS18: =(DN18+42) -> 43297 | DT18: =(DR18*0.03) -> 1245.375 | DZ18: OC | EA18: DATA | ED18: PREÇO | EE18: CODIGO | EF18: DATA | EG18: DATA | EL18: DATA | EM18: VALOR DA
N19: =(O18) -> 58042.326 | P19: SERRAPLAST FEVEREIRO 2017 | AJ19: CUMBUCA 500 G - MA15 CRISTAL | AK19: 10 | AL19: VERBAL | AM19: 43710 | AN19: 20 | AO19: MIL | AP19: 290 | AR19: 43731 | AS19: 43729 | AT19: 3936 | AU19: 20000 | AV19: =(AU19-AN19*1000) -> 0 | AW19: =(AU19*AP19/1000) -> 5800 | AX19: =(AW19*0.05) -> 290 | BV19: OC | BW19: DATA | BZ19: PREÇO | CA19: CODIGO | CB19: DATA | CC19: DATA | CH19: VALOR DA | CK19: CLIENTE | CL19: PRODUTO | CM19: PEDIDO | CN19: DO | CO19: DO | CP19: QUANT | CQ19: UND | CR19: POR | CS19: DO | CT19: DE | CU19: DE | CV19: N F | CW19: QUANT | CX19: SALDO | CY19: VALOR | CZ19: COMISSÃO | DA19: COMISSÃO | DB19: OBSERVAÇÃO | DE19: CONJUNTO ENVASE MEL 200G | DF19: 135 | DH19: 43125 | DI19: 45 | DJ19: MIL | DK19: 922.5 | DM19: 43285 | DN19: 43291 | DO19: 13424 | DP19: 45000 | DQ19: =(DI19*1000-DP19) -> 0 | DR19: =(DK19*DP19/1000) -> 41512.5 | DS19: =(DN19+42) -> 43333 | DT19: =(DR19*0.03) -> 1245.375 | DW19: CLIENTE | DX19: PRODUTO | DY19: PEDIDO | DZ19: DO | EA19: DO | EB19: QUANT | EC19: UND | ED19: POR | EE19: DO | EF19: DE | EG19: DE | EH19: N F | EI19: QUANT | EJ19: SALDO | EK19: VALOR | EL19: COMISSÃO | EM19: COMISSÃO | EN19: OBSERVAÇÃO
B20: 2018 | S20: OC | T20: DATA | W20: PREÇO | X20: CODIGO | Y20: DATA | Z20: DATA | AE20: VALOR DA | AJ20: CUMBUCA 500 G - MA15 CRISTAL | AK20: 11 | AL20: VERBAL | AM20: 43781 | AN20: 100 | AO20: MIL | AP20: 330 | AR20: 43787 | AS20: 43787 | AT20: 3981 | AU20: 89000 | AV20: =(AU20-AN20*1000) -> -11000 | AW20: =(AU20*AP20/1000) -> 29370 | AX20: =(AW20*0.05) -> 1468.5 | BT20: PRODUTO | BU20: PEDIDO | BV20: DO | BW20: DO | BX20: QUANT | BY20: UND | BZ20: POR | CA20: DO | CB20: DE | CC20: DE | CD20: N F | CE20: QUANT | CF20: SALDO | CG20: VALOR | CH20: COMISSÃO | CI20: OBSERVAÇÃO | CN20: CLIENTE | CO20: PEDIDO | CR20: UND | CS20: CLIENTE | CT20: ENTREGA | CU20: FATURA | CZ20: 30 DD | DA20: R$ | DE20: CONJUNTO ENVASE MEL 200G | DF20: 136 | DH20: 43125 | DI20: 45 | DJ20: MIL | DK20: 922.5 | DM20: 43318 | DN20: 43313 | DO20: 13457 | DP20: 45000 | DQ20: =(DI20*1000-DP20) -> 0 | DR20: =(DK20*DP20/1000) -> 41512.5 | DS20: =(DN20+42) -> 43355 | DT20: =(DR20*0.03) -> 1245.375 | DZ20: CLIENTE | EA20: PEDIDO | ED20: UND | EE20: CLIENTE | EF20: ENTREGA | EG20: FATURA | EL20: 30 DD | EM20: R$
B21: REPRESENTADA | C21: JAN 12 | D21: FEV 01 | E21: MAR 02 | F21: ABR 03 | G21: MAI 04 | H21: JUN 05 | I21: JUL 06 | J21: AGO 07 | K21: SET 08 | L21: OUT 09 | M21: NOV 10 | N21: DEZ 11 | P21: CLIENTE | Q21: PRODUTO | R21: PEDIDO | S21: DO | T21: DO | U21: QUANT | V21: UND | W21: POR | X21: DO | Y21: DE | Z21: DE | AA21: N F | AB21: QUANT | AC21: SALDO | AD21: VALOR | AE21: COMISSÃO | AF21: OBSERVAÇÃO | AJ21: CUMBUCA 500 G - MA15 CRISTAL | AK21: 11 | AL21: VERBAL | AM21: 43781 | AN21: 11 | AO21: MIL | AP21: 330 | AR21: 43787 | AS21: 43793 | AT21: 3987 | AU21: 11000 | AV21: =(AU21-AN21*1000) -> 0 | AW21: =(AU21*AP21/1000) -> 3630 | AX21: =(AW21*0.05) -> 181.5 | BV21: CLIENTE | BW21: PEDIDO | BZ21: UND | CA21: CLIENTE | CB21: ENTREGA | CC21: FATURA | CH21: R$ | CK21: SUPERBOM | CL21: CONJUNTO ENVASE MEL 200G | CM21: 132 | CO21: 43125 | CP21: 45 | CQ21: MIL | CR21: 894.9 | CT21: 43179 | CU21: 43182 | CV21: 13255 | CW21: 45000 | CX21: =(CP21*1000-CW21) -> 0 | CY21: 40359.99 | CZ21: =(CU21+42) -> 43224 | DA21: =(CY21*0.03) -> 1210.7997 | DE21: CONJUNTO ENVASE MEL 200G | DF21: 137 | DH21: 43377 | DI21: 45 | DJ21: MIL | DK21: 984.5 | DM21: 43411 | DN21: 43427 | DO21: 13588 | DP21: 45000 | DQ21: =(DI21*1000-DP21) -> 0 | DR21: =(DK21*DP21/1000) -> 44302.5 | DS21: =(DN21+42) -> 43469 | DT21: =(DR21*0.03) -> 1329.075 | DW21: HORTA VITAE | DX21: ETIQUETA ADESIVA OVO CAIPIRA TG 20 UND | DY21: 1 | DZ21: E-MAIL | EA21: 44469 | EB21: 30 | EC21: MIL | ED21: 145.65 | EF21: 44480 | EG21: 44480 | EI21: 30000 | EJ21: =(EI21-EB21*1000) -> 0 | EK21: =(EI21*ED21/1000) -> 4369.5 | EM21: =(EK21*0.04) -> 174.78
S22: CLIENTE | T22: PEDIDO | W22: UND | X22: CLIENTE | Y22: ENTREGA | Z22: FATURA | AE22: R$ | AJ22: CUMBUCA 500 G - MA15 CRISTAL | AK22: 12 | AL22: VERBAL | AM22: 43781 | AN22: 11 | AO22: MIL | AP22: 330 | AR22: 43787 | AS22: 43793 | AT22: 3987 | AU22: 11000 | AV22: =(AU22-AN22*1000) -> 0 | AW22: =(AU22*AP22/1000) -> 3630 | AX22: =(AW22*0.05) -> 181.5 | BT22: FILME PVC ESTICAVEL 200 MM X 25 MICRA | BU22: 1 | BV22: VERBAL | BW22: 44365 | BX22: 1 | BY22: BOB | BZ22: 21.24 | CB22: 44377 | CE22: 1 | CF22: =(CE22-BX22) -> 0 | CG22: =(CE22*BZ22) -> 21.24 | CH22: =(CG22*0.05) -> 1.062 | DE22: CONJUNTO ENVASE MEL 200G | DF22: 138 | DH22: 43377 | DI22: 45 | DJ22: MIL | DK22: 984.5 | DM22: 43452 | DN22: 43490 | DO22: 13675 | DP22: 45000 | DQ22: =(DI22*1000-DP22) -> 0 | DR22: =(DK22*DP22/1000) -> 44302.5 | DS22: =(DN22+42) -> 43532 | DT22: =(DR22*0.03) -> 1329.075
B23: SERRAPLAST | C23: =(AE198) -> 6454.25 | D23: =(AE215) -> 6903.57 | E23: =(AE234) -> 8595.95 | F23: =(AE251) -> 5641.25 | G23: =(AE264) -> 2288 | H23: =(AE281) -> 6637.6 | I23: =(AE297) -> 5369.3 | J23: =(AE316) -> 7034.55 | K23: =(AE335) -> 7028.25 | L23: =(AE354) -> 4780.6 | M23: =(AE369) -> 6273 | N23: =(AE385) -> 5321.1875 | P23: CACO | Q23: CUMBUCA 500 G - MA 15 | R23: 6 | S23: VERBAL | T23: 42758 | U23: 15 | V23: MIL | W23: 335 | Y23: 42762 | Z23: 42758 | AA23: 1650 | AB23: 15000 | AC23: =(AB23-U23*1000) -> 0 | AD23: =(AB23*W23/1000) -> 5025 | AE23: =(AD23*0.05) -> 251.25 | AF23: PAGO | AJ23: CUMBUCA 500 G - MA15 CRISTAL | AK23: 13 | AL23: WHATSAPP | AM23: 43874 | AN23: 30 | AO23: MIL | AP23: 330 | AR23: 43881 | AS23: 43878 | AT23: 12628 | AU23: 30000 | AV23: =(AU23-AN23*1000) -> 0 | AW23: =(AU23*AP23/1000) -> 9900 | AX23: =(AW23*0.05) -> 495 | BT23: FILME PVC ESTICAVEL 500 MM X 25 MICRA | BU23: 2 | BV23: VERBAL | BW23: 44365 | BX23: 1 | BY23: BOB | BZ23: 21.24 | CB23: 44377 | CE23: 1 | CF23: =(CE23-BX23) -> 0 | CG23: =(CE23*BZ23) -> 21.24 | CH23: =(CG23*0.05) -> 1.062 | DE23: CONJUNTO ENVASE MEL 200G | DF23: 139 | DH23: 43496 | DI23: 45 | DJ23: MIL | DK23: 1018.96 | DM23: 43507 | DN23: 43514 | DO23: 13701 | DP23: 45000 | DQ23: =(DI23*1000-DP23) -> 0 | DR23: =(DK23*DP23/1000) -> 45853.2 | DS23: =(DN23+42) -> 43556 | DT23: =(DR23*0.03) -> 1375.596
P24: GO GREEN | Q24: CUMBUCA 500 G - MA 15 | R24: 3 | S24: VERBAL | T24: 42762 | U24: 20 | V24: MIL | W24: 315 | Y24: 42765 | Z24: 42765 | AA24: 9326 | AB24: 20000 | AC24: =(AB24-U24*1000) -> 0 | AD24: =(AB24*W24/1000) -> 6300 | AE24: =(AD24*0.05) -> 315 | AF24: PAGO | AJ24: CUMBUCA 500 G - MA15 CRISTAL | AK24: 14 | AL24: WHATSAPP | AM24: 43972 | AN24: 20 | AO24: MIL | AP24: 310 | AR24: 43976 | AS24: 43976 | AT24: 13174 | AU24: 20000 | AV24: =(AU24-AN24*1000) -> 0 | AW24: =(AU24*AP24/1000) -> 6200 | AX24: =(AW24*0.05) -> 310 | BT24: FILME PVC EST. 50 MM X 25 MICRA | BU24: 3 | BV24: 4500031322 | BW24: 44466 | BX24: 300 | BY24: BOB | BZ24: 17.32 | CB24: 44483 | CC24: 44483 | CD24: 63461 | CE24: 300.55 | CF24: =(CE24-BX24) -> 0.55 | CG24: =(CE24*BZ24) -> 5205.526 | CH24: =(CG24*0.025) -> 130.13815 | DE24: CONJUNTO ENVASE MEL 200G | DF24: 140 | DH24: 43496 | DI24: 45 | DJ24: MIL | DK24: 1018.96 | DM24: 43535 | DN24: 43621 | DO24: 13848 | DP24: 45000 | DQ24: =(DI24*1000-DP24) -> 0 | DR24: =(DK24*DP24/1000) -> 45853.2 | DS24: =(DN24+42) -> 43663 | DT24: =(DR24*0.03) -> 1375.596
B25: QUADRANTE | P25: GO GREEN | Q25: EMBALAGEM TOMATINHO - SRT 08 | R25: 4 | S25: VERBAL | T25: 42762 | U25: 30 | V25: MIL | W25: 154 | Y25: 42765 | Z25: 42765 | AA25: 9326 | AB25: 30000 | AC25: =(AB25-U25*1000) -> 0 | AD25: =(AB25*W25/1000) -> 4620 | AE25: =(AD25*0.05) -> 231 | AF25: PAGO | AJ25: CUMBUCA 500 G - MA15 CRISTAL | AK25: 15 | AL25: WHATSAPP | AM25: 43972 | AN25: 20 | AO25: MIL | AP25: 310 | AR25: 44011 | AS25: 44005 | AT25: 13316 | AU25: 20000 | AV25: =(AU25-AN25*1000) -> 0 | AW25: =(AU25*AP25/1000) -> 6200 | AX25: =(AW25*0.05) -> 310 | DE25: CONJUNTO ENVASE MEL 200G | DF25: 141 | DH25: 43496 | DI25: 45 | DJ25: MIL | DK25: 1018.96 | DM25: 43598 | DN25: 43602 | DO25: 13817 | DP25: 45000 | DQ25: =(DI25*1000-DP25) -> 0 | DR25: =(DK25*DP25/1000) -> 45853.2 | DS25: =(DN25+42) -> 43644 | DT25: =(DR25*0.03) -> 1375.596
P26: JOSE PAULO LAZZARI | Q26: EMB. OVO GALINHA 10 UND SRG - C10 | R26: 1 | S26: E-MAIL | T26: 42754 | U26: 1 | V26: MIL | W26: 430 | Y26: 42758 | Z26: 42766 | AA26: 9334 | AB26: 1000 | AC26: =(AB26-U26*1000) -> 0 | AD26: =(AB26*W26/1000) -> 430 | AE26: =(AD26*0.05) -> 21.5 | AF26: PAGO | AJ26: CUMBUCA 500 G - MA15 CRISTAL | AK26: 16 | AL26: WHATSAPP | AM26: 44034 | AN26: 30 | AO26: MIL | AP26: 310 | AR26: 44039 | AS26: 44037 | AT26: 13509 | AU26: 30000 | AV26: =(AU26-AN26*1000) -> 0 | AW26: =(AU26*AP26/1000) -> 9300 | AX26: =(AW26*0.05) -> 465 | DE26: CONJUNTO ENVASE MEL 200G | DF26: 142 | DH26: 43496 | DI26: 45 | DJ26: MIL | DK26: 1018.96 | DM26: 43626 | DN26: 43679 | DO26: 13923 | DP26: 45000 | DQ26: =(DI26*1000-DP26) -> 0 | DR26: =(DK26*DP26/1000) -> 45853.2 | DS26: =(DN26+42) -> 43721 | DT26: =(DR26*0.03) -> 1375.596
B27: CCS | C27: 1172.93 | D27: =(DA15) -> 1175.5135 | E27: =(DA28) -> 1210.7997 | F27: =(DA49) -> 1208.115 | G27: =(DA62) -> 0 | H27: =(DA75) -> 1245.375 | I27: =(DA68) -> 1245.375 | J27: =(DA90) -> 1245.375 | K27: 1245.38 | N27: =(DA136) -> 1329.075 | AJ27: CUMBUCA 500 G - MA15 CRISTAL | AK27: 17 | AL27: WHATSAPP | AM27: 44057 | AN27: 60 | AO27: MIL | AP27: 310 | AR27: 44067 | AS27: 44061 | AT27: 13686 | AU27: 60000 | AV27: =(AU27-AN27*1000) -> 0 | AW27: =(AU27*AP27/1000) -> 18600 | AX27: =(AW27*0.05) -> 930 | BA27: BRASIL SUL MAIO 2017 | DE27: CONJUNTO ENVASE MEL 200G | DF27: 143 | DH27: 43514 | DI27: 45 | DJ27: MIL | DK27: 1018.96 | DM27: 43564 | DN27: 43556 | DO27: 13759 | DP27: 45000 | DQ27: =(DI27*1000-DP27) -> 0 | DR27: =(DK27*DP27/1000) -> 45853.2 | DS27: =(DN27+42) -> 43598 | DT27: =(DR27*0.03) -> 1375.596
AD28: =SUM(AD23:AD27) -> 16375 | AE28: =(AD28*0.05) -> 818.75 | AJ28: CUMBUCA 500 G - MA15 CRISTAL | AK28: 18 | AL28: WHATSAPP | AM28: 44162 | AN28: 30 | AO28: MIL | AP28: 355 | AR28: 44172 | AS28: 44173 | AT28: 14477 | AU28: 30000 | AV28: =(AU28-AN28*1000) -> 0 | AW28: =(AU28*AP28/1000) -> 10650 | AX28: =(AW28*0.05) -> 532.5 | BD28: OC | BE28: DATA | BH28: PREÇO | BI28: CODIGO | BJ28: DATA | BK28: DATA | BP28: VALOR DA | BT28: COBREFLEX | BU28: ROBERTO R. LABLEUK 11 4707-0650 | BZ28: GIOVANI | CY28: =SUM(CY21:CY27) -> 40359.99 | DA28: =SUM(DA21:DA27) -> 1210.7997 | DE28: CONJUNTO ENVASE MEL 200G | DF28: 144 | DI28: 45 | DJ28: MIL | DK28: 1018.96 | DM28: 43854 | DN28: 43854 | DO28: 14150 | DP28: 45000 | DQ28: =(DI28*1000-DP28) -> 0 | DR28: =(DK28*DP28/1000) -> 45853.2 | DS28: =(DN28+42) -> 43896 | DT28: =(DR28*0.03) -> 1375.596 | DU28: PAGO | EK28: =SUM(EK21:EK27) -> 4369.5 | EM28: =SUM(EM21:EM27) -> 174.78
B29: BRASIL SUL | C29: =(BP123) -> 435 | D29: =(BP132) -> 439.41525 | E29: =(BP141) -> 438.2886 | F29: =(BP151) -> 606.35 | G29: =(BP159) -> 228.25 | H29: =(BP168) -> 255.25 | I29: =(BP177) -> 271.75942 | J29: =(BP187) -> 634.32764 | K29: =(BP199) -> 993.4542 | L29: =(BP208) -> 485.97156 | M29: =(BP218) -> 677.45808 | N29: =(BP230) -> 1982.3908 | AJ29: CUMBUCA 500 G - MA15 CRISTAL | AK29: 19 | AL29: WHATSAPP | AM29: 44215 | AN29: 20 | AO29: MIL | AP29: 390 | AR29: 44217 | AS29: 44225 | AT29: 14820 | AU29: 20000 | AV29: =(AU29-AN29*1000) -> 0 | AW29: =(AU29*AP29/1000) -> 7800 | AX29: =(AW29*0.05) -> 390 | BA29: CLIENTE | BB29: PRODUTO | BC29: PEDIDO | BD29: DO | BE29: DO | BF29: QUANT | BG29: UND | BH29: POR | BI29: DO | BJ29: DE | BK29: DE | BL29: N F | BM29: QUANT | BN29: SALDO | BO29: VALOR | BP29: COMISSÃO | BQ29: OBSERVAÇÃO | BV29: OC | BW29: DATA | BZ29: PREÇO | CA29: CODIGO | CB29: DATA | CC29: DATA | CH29: VALOR DA | DE29: CONJUNTO ENVASE MEL 200G | DF29: 144 | DG29: VERBAL | DH29: 43867 | DI29: 45 | DJ29: MIL | DK29: 1111.57 | DM29: 43885 | DN29: 43880 | DO29: 14181 | DP29: 45000 | DQ29: =(DI29*1000-DP29) -> 0 | DR29: =(DK29*DP29/1000) -> 50020.65 | DS29: =(DN29+42) -> 43922 | DT29: =(DR29*0.03) -> 1500.6195 | DU29: PAGO
P30: SERRAPLAST MARÇO 2017 | AJ30: CUMBUCA 500 G - MA15 CRISTAL | AK30: 20 | AL30: WHATSAPP | AM30: 44264 | AN30: 30 | AO30: MIL | AP30: 350 | AR30: 44267 | AS30: 44265 | AT30: 15109 | AU30: 30000 | AV30: =(AU30-AN30*1000) -> 0 | AW30: =(AU30*AP30/1000) -> 10500 | AX30: =(AW30*0.05) -> 525 | BD30: CLIENTE | BE30: PEDIDO | BH30: UND | BI30: CLIENTE | BJ30: ENTREGA | BK30: FATURA | BP30: R$ | BT30: PRODUTO | BU30: PEDIDO | BV30: DO | BW30: DO | BX30: QUANT | BY30: UND | BZ30: POR | CA30: DO | CB30: DE | CC30: DE | CD30: N F | CE30: QUANT | CF30: SALDO | CG30: VALOR | CH30: COMISSÃO | CI30: OBSERVAÇÃO | CK30: CCS MAIO 2018 | DE30: CONJUNTO ENVASE MEL 200G | DF30: 145 | DG30: VERBAL | DH30: 43867 | DI30: 45 | DJ30: MIL | DK30: 1111.57 | DM30: 43914 | DN30: 43929 | DO30: 14265 | DP30: 45000 | DQ30: =(DI30*1000-DP30) -> 0 | DR30: =(DK30*DP30/1000) -> 50020.65 | DS30: =(DN30+42) -> 43971 | DT30: =(DR30*0.03) -> 1500.6195 | DU30: PAGO | DW30: EDIPRINT DEZEMBRO 2021
S31: OC | T31: DATA | W31: PREÇO | X31: CODIGO | Y31: DATA | Z31: DATA | AE31: VALOR DA | AJ31: CUMBUCA 500 G - MA15 CRISTAL | AK31: 21 | AL31: WHATSAPP | AM31: 44312 | AN31: 40 | AO31: MIL | AP31: 335 | AR31: 44312 | AS31: 44313 | AT31: 15380 | AU31: 30000 | AV31: =(AU31-AN31*1000) -> -10000 | AW31: =(AU31*AP31/1000) -> 10050 | AX31: =(AW31*0.05) -> 502.5 | BA31: METALFLEX | BB31: FILME PVC EST. 60 MM X 40 MICRA | BC31: 1 | BD31: e-mail | BE31: 42822 | BF31: 1000 | BG31: KG | BH31: 9.7 | BJ31: 42829 | BK31: 42829 | BL31: 46790 | BM31: 1010.66 | BN31: =(BM31-BF31) -> 10.66 | BO31: 8792.74 | BP31: =(BO31*0.05) -> 439.637 | BQ31: PAGO | BV31: CLIENTE | BW31: PEDIDO | BZ31: UND | CA31: CLIENTE | CB31: ENTREGA | CC31: FATURA | CH31: R$ | CN31: OC | CO31: DATA | CR31: PREÇO | CS31: CODIGO | CT31: DATA | CU31: DATA | CZ31: DATA | DA31: VALOR DA | DE31: CONJUNTO ENVASE MEL 200G | DF31: 146 | DG31: VERBAL | DH31: 43937 | DI31: 45 | DJ31: MIL | DK31: 1111.57 | DM31: 43969 | DN31: 43966 | DO31: 14326 | DP31: 45100 | DQ31: =(DI31*1000-DP31) -> -100 | DR31: =(DK31*DP31/1000) -> 50131.807 | DS31: =(DN31+42) -> 44008 | DT31: =(DR31*0.03) -> 1503.9542 | DU31: PAGO | DZ31: OC | EA31: DATA | ED31: PREÇO | EE31: CODIGO | EF31: DATA | EG31: DATA | EL31: DATA | EM31: VALOR DA
P32: CLIENTE | Q32: PRODUTO | R32: PEDIDO | S32: DO | T32: DO | U32: QUANT | V32: UND | W32: POR | X32: DO | Y32: DE | Z32: DE | AA32: N F | AB32: QUANT | AC32: SALDO | AD32: VALOR | AE32: COMISSÃO | AF32: OBSERVAÇÃO | AJ32: CUMBUCA 500 G - MA15 CRISTAL | AK32: 21 | AL32: WHATSAPP | AM32: 44312 | AN32: 10 | AO32: MIL | AP32: 335 | AR32: 44312 | AS32: 44319 | AT32: 15408 | AU32: 10000 | AV32: =(AU32-AN32*1000) -> 0 | AW32: =(AU32*AP32/1000) -> 3350 | AX32: =(AW32*0.05) -> 167.5 | BA32: COBREMACK BH | BB32: FILME PVC EST. 60 MM X 40 MICRA | BC32: 1 | BE32: 42824 | BF32: 1000 | BG32: KG | BH32: 9.7 | BJ32: 42830 | BK32: 42830 | BL32: 46765 | BM32: 255.5 | BN32: =(BM32-BF32) -> -744.5 | BO32: =(BM32*BH32) -> 2478.35 | BP32: =(BO32*0.05) -> 123.9175 | BQ32: PAGO | BT32: FILME PVC EST. 60 MM X 40 MICRA | BU32: 1 | BV32: E-MAIL | BW32: 42995 | BX32: 500 | BY32: KG | BZ32: 8.7 | CB32: 42998 | CC32: 43000 | CD32: 48618 | CE32: 504 | CF32: =(CE32-BX32) -> 4 | CG32: =(CE32*BZ32) -> 4384.8 | CH32: =(CG32*0.05) -> 219.24 | CK32: CLIENTE | CL32: PRODUTO | CM32: PEDIDO | CN32: DO | CO32: DO | CP32: QUANT | CQ32: UND | CR32: POR | CS32: DO | CT32: DE | CU32: DE | CV32: N F | CW32: QUANT | CX32: SALDO | CY32: VALOR | CZ32: COMISSÃO | DA32: COMISSÃO | DB32: OBSERVAÇÃO | DE32: CONJUNTO ENVASE MEL 200G | DF32: 147 | DG32: E-MAIL | DH32: 43979 | DI32: 45 | DJ32: MIL | DK32: 1111.58 | DM32: 43999 | DN32: 43999 | DO32: 14366 | DP32: 45100 | DQ32: =(DI32*1000-DP32) -> -100 | DR32: =(DK32*DP32/1000) -> 50132.258 | DS32: =(DN32+42) -> 44041 | DT32: =(DR32*0.03) -> 1503.9677 | DU32: PAGO | DW32: CLIENTE | DX32: PRODUTO | DY32: PEDIDO | DZ32: DO | EA32: DO | EB32: QUANT | EC32: UND | ED32: POR | EE32: DO | EF32: DE | EG32: DE | EH32: N F | EI32: QUANT | EJ32: SALDO | EK32: VALOR | EL32: COMISSÃO | EM32: COMISSÃO | EN32: OBSERVAÇÃO
S33: CLIENTE | T33: PEDIDO | W33: UND | X33: CLIENTE | Y33: ENTREGA | Z33: FATURA | AE33: R$ | AJ33: CUMBUCA 500 G - MA15 CRISTAL | AK33: 22 | AL33: WHATSAPP | AM33: 44370 | AN33: 40 | AO33: MIL | AP33: 335 | AR33: 44375 | AS33: 44373 | AT33: 15715 | AU33: 40000 | AV33: =(AU33-AN33*1000) -> 0 | AW33: =(AU33*AP33/1000) -> 13400 | AX33: =(AW33*0.05) -> 670 | BF33: 744.5 | BG33: KG | BH33: 9.7 | BJ33: 42830 | BK33: 42843 | BL33: 46862 | BM33: 753.92 | BN33: =(BM33-BF33) -> 9.42 | BO33: =(BM33*BH33) -> 7313.024 | BP33: =(BO33*0.05) -> 365.6512 | BQ33: PAGO | BT33: FILME PVC EST. 60 MM X 40 MICRA | BU33: 2 | BV33: E-MAIL | BW33: 42995 | BX33: 500 | BY33: KG | BZ33: 8.7 | CB33: 43017 | CC33: 43042 | CD33: 48784 | CE33: 518 | CF33: =(CE33-BX33) -> 18 | CG33: =(CE33*BZ33) -> 4506.6 | CH33: =(CG33*0.05) -> 225.33 | CN33: CLIENTE | CO33: PEDIDO | CR33: UND | CS33: CLIENTE | CT33: ENTREGA | CU33: FATURA | CZ33: 30 DD | DA33: R$ | DE33: CONJUNTO ENVASE MEL 200G | DF33: 148 | DG33: VERBAL | DH33: 44004 | DI33: 45 | DJ33: MIL | DK33: 1111.58 | DM33: 44025 | DN33: 44029 | DO33: 14394 | DP33: 45000 | DQ33: =(DI33*1000-DP33) -> 0 | DR33: =(DK33*DP33/1000) -> 50021.1 | DS33: =(DN33+42) -> 44071 | DT33: =(DR33*0.03) -> 1500.633 | DU33: PAGO | DZ33: CLIENTE | EA33: PEDIDO | ED33: UND | EE33: CLIENTE | EF33: ENTREGA | EG33: FATURA | EL33: 30 DD | EM33: R$
B34: TOTAL | C34: =SUM(C23:C33) -> 8062.18 | D34: =SUM(D23:D33) -> 8518.4987 | E34: =SUM(E23:E33) -> 10245.038 | F34: =SUM(F23:F33) -> 7455.715 | G34: =SUM(G23:G33) -> 2516.25 | H34: =(H23+H27+H29) -> 8138.225 | I34: =SUM(I23:I33) -> 6886.4344 | J34: =SUM(J23:J33) -> 8914.2526 | K34: =SUM(K23:K33) -> 9267.0842 | L34: =SUM(L23:L33) -> 5266.5716 | M34: =SUM(M23:M33) -> 6950.4581 | N34: =SUM(N23:N33) -> 8632.6533 | O34: =SUM(C34:N34) -> 90853.361 | P34: BIANCHI | Q34: EMB. OVO GALINHA 10 UND SRG - C10 | R34: 5 | S34: E-MAIL | T34: 42775 | U34: 20 | V34: MIL | W34: 270 | Y34: 42781 | Z34: 42775 | AA34: 9377 | AB34: 20000 | AC34: =(AB34-U34*1000) -> 0 | AD34: =(AB34*W34/1000) -> 5400 | AE34: =(AD34*0.05) -> 270 | AF34: PAGO | AJ34: CUMBUCA 500 G - MA15 CRISTAL | AK34: 23 | AL34: WHATSAPP | AM34: 44439 | AN34: 50 | AO34: MIL | AP34: 328 | AR34: 44439 | AS34: 44439 | AT34: 16093 | AU34: 50000 | AV34: =(AU34-AN34*1000) -> 0 | AW34: =(AU34*AP34/1000) -> 16400 | AX34: =(AW34*0.05) -> 820 | BA34: COBREMACK SP | BB34: FILME PVC EST. 60 MM X 40 MICRA | BC34: 1 | BE34: 42824 | BF34: 1000 | BG34: KG | BH34: 9.7 | BJ34: 42830 | BK34: 42830 | BL34: 46764 | BM34: 272.3 | BN34: =(BM34-BF34) -> -727.7 | BO34: =(BM34*BH34) -> 2641.31 | BP34: =(BO34*0.05) -> 132.0655 | BQ34: PAGO | BT34: FILME PVC EST. 60 MM X 40 MICRA | BU34: 3 | BV34: E-MAIL | BW34: 42995 | BX34: 500 | BY34: KG | BZ34: 8.7 | CB34: 43031 | CC34: 43040 | CD34: 49070 | CE34: 508.72 | CF34: =(CE34-BX34) -> 8.72 | CG34: =(CE34*BZ34) -> 4425.864 | CH34: =(CG34*0.05) -> 221.2932 | CK34: SUPERBOM | CL34: CONJUNTO ENVASE MEL 200G | CM34: 133 | CO34: 43125 | CP34: 45 | CQ34: MIL | CR34: 894.9 | CT34: 43214 | CU34: 43217 | CV34: 13315 | CW34: 45000 | CX34: =(CP34*1000-CW34) -> 0 | CY34: =(CR34*CW34/1000) -> 40270.5 | CZ34: =(CU34+42) -> 43259 | DA34: =(CY34*0.03) -> 1208.115 | DE34: CONJUNTO ENVASE MEL 200G | DF34: 149 | DG34: VERBAL | DH34: 44023 | DI34: 45 | DJ34: MIL | DK34: 1111.58 | DM34: 44056 | DN34: 44071 | DO34: 14456 | DP34: 45000 | DQ34: =(DI34*1000-DP34) -> 0 | DR34: =(DK34*DP34/1000) -> 50021.1 | DS34: =(DN34+42) -> 44113 | DT34: =(DR34*0.03) -> 1500.633 | DU34: PAGO | DW34: ROZENDO | DX34: ETIQUETA ADESIVA ROTULO NATUREGG 20 UND | DY34: 1 | DZ34: E-MAIL | EA34: 44491 | EB34: 20 | EC34: MIL | ED34: 146.09 | EF34: 44510 | EG34: 44510 | EI34: 20000 | EJ34: =(EI34-EB34*1000) -> 0 | EK34: =(EI34*ED34/1000) -> 2921.8 | EM34: =(EK34*0.04) -> 116.872
N35: =(O34) -> 90853.361 | P35: AURORA | Q35: CUMBUCA 500 G - MA 15 | R35: 3 | S35: verbal | T35: 42779 | U35: 20 | V35: MIL | W35: 335 | Y35: 42783 | Z35: 42779 | AA35: 1667 | AB35: 20000 | AC35: =(AB35-U35*1000) -> 0 | AD35: =(AB35*W35/1000) -> 6700 | AE35: =(AD35*0.05) -> 335 | AF35: PAGO | BF35: 727.7 | BG35: KG | BH35: 9.7 | BJ35: 42830 | BK35: 42842 | BL35: 46850 | BM35: 757.04 | BN35: =(BM35-BF35) -> 29.34 | BO35: =(BM35*BH35) -> 7343.288 | BP35: =(BO35*0.05) -> 367.1644 | BQ35: PAGO | BT35: FILME PVC EST. 60 MM X 40 MICRA | BU35: 4 | BV35: E-MAIL | BW35: 42995 | BX35: 500 | BY35: KG | BZ35: 8.7 | CB35: 43052 | CC35: 43059 | CE35: 500 | CF35: =(CE35-BX35) -> 0 | CG35: =(CE35*BZ35) -> 4350 | CH35: =(CG35*0.05) -> 217.5 | DE35: CONJUNTO ENVASE MEL 200G | DF35: 150 | DG35: 23961 | DH35: 44126 | DI35: 45.1 | DJ35: MIL | DK35: 1243.32 | DM35: 44151 | DN35: 44153 | DO35: 14581 | DP35: 45100 | DQ35: =(DI35*1000-DP35) -> 0 | DR35: =(DK35*DP35/1000) -> 56073.732 | DS35: =(DN35+42) -> 44195 | DT35: =(DR35*0.03) -> 1682.212 | DU35: PAGO | DW35: ROZENDO | DX35: ETIQUETA ADESIVA ROTULO NATUREGG 30 UND | DY35: 2 | DZ35: E-MAIL | EA35: 44491 | EB35: 30 | EC35: MIL | ED35: 116.76 | EF35: 44510 | EG35: 44510 | EI35: 30000 | EJ35: =(EI35-EB35*1000) -> 0 | EK35: =(EI35*ED35/1000) -> 3502.8 | EM35: =(EK35*0.04) -> 140.112 | EP35: PLASTRELA | EQ35: JULIO RICARDO BRUST 51 3736-1122 51 98151-9119
B36: 2019 | P36: CACO | Q36: CUMBUCA 500 G - MA 15 | R36: 7 | S36: VERBAL | T36: 42781 | U36: 20 | V36: MIL | W36: 335 | Y36: 42783 | Z36: 42781 | AA36: 9395 | AB36: 20000 | AC36: =(AB36-U36*1000) -> 0 | AD36: =(AB36*W36/1000) -> 6700 | AE36: =(AD36*0.05) -> 335 | AF36: PAGO | BA36: GO GREEN | BB36: FILME PVC GA 380 X 10 X 1200 | BC36: 2 | BD36: VERBAL | BE36: 42832 | BF36: 50 | BG36: BOB | BH36: 52.9 | BJ36: 42837 | BK36: 42844 | BL36: 46875 | BM36: 54 | BN36: =(BM36-BF36) -> 4 | BO36: =(BM36*BH36) -> 2856.6 | BP36: =(BO36*0.05) -> 142.83 | BQ36: PAGO | BT36: FILME PVC EST. 60 MM X 40 MICRA | BU36: 5 | BV36: E-MAIL | BW36: 43047 | BX36: 500 | BY36: KG | BZ36: 8.7 | CB36: 43073 | CC36: 43073 | CE36: 500 | CF36: =(CE36-BX36) -> 0 | CG36: =(CE36*BZ36) -> 4350 | CH36: =(CG36*0.05) -> 217.5 | DE36: CONJUNTO ENVASE MEL 200G | DF36: 151 | DG36: 24809 | DH36: 44223 | DI36: 45.1 | DJ36: MIL | DK36: 1284.6 | DM36: 44228 | DN36: 44225 | DO36: 14670 | DP36: 45100 | DQ36: =(DI36*1000-DP36) -> 0 | DR36: =(DK36*DP36/1000) -> 57935.46 | DS36: =(DN36+42) -> 44267 | DT36: =(DR36*0.03) -> 1738.0638 | DU36: PAGO | ER36: OC | ES36: DATA | EV36: PREÇO | EW36: CODIGO | EX36: DATA | EY36: DATA | FD36: DATA | FE36: VALOR DA
B37: REPRESENTADA | C37: JAN 12 | D37: FEV 01 | E37: MAR 02 | F37: ABR 03 | G37: MAI 04 | H37: JUN 05 | I37: JUL 06 | J37: AGO 07 | K37: SET 08 | L37: OUT 09 | M37: NOV 10 | N37: DEZ 11 | P37: CEU AZUL | Q37: EMBALAGEM TOMATINHO - SRT 07 | R37: 1 | S37: VERBAL | T37: 42781 | U37: 10 | V37: MIL | W37: 154 | Y37: 42795 | Z37: 42790 | AA37: 1711 | AB37: 7000 | AC37: =(AB37-U37*1000) -> -3000 | AD37: =(AB37*W37/1000) -> 1078 | AE37: =(AD37*0.05) -> 53.9 | AF37: PAGO | BA37: LOSCHI | BB37: FILME PVC GA 380 X 10 X 1000 | BC37: 2 | BD37: VERBAL | BE37: 42835 | BF37: 50 | BG37: BOB | BH37: 45 | BJ37: 42839 | BK37: 42849 | BL37: 46908 | BM37: 54 | BN37: =(BM37-BF37) -> 4 | BO37: =(BM37*BH37) -> 2430 | BP37: =(BO37*0.05) -> 121.5 | BQ37: PAGO | BT37: FILME PVC EST. 60 MM X 40 MICRA | BU37: 6 | BV37: E-MAIL | BW37: 43047 | BX37: 500 | BY37: KG | BZ37: 8.7 | CB37: 43087 | CC37: 43087 | CE37: 500 | CF37: =(CE37-BX37) -> 0 | CG37: =(CE37*BZ37) -> 4350 | CH37: =(CG37*0.05) -> 217.5 | DE37: CONJUNTO ENVASE MEL 200G | DF37: 152 | DG37: 25240 | DH37: 44271 | DI37: 45.1 | DJ37: MIL | DK37: 1315.61 | DM37: 44285 | DN37: 44287 | DO37: 14765 | DP37: 45100 | DQ37: =(DI37*1000-DP37) -> 0 | DR37: =(DK37*DP37/1000) -> 59334.011 | DS37: =(DN37+42) -> 44329 | DT37: =(DR37*0.03) -> 1780.0203 | DU37: PAGO | EP37: PRODUTO | EQ37: PEDIDO | ER37: DO | ES37: DO | ET37: QUANT | EU37: UND | EV37: POR | EW37: DO | EX37: DE | EY37: DE | EZ37: N F | FA37: QUANT | FB37: SALDO | FC37: VALOR | FD37: COMISSÃO | FE37: COMISSÃO | FF37: OBSERVAÇÃO
P38: MAPE | Q38: CUMBUCA 500 G - MA15 | R38: 8 | S38: verbal | T38: 42786 | U38: 30 | V38: MIL | W38: 305 | Y38: 42790 | Z38: 42787 | AA38: 1695 | AB38: 30000 | AC38: =(AB38-U38*1000) -> 0 | AD38: =(AB38*W38/1000) -> 9150 | AE38: =(AD38*0.05) -> 457.5 | AF38: PAGO | BA38: COBREFLEX | BB38: FILME PVC EST. 60 MM X 40 MICRA | BC38: 13 | BD38: VERBAL | BE38: 43126 | BF38: 500 | BG38: KG | BH38: 9.13 | BJ38: 43220 | BK38: =(BJ38) -> 43220 | BL38: 50997 | BM38: 506.2 | BN38: =(BM38-BF38) -> 6.2 | BO38: =(BM38*BH38) -> 4621.606 | BP38: =(BO38*0.05) -> 231.0803 | BT38: FILME PVC EST. 60 MM X 40 MICRA | BU38: 7 | BV38: E-MAIL | BW38: 43047 | BX38: 500 | BY38: KG | BZ38: 8.7 | CB38: 43102 | CC38: 43102 | CE38: 500 | CF38: =(CE38-BX38) -> 0 | CG38: =(CE38*BZ38) -> 4350 | CH38: =(CG38*0.05) -> 217.5 | DE38: CONJUNTO ENVASE MEL 200G | DF38: 153 | DG38: E-MAIL | DH38: 44426 | DI38: 45.1 | DJ38: MIL | DK38: 1315.61 | DM38: 44445 | DN38: 44441 | DO38: 14909 | DP38: 45100 | DQ38: =(DI38*1000-DP38) -> 0 | DR38: =(DK38*DP38/1000) -> 59334.011 | DS38: =(DN38+42) -> 44483 | DT38: =(DR38*0.03) -> 1780.0203 | ER38: CLIENTE | ES38: PEDIDO | EV38: UND | EW38: CLIENTE | EX38: ENTREGA | EY38: FATURA | FD38: 42 DD | FE38: R$
B39: SERRAPLAST | C39: =(AE402) -> 5757.75 | D39: =(AE420) -> 3890.98 | E39: =(AE447) -> 7996.99 | F39: =(AE463) -> 5586.99 | G39: =(AE484) -> 6094.58 | H39: =(AE501) -> 5811.35 | I39: =(AE519) -> 7225.225 | J39: =(AE539) -> 11027.773 | K39: =(AE562) -> 7439.65 | L39: =(AE586) -> 6846.59 | M39: =(AE603) -> 4679.445 | N39: =(AE626) -> 11340.312 | BT39: FILME PVC EST. 60 MM X 40 MICRA | BU39: 8 | BV39: E-MAIL | BW39: 43047 | BX39: 500 | BY39: KG | BZ39: 8.7 | CB39: 43115 | CC39: 43119 | CD39: 48841 | CE39: 510.15 | CF39: =(CE39-BX39) -> 10.15 | CG39: =(CE39*BZ39) -> 4438.305 | CH39: =(CG39*0.05) -> 221.91525 | DE39: CONJUNTO ENVASE MEL 200G | DF39: 154 | DG39: E-MAIL | DH39: 44470 | DI39: 34 | DJ39: MIL | DK39: 1315.61 | DM39: 44487 | DN39: 44487 | DP39: 34000 | DQ39: =(DI39*1000-DP39) -> 0 | DR39: 47944.34 | DS39: =(DN39+42) -> 44529 | DT39: =(DR39*0.03) -> 1438.3302
AD40: =SUM(AD34:AD39) -> 29028 | AE40: =(AD40*0.05) -> 1451.4 | BO40: =SUM(BO31:BO38) -> 38476.918 | BP40: =SUM(BP31:BP39) -> 1923.8459 | BT40: FILME PVC EST. 60 MM X 40 MICRA | BU40: 9 | BV40: VERBAL | BW40: 43126 | BX40: 500 | BY40: KG | BZ40: 8.7 | CB40: 43136 | CC40: 43137 | CD40: 50058 | CE40: 504.28 | CF40: =(CE40-BX40) -> 4.28 | CG40: =(CE40*BZ40) -> 4387.236 | CH40: =(CG40*0.05) -> 219.3618 | EP40: VALVULA 1774 SEM FILTRO | EQ40: 1 | ER40: E-MAIL | ES40: 43707 | ET40: 25.5 | EU40: MIL | EV40: 174.64 | EX40: 43710 | EY40: 43710 | EZ40: 13960 | FA40: 25500 | FB40: =(ET40*1000-FA40) -> 0 | FC40: =(EV40*FA40/1000) -> 4453.32 | FD40: =(EY40+28) -> 43738 | FE40: =(FC40*0.03) -> 133.5996
B41: CCS | C41: =(DA149) -> 1329.075 | D41: =(DA169) -> 0 | E41: =(DA182) -> 1375.596 | F41: =(DA195) -> 1375.596 | G41: =(DA208) -> 1375.596 | H41: =(DA221) -> 1375.596 | I41: =(DA234) -> 0 | J41: 0 | K41: =(DA260) -> 1375.596 | L41: =(DA266) -> 133.5996 | M41: =(DA286) -> 0 | N41: =(DA299) -> 0 | BT41: FILME PVC EST. 60 MM X 40 MICRA | BU41: 10 | BV41: VERBAL | BW41: 43126 | BX41: 500 | BY41: KG | BZ41: 8.7 | CB41: 43150 | CC41: 43152 | CD41: 50243 | CE41: 503.28 | CF41: =(CE41-BX41) -> 3.28 | CG41: =(CE41*BZ41) -> 4378.536 | CH41: =(CG41*0.05) -> 218.9268 | EP41: VALVULA 1774 SEM FILTRO | EQ41: 2 | ER41: E-MAIL | ES41: 43732 | ET41: 51 | EU41: MIL | EV41: 174.64 | EX41: 43734 | EY41: 43734 | FA41: 51000 | FB41: =(ET41*1000-FA41) -> 0 | FC41: =(EV41*FA41/1000) -> 8906.64 | FD41: =(EY41+28) -> 43762 | FE41: =(FC41*0.03) -> 267.1992
P42: SERRAPLAST ABRIL 2017 | AJ42: BOA FRUTA | AK42: CLAUDIO RODRIGUES 27 3768-1468 | AP42: 27 99948-7636 | BA42: BRASIL SUL JUNHO 2017 | BT42: FILME PVC EST. 60 MM X 40 MICRA | BU42: 11 | BV42: VERBAL | BW42: 43126 | BX42: 500 | BY42: KG | BZ42: 9.13 | CB42: 43164 | CC42: 43161 | CD42: 50345 | CE42: 500 | CF42: =(CE42-BX42) -> 0 | CG42: =(CE42*BZ42) -> 4565 | CH42: =(CG42*0.05) -> 228.25
B43: BRASIL SUL | C43: =(BP238) -> 273.6936 | D43: =(BP251) -> 1169.7897 | E43: =(BP260) -> 709.2792 | F43: =(BP274) -> 1503.7965 | G43: =(BP284) -> 801.3918 | H43: =(BP298) -> 1599.4658 | I43: =(BP309) -> 1340.0944 | J43: =(BP321) -> 2790.0275 | K43: =(BP329) -> 1105.2729 | L43: =(BP342) -> 0 | M43: =(BP352) -> 928.39839 | N43: =(BP365) -> 0 | S43: OC | T43: DATA | W43: PREÇO | X43: CODIGO | Y43: DATA | Z43: DATA | AE43: VALOR DA | AL43: OC | AM43: DATA | AP43: PREÇO | AQ43: CODIGO | AR43: DATA | AS43: DATA | AX43: VALOR DA | BD43: OC | BE43: DATA | BH43: PREÇO | BI43: CODIGO | BJ43: DATA | BK43: DATA | BP43: VALOR DA | BT43: FILME PVC EST. 60 MM X 40 MICRA | BU43: 12 | BV43: VERBAL | BW43: 43126 | BX43: 500 | BY43: KG | BZ43: 9.13 | CB43: 43178 | CC43: 43174 | CD43: 50496 | CE43: 500 | CF43: =(CE43-BX43) -> 0 | CG43: =(CE43*BZ43) -> 4565 | CH43: =(CG43*0.05) -> 228.25
P44: CLIENTE | Q44: PRODUTO | R44: PEDIDO | S44: DO | T44: DO | U44: QUANT | V44: UND | W44: POR | X44: DO | Y44: DE | Z44: DE | AA44: N F | AB44: QUANT | AC44: SALDO | AD44: VALOR | AE44: COMISSÃO | AF44: OBSERVAÇÃO | AJ44: PRODUTO | AK44: PEDIDO | AL44: DO | AM44: DO | AN44: QUANT | AO44: UND | AP44: POR | AQ44: DO | AR44: DE | AS44: DE | AT44: N F | AU44: QUANT | AV44: SALDO | AW44: VALOR | AX44: COMISSÃO | AY44: OBSERVAÇÃO | BA44: CLIENTE | BB44: PRODUTO | BC44: PEDIDO | BD44: DO | BE44: DO | BF44: QUANT | BG44: UND | BH44: POR | BI44: DO | BJ44: DE | BK44: DE | BL44: N F | BM44: QUANT | BN44: SALDO | BO44: VALOR | BP44: COMISSÃO | BQ44: OBSERVAÇÃO | BT44: FILME PVC EST. 60 MM X 40 MICRA | BU44: 13 | BV44: VERBAL | BW44: 43126 | BX44: 500 | BY44: KG | BZ44: 9.13 | CB44: 43220 | CC44: =(CB44) -> 43220 | CD44: 50997 | CE44: 506.2 | CF44: =(CE44-BX44) -> 6.2 | CG44: =(CE44*BZ44) -> 4621.606 | CH44: =(CG44*0.05) -> 231.0803 | DE44: PLASTRELA | DF44: RUDIMAR SULZBACH 51 3736-1122
S45: CLIENTE | T45: PEDIDO | W45: UND | X45: CLIENTE | Y45: ENTREGA | Z45: FATURA | AE45: R$ | AL45: CLIENTE | AM45: PEDIDO | AP45: UND | AQ45: CLIENTE | AR45: ENTREGA | AS45: FATURA | AX45: R$ | BD45: CLIENTE | BE45: PEDIDO | BH45: UND | BI45: CLIENTE | BJ45: ENTREGA | BK45: FATURA | BP45: R$ | BT45: FILME PVC EST. 60 MM X 40 MICRA | BU45: 14 | BV45: VERBAL | BW45: 43126 | BX45: 500 | BY45: KG | BZ45: 9.13 | CB45: 43243 | CC45: =(CB45) -> 43243 | CD45: 51442 | CE45: 500 | CF45: =(CE45-BX45) -> 0 | CG45: =(CE45*BZ45) -> 4565 | CH45: =(CG45*0.05) -> 228.25 | DG45: OC | DH45: DATA | DK45: PREÇO | DL45: CODIGO | DM45: DATA | DN45: DATA | DS45: DATA | DT45: VALOR DA
P46: KORIN AGRO | Q46: EMB. OVO GALINHA 10 UND SRG - C10 | R46: 9 | S46: 3170 | T46: 42807 | U46: 130 | V46: MIL | W46: 260 | Y46: 42814 | Z46: 42812 | AA46: 9429 | AB46: 130000 | AC46: =(AB46-U46*1000) -> 0 | AD46: =(AB46*W46/1000) -> 33800 | AE46: =(AD46*0.05) -> 1690 | AF46: PAGO | AJ46: EMBALAGEM MAMÃO - SRP 04 - AZUL | AK46: 1 | AL46: E-MAIL | AM46: 43228 | AN46: 3 | AO46: MIL | AP46: 425 | AR46: 43235 | AS46: 43231 | AT46: 10207 | AU46: 3000 | AV46: =(AU46-AN46*1000) -> 0 | AW46: =(AU46*AP46/1000) -> 1275 | AX46: =(AW46*0.05) -> 63.75 | BA46: MAPE | BB46: FILME PVC GA 350 X 10 X 1000 | BC46: 1 | BD46: VERBAL | BE46: 42857 | BF46: 30 | BG46: BOB | BH46: 41 | BJ46: 42864 | BK46: 42881 | BL46: 47289 | BM46: 30 | BN46: =(BM46-BF46) -> 0 | BO46: =(BM46*BH46) -> 1230 | BP46: =(BO46*0.035) -> 43.05 | BT46: FILME PVC EST. 60 MM X 40 MICRA | BU46: 15 | BV46: VERBAL | BW46: 43248 | BX46: 500 | BY46: KG | BZ46: 9.13 | CB46: 43271 | CC46: 43258 | CD46: 51411 | CE46: 501.08 | CF46: =(CE46-BX46) -> 1.08 | CG46: =(CE46*BZ46) -> 4574.8604 | CH46: =(CG46*0.05) -> 228.74302 | DE46: PRODUTO | DF46: PEDIDO | DG46: DO | DH46: DO | DI46: QUANT | DJ46: UND | DK46: POR | DL46: DO | DM46: DE | DN46: DE | DO46: N F | DP46: QUANT | DQ46: SALDO | DR46: VALOR | DS46: COMISSÃO | DT46: COMISSÃO | DU46: OBSERVAÇÃO
P47: CACO | Q47: CUMBUCA 500 G - MA 15 | R47: 8 | S47: VERBAL | T47: 42809 | U47: 10 | V47: MIL | W47: 335 | Y47: 42814 | Z47: 42812 | AA47: 1792 | AB47: 10000 | AC47: =(AB47-U47*1000) -> 0 | AD47: =(AB47*W47/1000) -> 3350 | AE47: =(AD47*0.05) -> 167.5 | AF47: PAGO | AJ47: EMBALAGEM MAMÃO - SRP 04 - AZUL | AK47: 2 | AL47: E-MAIL | AM47: 43334 | AN47: 10 | AO47: MIL | AP47: 425 | AQ47: 455 | AR47: 43339 | AS47: 43338 | AT47: 3167 | AU47: 10000 | AV47: =(AU47-AN47*1000) -> 0 | AW47: =(AU47*AP47/1000) -> 4250 | AX47: =(AW47*0.05) -> 212.5 | BA47: COBREMACK BAHIA | BB47: FILME PVC EST. 60 MM X 40 MICRA | BC47: 2 | BE47: 42875 | BF47: 1000 | BG47: KG | BH47: 9.7 | BJ47: 42886 | BK47: 42884 | BL47: 47301 | BM47: 1010.03 | BN47: =(BM47-BF47) -> 10.03 | BO47: =(BM47*BH47) -> 9797.291 | BP47: =(BO47*0.06) -> 587.83746 | BT47: FILME PVC EST. 60 MM X 40 MICRA | BU47: 16 | BV47: VERBAL | BW47: 43248 | BX47: 500 | BY47: KG | BZ47: 9.13 | CB47: 43297 | CC47: 43293 | CD47: 51819 | CE47: 503.52 | CF47: =(CE47-BX47) -> 3.52 | CG47: =(CE47*BZ47) -> 4597.1376 | CH47: =(CG47*0.05) -> 229.85688 | DG47: CLIENTE | DH47: PEDIDO | DK47: UND | DL47: CLIENTE | DM47: ENTREGA | DN47: FATURA | DS47: 42 DD | DT47: R$
P48: JOSE PAULO LAZZARI | Q48: EMB. OVO GALINHA 10 UND SRG - C10 | R48: 2 | S48: E-MAIL | T48: 42815 | U48: 1 | V48: MIL | W48: 430 | Y48: 42817 | Z48: 42817 | AA48: 1800 | AB48: 1000 | AC48: =(AB48-U48*1000) -> 0 | AD48: =(AB48*W48/1000) -> 430 | AE48: =(AD48*0.05) -> 21.5 | AF48: PAGO | AJ48: CUMBUCA 500 G - MA 15 | AK48: 3 | AL48: VERBAL | AM48: 43370 | AN48: 3 | AO48: MIL | AP48: 300 | AQ48: 315 | AR48: 43374 | AS48: 43371 | AT48: 10499 | AU48: 3000 | AV48: =(AU48-AN48*1000) -> 0 | AW48: =(AU48*AP48/1000) -> 900 | AX48: =(AW48*0.05) -> 45 | BA48: METALFLEX | BB48: FILME PVC EST. 60 MM X 40 MICRA | BC48: 2 | BD48: E-MAIL | BE48: 42874 | BF48: 500 | BG48: KG | BH48: 8.7 | BJ48: 42881 | BK48: 42892 | BL48: 47402 | BM48: 509.4 | BN48: =(BM48-BF48) -> 9.4 | BO48: =(BM48*BH48) -> 4431.78 | BP48: =(BO48*0.035) -> 155.1123 | BT48: FILME PVC EST. 60 MM X 40 MICRA | BU48: 17 | BV48: VERBAL | BW48: 43248 | BX48: 700 | BY48: KG | BZ48: 9.13 | CB48: 43325 | CC48: 43300 | CD48: 51884 | CE48: 700.67 | CF48: =(CE48-BX48) -> 0.67 | CG48: =(CE48*BZ48) -> 6397.1171 | CH48: =(CG48*0.05) -> 319.85586
AJ49: CUMBUCA 500 G - MA 15 | AK49: 4 | AL49: VERBAL | AM49: 43591 | AN49: 5 | AO49: MIL | AP49: 300 | AQ49: 315 | AR49: 43598 | AS49: 43595 | AT49: 3784 | AU49: 5000 | AV49: =(AU49-AN49*1000) -> 0 | AW49: =(AU49*AP49/1000) -> 1500 | AX49: =(AW49*0.05) -> 75 | BA49: ALL CAB | BB49: FILME PVC EST. 60 MM X 40 MICRA | BC49: 2 | BD49: E-MAIL | BE49: 42877 | BF49: 300 | BG49: KG | BH49: 9.7 | BJ49: 42884 | BK49: 42886 | BL49: 47336 | BM49: 300 | BN49: =(BM49-BF49) -> 0 | BO49: =(BM49*BH49) -> 2910 | BP49: =(BO49*0.05) -> 145.5 | BT49: FILME PVC EST. 60 MM X 40 MICRA | BU49: 18 | BV49: e-mail | BW49: 43299 | BX49: 700 | BY49: KG | BZ49: 9.6 | CB49: 43329 | CC49: 43327 | CD49: 52207 | CE49: 701.8 | CF49: =(CE49-BX49) -> 1.8 | CG49: =(CE49*BZ49) -> 6737.28 | CH49: =(CG49*0.05) -> 336.864 | CY49: =SUM(CY34:CY40) -> 40270.5 | DA49: =SUM(DA34:DA40) -> 1208.115 | DE49: VALVULA 1774 SEM FILTRO | DF49: 1 | DG49: E-MAIL | DH49: 43707 | DI49: 25.5 | DJ49: MIL | DK49: 174.64 | DM49: 43710 | DN49: 43710 | DO49: 13960 | DP49: 25500 | DQ49: =(DI49*1000-DP49) -> 0 | DR49: =(DK49*DP49/1000) -> 4453.32 | DS49: =(DN49+28) -> 43738 | DT49: =(DR49*0.03) -> 133.5996 | DU49: PAGO | EK49: =SUM(EK34:EK40) -> 6424.6 | EM49: =SUM(EM34:EM40) -> 256.984
B50: TOTAL | C50: =SUM(C39:C49) -> 7360.5186 | D50: =SUM(D39:D49) -> 5060.7697 | E50: =SUM(E39:E49) -> 10081.865 | F50: =SUM(F39:F49) -> 8466.3825 | G50: =SUM(G39:G49) -> 8271.5678 | H50: =(H39+H41+H43) -> 8786.4118 | I50: =SUM(I39:I49) -> 8565.3194 | J50: =SUM(J39:J49) -> 13817.8 | K50: =SUM(K39:K49) -> 9920.5189 | L50: =SUM(L39:L49) -> 6980.1896 | M50: =SUM(M39:M49) -> 5607.8434 | N50: =SUM(N39:N49) -> 11340.312 | O50: =SUM(C50:N50) -> 104259.5 | AD50: =SUM(AD46:AD49) -> 37580 | AE50: =(AD50*0.05) -> 1879 | AJ50: CUMBUCA 500 G - MA 15 | AK50: 5 | AL50: WHATSAPP | AM50: 43815 | AN50: 10 | AO50: MIL | AP50: 315 | AQ50: 315 | AR50: 43816 | AS50: 43816 | AT50: 12295 | AU50: 10000 | AV50: =(AU50-AN50*1000) -> 0 | AW50: =(AU50*AP50/1000) -> 3150 | AX50: =(AW50*0.05) -> 157.5 | BT50: FILME PVC EST. 60 MM X 40 MICRA | BU50: 19 | BV50: e-mail | BW50: 43299 | BX50: 700 | BY50: KG | BZ50: 9.6 | CB50: 43346 | CC50: 43342 | CD50: 52359 | CE50: 704.65 | CF50: =(CE50-BX50) -> 4.65 | CG50: =(CE50*BZ50) -> 6764.64 | CH50: =(CG50*0.05) -> 338.232 | DE50: VALVULA 1774 SEM FILTRO | DF50: 2 | DG50: E-MAIL | DH50: 43732 | DI50: 51 | DJ50: MIL | DK50: 174.64 | DM50: 43734 | DN50: 43733 | DO50: 13990 | DP50: 51000 | DQ50: =(DI50*1000-DP50) -> 0 | DR50: =(DK50*DP50/1000) -> 8906.64 | DS50: =(DN50+28) -> 43761 | DT50: =(DR50*0.03) -> 267.1992 | DU50: PAGO
N51: =(O50) -> 104259.5 | BO51: =SUM(BO46:BO50) -> 18369.071 | BP51: =SUM(BP46:BP50) -> 931.49976 | BT51: FILME PVC EST. 60 MM X 40 MICRA | BU51: 20 | BV51: e-mail | BW51: 43299 | BX51: 700 | BY51: KG | BZ51: 9.6 | CB51: 43360 | CC51: 43367 | CD51: 52599 | CE51: 705.82 | CF51: =(CE51-BX51) -> 5.82 | CG51: =(CE51*BZ51) -> 6775.872 | CH51: =(CG51*0.05) -> 338.7936 | CK51: CCS JUNHO 2018 | DE51: VALVULA 6103 COM FILTRO | DF51: 3 | DG51: E-MAIL | DH51: 44067 | DI51: 50 | DJ51: MIL | DK51: 186.4 | DM51: 44074 | DN51: 44078 | DO51: 14468 | DP51: 50000 | DQ51: =(DI51*1000-DP51) -> 0 | DR51: =(DK51*DP51/1000) -> 9320 | DS51: =(DN51+28) -> 44106 | DT51: =(DR51*0.03) -> 279.6 | DU51: PAGO | DW51: EDIPRINT JANEIRO 2022
B52: 2020 | P52: SERRAPLAST MAIO 2017 | BT52: FILME PVC EST. 60 MM X 40 MICRA | BU52: 21 | BV52: e-mail | BW52: 43299 | BX52: 700 | BY52: KG | BZ52: 9.6 | CB52: 43381 | CC52: 43375 | CD52: 52703 | CE52: 703.78 | CF52: =(CE52-BX52) -> 3.78 | CG52: =(CE52*BZ52) -> 6756.288 | CH52: =(CG52*0.05) -> 337.8144 | CN52: OC | CO52: DATA | CR52: PREÇO | CS52: CODIGO | CT52: DATA | CU52: DATA | CZ52: DATA | DA52: VALOR DA | DE52: VALVULA 6103 COM FILTRO | DF52: 4 | DG52: E-MAIL | DH52: 44089 | DI52: 102 | DJ52: MIL | DK52: 193.09 | DM52: 44104 | DN52: 44096 | DO52: 14499 | DP52: 102000 | DQ52: =(DI52*1000-DP52) -> 0 | DR52: =(DK52*DP52/1000) -> 19695.18 | DS52: =(DN52+28) -> 44124 | DT52: =(DR52*0.03) -> 590.8554 | DU52: PAGO | DZ52: OC | EA52: DATA | ED52: PREÇO | EE52: CODIGO | EF52: DATA | EG52: DATA | EL52: DATA | EM52: VALOR DA
B53: REPRESENTADA | C53: JAN 12 | D53: FEV 01 | E53: MAR 02 | F53: ABR 03 | G53: MAI 04 | H53: JUN 05 | I53: JUL 06 | J53: AGO 07 | K53: SET 08 | L53: OUT 09 | M53: NOV 10 | N53: DEZ 11 | S53: OC | T53: DATA | W53: PREÇO | X53: CODIGO | Y53: DATA | Z53: DATA | AE53: VALOR DA | AY53: CARTA DE ISENÇÃO IPI | BA53: BRASIL SUL JULHO 2017 | BT53: FILME PVC EST. 60 MM X 40 MICRA | BU53: 22 | BV53: e-mail | BW53: 43299 | BX53: 700 | BY53: KG | BZ53: 9.6 | CB53: 43395 | CC53: 43382 | CD53: 52769 | CE53: 706.88 | CF53: =(CE53-BX53) -> 6.88 | CG53: =(CE53*BZ53) -> 6786.048 | CH53: =(CG53*0.05) -> 339.3024 | CK53: CLIENTE | CL53: PRODUTO | CM53: PEDIDO | CN53: DO | CO53: DO | CP53: QUANT | CQ53: UND | CR53: POR | CS53: DO | CT53: DE | CU53: DE | CV53: N F | CW53: QUANT | CX53: SALDO | CY53: VALOR | CZ53: COMISSÃO | DA53: COMISSÃO | DB53: OBSERVAÇÃO | DE53: VALVULA 6103 COM FILTRO | DF53: 5 | DG53: E-MAIL | DH53: 44118 | DI53: 153 | DJ53: MIL | DK53: 200.6 | DM53: 44130 | DN53: 44133 | DO53: 14554 | DP53: 153000 | DQ53: =(DI53*1000-DP53) -> 0 | DR53: =(DK53*DP53/1000) -> 30691.8 | DS53: =(DN53+28) -> 44161 | DT53: =(DR53*0.03) -> 920.754 | DU53: PAGO | DW53: CLIENTE | DX53: PRODUTO | DY53: PEDIDO | DZ53: DO | EA53: DO | EB53: QUANT | EC53: UND | ED53: POR | EE53: DO | EF53: DE | EG53: DE | EH53: N F | EI53: QUANT | EJ53: SALDO | EK53: VALOR | EL53: COMISSÃO | EM53: COMISSÃO | EN53: OBSERVAÇÃO | EP53: ROZENDO | EQ53: MOISÉS S. TEIXEIRA - 19 3608-8227
P54: CLIENTE | Q54: PRODUTO | R54: PEDIDO | S54: DO | T54: DO | U54: QUANT | V54: UND | W54: POR | X54: DO | Y54: DE | Z54: DE | AA54: N F | AB54: QUANT | AC54: SALDO | AD54: VALOR | AE54: COMISSÃO | AF54: OBSERVAÇÃO | BD54: OC | BE54: DATA | BH54: PREÇO | BI54: CODIGO | BJ54: DATA | BK54: DATA | BP54: VALOR DA | BT54: FILME PVC EST. 60 MM X 40 MICRA | BU54: 23 | BV54: VERBAL | BW54: 43360 | BX54: 800 | BY54: KG | BZ54: 10.6 | CB54: 43409 | CC54: 43405 | CD54: 53038 | CE54: 800.9 | CF54: =(CE54-BX54) -> 0.9 | CG54: =(CE54*BZ54) -> 8489.54 | CH54: =(CG54*0.05) -> 424.477 | CN54: CLIENTE | CO54: PEDIDO | CR54: UND | CS54: CLIENTE | CT54: ENTREGA | CU54: FATURA | CZ54: 30 DD | DA54: R$ | DE54: VALVULA 6103 COM FILTRO | DF54: 6 | DG54: E-MAIL | DH54: 44118 | DI54: 153 | DJ54: MIL | DK54: 200.6 | DM54: 44161 | DN54: 44165 | DO54: 14598 | DP54: 153000 | DQ54: =(DI54*1000-DP54) -> 0 | DR54: =(DK54*DP54/1000) -> 30691.8 | DS54: =(DN54+28) -> 44193 | DT54: =(DR54*0.03) -> 920.754 | DU54: PAGO | DZ54: CLIENTE | EA54: PEDIDO | ED54: UND | EE54: CLIENTE | EF54: ENTREGA | EG54: FATURA | EL54: 30 DD | EM54: R$ | ER54: OC | ES54: DATA | EV54: PREÇO | EW54: CODIGO | EX54: DATA | EY54: DATA | FD54: DATA | FE54: VALOR DA
B55: SERRAPLAST | C55: =(AE643) -> 7817 | D55: =(AE666) -> 10487.6 | E55: =(AE684) -> 6409.4 | F55: =(AE713) -> 12860.55 | G55: =(AE734) -> 9925.4 | H55: =(AE760) -> 16205.95 | I55: =(AE785) -> 10694.7 | J55: =(AE805) -> 8911.14 | K55: =(AE836) -> 12136.07 | L55: =(AE868) -> 12973.879 | M55: =(AE895) -> 14034.081 | N55: =(AE929) -> 11513.41 | S55: CLIENTE | T55: PEDIDO | W55: UND | X55: CLIENTE | Y55: ENTREGA | Z55: FATURA | AE55: R$ | AJ55: BRUNO MARQUES FELIPPE | AK55: BRUNO 38 99190-2210 | BA55: CLIENTE | BB55: PRODUTO | BC55: PEDIDO | BD55: DO | BE55: DO | BF55: QUANT | BG55: UND | BH55: POR | BI55: DO | BJ55: DE | BK55: DE | BL55: N F | BM55: QUANT | BN55: SALDO | BO55: VALOR | BP55: COMISSÃO | BQ55: OBSERVAÇÃO | BT55: FILME PVC EST. 60 MM X 40 MICRA | BU55: 24 | BV55: VERBAL | BW55: 43360 | BX55: 800 | BY55: KG | BZ55: 10.6 | CB55: 43423 | CC55: 43416 | CD55: 53122 | CE55: 804.3 | CF55: =(CE55-BX54) -> 4.3 | CG55: =(CE55*BZ54) -> 8525.58 | CH55: =(CG55*0.05) -> 426.279 | DE55: VALVULA 6103 COM FILTRO | DF55: 7 | DG55: E-MAIL | DH55: 44118 | DI55: 153 | DJ55: MIL | DK55: 200.6 | DM55: 44186 | DN55: 44186 | DO55: 14631 | DP55: 153000 | DQ55: =(DI55*1000-DP55) -> 0 | DR55: =(DK55*DP55/1000) -> 30691.8 | DS55: =(DN55+28) -> 44214 | DT55: =(DR55*0.03) -> 920.754 | DU55: PAGO | EP55: PRODUTO | EQ55: PEDIDO | ER55: DO | ES55: DO | ET55: QUANT | EU55: UND | EV55: POR | EW55: DO | EX55: DE | EY55: DE | EZ55: N F | FA55: QUANT | FB55: SALDO | FC55: VALOR | FD55: COMISSÃO | FE55: COMISSÃO | FF55: OBSERVAÇÃO
P56: FAZENDA DA TOCA | Q56: EMB. OVO GALINHA 06 UND SRG - C06 | R56: 3 | S56: 16975 | T56: 42822 | U56: 70 | V56: MIL | W56: 200 | X56: 1010506 | Y56: 42832 | Z56: 42832 | AA56: 9555 | AB56: 70000 | AC56: =(AB56-U56*1000) -> 0 | AD56: =(AB56*W56/1000) -> 14000 | AE56: =(AD56*0.05) -> 700 | AF56: PAGO | AL56: OC | AM56: DATA | AP56: PREÇO | AQ56: CODIGO | AR56: DATA | AS56: DATA | AX56: VALOR DA | BD56: CLIENTE | BE56: PEDIDO | BH56: UND | BI56: CLIENTE | BJ56: ENTREGA | BK56: FATURA | BP56: R$ | BT56: FILME PVC EST. 60 MM X 40 MICRA | BU56: 25 | BV56: VERBAL | BW56: 43360 | BX56: 800 | BY56: KG | BZ56: 10.6 | CB56: 43437 | CC56: 43423 | CD56: 53188 | CE56: 799.71 | CF56: =(CE56-BX55) -> -0.29 | CG56: =(CE56*BZ55) -> 8476.926 | CH56: =(CG56*0.05) -> 423.8463 | DE56: VALVULA 6103 COM FILTRO | DF56: 8 | DG56: E-MAIL | DH56: 44118 | DI56: 153 | DJ56: MIL | DK56: 200.6 | DM56: 44249 | DN56: 44242 | DO56: 14695 | DP56: 153000 | DQ56: =(DI56*1000-DP56) -> 0 | DR56: =(DK56*DP56/1000) -> 30691.8 | DS56: =(DN56+28) -> 44270 | DT56: =(DR56*0.03) -> 920.754 | DU56: PAGO | ER56: CLIENTE | ES56: PEDIDO | EV56: UND | EW56: CLIENTE | EX56: ENTREGA | EY56: FATURA | FD56: 42 DD | FE56: R$
B57: CCS | C57: =(DA312) -> 0 | D57: =(DA325) -> 2876.2155 | E57: =(DA338) -> 1500.6195 | F57: =(DA351) -> 1500.6195 | G57: =(DA364) -> 0 | H57: =(DA378) -> 1503.9542 | I57: =(DA391) -> 1503.9677 | J57: =(DA404) -> 1500.633 | K57: =(DA417) -> 1696.48 | L57: =(DA430) -> 590.8554 | M57: =(DA443) -> 920.754 | N57: =(DA456) -> 2602.966 | P57: BIANCHI | Q57: EMB. OVO GALINHA 10 UND SRG - C10 | R57: 6 | S57: E-MAIL | T57: 42824 | U57: 20 | V57: MIL | W57: 270 | Y57: 42832 | Z57: 42832 | AA57: 1849 | AB57: 20000 | AC57: =(AB57-U57*1000) -> 0 | AD57: =(AB57*W57/1000) -> 5400 | AE57: =(AD57*0.05) -> 270 | AF57: PAGO | AJ57: PRODUTO | AK57: PEDIDO | AL57: DO | AM57: DO | AN57: QUANT | AO57: UND | AP57: POR | AQ57: DO | AR57: DE | AS57: DE | AT57: N F | AU57: QUANT | AV57: SALDO | AW57: VALOR | AX57: COMISSÃO | AY57: OBSERVAÇÃO | BA57: METALFLEX | BB57: FILME PVC EST. 60 MM X 40 MICRA | BC57: 3 | BD57: e-mail | BE57: 42898 | BF57: 500 | BG57: KG | BH57: 8.7 | BJ57: 42908 | BK57: 42915 | BL57: 47649 | BM57: 494.8 | BN57: =(BM57-BF57) -> -5.2 | BO57: =(BM57*BH57) -> 4304.76 | BP57: =(BO57*0.035) -> 150.6666 | BT57: FILME PVC EST. 60 MM X 40 MICRA | BU57: 26 | BV57: VERBAL | BW57: 43360 | BX57: 800 | BY57: KG | BZ57: 10.6 | CB57: 43451 | CC57: 43434 | CD57: 53342 | CE57: 809.49 | CF57: =(CE57-BX56) -> 9.49 | CG57: =(CE57*BZ56) -> 8580.594 | CH57: =(CG57*0.05) -> 429.0297 | DE57: VALVULA 6103 COM FILTRO | DF57: 9 | DG57: E-MAIL | DH57: 44118 | DI57: 153 | DJ57: MIL | DK57: 200.6 | DM57: 44270 | DN57: 44257 | DO57: 14719 | DP57: 102000 | DQ57: =(DI57*1000-DP57) -> 51000 | DR57: =(DK57*DP57/1000) -> 20461.2 | DS57: =(DN57+28) -> 44285 | DT57: =(DR57*0.03) -> 613.836 | DU57: PAGO
P58: CACO | Q58: CUMBUCA 500 G - MA 15 | R58: 9 | S58: VERBAL | T58: 42835 | U58: 10 | V58: MIL | W58: 335 | Y58: 42839 | Z58: 42838 | AA58: 1874 | AB58: 10000 | AC58: =(AB58-U58*1000) -> 0 | AD58: =(AB58*W58/1000) -> 3350 | AE58: =(AD58*0.05) -> 167.5 | AF58: PAGO | AL58: CLIENTE | AM58: PEDIDO | AP58: UND | AQ58: CLIENTE | AR58: ENTREGA | AS58: FATURA | AX58: R$ | BT58: FILME PVC EST. 60 MM X 40 MICRA | BU58: 27 | BV58: VERBAL | BW58: 43453 | BX58: 500 | BY58: KG | BZ58: 10.6 | CB58: 43475 | CC58: 43475 | CD58: 53582 | CE58: 500.68 | CF58: =(CE58-BX58) -> 0.68 | CG58: =(CE58*BZ56) -> 5307.208 | CH58: =(CG58*0.05) -> 265.3604 | DE58: VALVULA 6103 COM FILTRO | DF58: 9 | DG58: E-MAIL | DH58: 44118 | DI58: 51 | DJ58: MIL | DK58: 200.6 | DM58: 44270 | DN58: 44272 | DO58: 14744 | DP58: 51000 | DQ58: =(DI58*1000-DP58) -> 0 | DR58: =(DK58*DP58/1000) -> 10230.6 | DS58: =(DN58+28) -> 44300 | DT58: =(DR58*0.03) -> 306.918 | EP58: ETIQUETA ADESIVA ROTULO NATUREGG 20 UND | EQ58: 1 | ER58: E-MAIL | ES58: 44491 | ET58: 20 | EU58: MIL | EV58: 146.09 | EX58: 44510 | EY58: 44510 | FA58: 20000 | FB58: =(FA58-ET58*1000) -> 0 | FC58: =(FA58*EV58/1000) -> 2921.8 | FE58: =(FC58*0.04) -> 116.872
B59: BRASIL SUL | C59: =(BP373) -> 163.7859 | D59: =(BP381) -> 537.6267 | E59: =(BP389) -> 795.94999 | F59: =(BP397) -> 801.01291 | G59: =(BP410) -> 1735.2918 | H59: =(BP426) -> 2396.1133 | I59: =(BP439) -> 832.35229 | J59: =(BP452) -> 923.0024 | K59: =(BP465) -> 1020.2926 | L59: =(BP478) -> 883.64478 | M59: =(BP491) -> 2529.7593 | N59: =(BP504) -> 1272.9588 | P59: CEU AZUL | Q59: EMBALAGEM TOMATINHO - SRT 07 | R59: 2 | S59: VERBAL | T59: 42835 | U59: 10 | V59: MIL | W59: 154 | Y59: 42839 | Z59: 42838 | AA59: 1873 | AB59: 10000 | AC59: =(AB59-U59*1000) -> 0 | AD59: =(AB59*W59/1000) -> 1540 | AE59: =(AD59*0.05) -> 77 | AF59: PAGO | AJ59: CUMBUCA 500 G - MA 15 | AK59: 1 | AL59: WHATSAPP | AM59: 44053 | AN59: 10 | AO59: MIL | AP59: 313 | AQ59: 315 | AR59: 44064 | AS59: 44053 | AT59: 13623 | AU59: 10000 | AV59: =(AU59-AN59*1000) -> 0 | AW59: =(AU59*AP59/1000) -> 3130 | AX59: =(AW59*0.05) -> 156.5 | BO59: =SUM(BO57:BO58) -> 4304.76 | BP59: =SUM(BP57:BP58) -> 150.6666 | BT59: FILME PVC EST. 60 MM X 40 MICRA | BU59: 28 | BV59: VERBAL | BW59: 43453 | BX59: 300 | BY59: KG | BZ59: 10.6 | CB59: 43475 | CC59: 43488 | CD59: 53731 | CE59: 307.08 | CF59: =(CE59-BX59) -> 7.08 | CG59: =(CE59*BZ57) -> 3255.048 | CH59: =(CG59*0.05) -> 162.7524 | DE59: VALVULA 6103 COM FILTRO | DF59: 10 | DG59: E-MAIL | DH59: 44118 | DI59: 153 | DJ59: MIL | DK59: 200.6 | DM59: 44284 | DN59: 44284 | DO59: 14756 | DP59: 153000 | DQ59: =(DI59*1000-DP59) -> 0 | DR59: =(DK59*DP59/1000) -> 30691.8 | DS59: =(DN59+28) -> 44312 | DT59: =(DR59*0.03) -> 920.754 | DU59: PAGO | EP59: ETIQUETA ADESIVA ROTULO NATUREGG 30 UND | EQ59: 2 | ER59: E-MAIL | ES59: 44491 | ET59: 30 | EU59: MIL | EV59: 116.76 | EX59: 44510 | EY59: 44510 | FA59: 30000 | FB59: =(FA59-ET59*1000) -> 0 | FC59: =(FA59*EV59/1000) -> 3502.8 | FE59: =(FC59*0.04) -> 140.112
P60: KORIN AGRO | Q60: EMB. OVO GALINHA 10 UND SRG - C10 | R60: 10 | S60: 4389 | T60: 42835 | U60: 130 | V60: MIL | W60: 260 | Y60: 42839 | Z60: 42841 | AA60: 9561 | AB60: 130000 | AC60: =(AB60-U60*1000) -> 0 | AD60: =(AB60*W60/1000) -> 33800 | AE60: =(AD60*0.05) -> 1690 | AF60: PAGO | AJ60: CUMBUCA 500 G - MA 15 | AK60: 2 | AL60: WHATSAPP | AM60: 44070 | AN60: 30 | AO60: MIL | AP60: 334.9 | AQ60: 315 | AR60: 44082 | AS60: 44082 | AT60: 13830 | AU60: 30000 | AV60: =(AU60-AN60*1000) -> 0 | AW60: =(AU60*AP60/1000) -> 10047 | AX60: =(AW60*0.05) -> 502.35 | BT60: FILME PVC EST. 60 MM X 40 MICRA | BU60: 29 | BV60: VERBAL | BW60: 43453 | BX60: 300 | BY60: KG | BZ60: 10.6 | CB60: 43497 | CC60: 43496 | CD60: 53825 | CE60: 308.73 | CF60: =(CE60-BX60) -> 8.73 | CG60: =(CE60*BZ60) -> 3272.538 | CH60: =(CG60*0.05) -> 163.6269 | DE60: VALVULA 6103 COM FILTRO | DF60: 11 | DG60: E-MAIL | DI60: 153 | DJ60: MIL | DM60: 44277 | DN60: 44277 | DO60: 14751 | DP60: 153000 | DR60: 23535.07 | DS60: =(DN60+28) -> 44305 | DT60: =(DR60*0.03) -> 706.0521 | DU60: PAGO
P61: AURORA | Q61: CUMBUCA 500 G - MA 15 | R61: 4 | S61: verbal | T61: 42836 | U61: 20 | V61: MIL | W61: 335 | Y61: 42839 | Z61: 42838 | AA61: 1875 | AB61: 20000 | AC61: =(AB61-U61*1000) -> 0 | AD61: =(AB61*W61/1000) -> 6700 | AE61: =(AD61*0.05) -> 335 | AF61: PAGO | AJ61: CUMBUCA 500 G - MA 15 | AK61: 3 | AL61: WHATSAPP | AM61: 44070 | AN61: 50 | AO61: MIL | AP61: 334.9 | AQ61: 315 | AR61: 44109 | AS61: 44109 | AU61: 50000 | AV61: =(AU61-AN61*1000) -> 0 | AW61: =(AU61*AP61/1000) -> 16745 | AX61: =(AW61*0.05) -> 837.25 | AY61: CANCELADO | BA61: BRASIL SUL AGOSTO 2017 | BT61: FILME PVC EST. 60 MM X 40 MICRA | BU61: 29 | BV61: VERBAL | BW61: 43453 | BX61: 300 | BY61: KG | BZ61: 10.6 | CB61: 43511 | CC61: 43514 | CD61: 53962 | CE61: 307.05 | CF61: =(CE61-BX60) -> 7.05 | CG61: =(CE61*BZ60) -> 3254.73 | CH61: =(CG61*0.05) -> 162.7365 | DE61: VALVULA 6103 COM FILTRO | DF61: 12 | DG61: E-MAIL | DI61: 153 | DJ61: MIL | DM61: 44299 | DN61: 44299 | DO61: 14780 | DP61: 153000 | DR61: 12601.54 | DS61: =(DN61+28) -> 44327 | DT61: =(DR61*0.03) -> 378.0462 | DU61: PAGO
P62: FAZENDA DA TOCA | Q62: EMB. OVO GALINHA 06 UND SRG - C06 | R62: 4 | S62: 17168 | T62: 42850 | U62: 39 | V62: MIL | W62: 400 | X62: 1010506 | Y62: 42857 | Z62: 42858 | AA62: 9579 | AB62: 39000 | AC62: =(AB62-U62*1000) -> 0 | AD62: =(AB62*W62/1000) -> 15600 | AE62: =(AD62*0.05) -> 780 | AF62: PAGO | AJ62: CUMBUCA 500 G - MA 15 | AK62: 4 | AL62: WHATSAPP | AM62: 44340 | AN62: 15 | AO62: MIL | AP62: 380 | AQ62: 315 | AR62: 44343 | AS62: 44341 | AT62: 15552 | AU62: 15000 | AV62: =(AU62-AN62*1000) -> 0 | AW62: =(AU62*AP62/1000) -> 5700 | AX62: =(AW62*0.05) -> 285 | BD62: OC | BE62: DATA | BH62: PREÇO | BI62: CODIGO | BJ62: DATA | BK62: DATA | BP62: VALOR DA | BT62: FILME PVC EST. 60 MM X 40 MICRA | BU62: 30 | BV62: VERBAL | BW62: 43453 | BX62: 300 | BY62: KG | BZ62: 10.6 | CB62: 43532 | CC62: 43532 | CD62: 54121 | CE62: 305.87 | CF62: =(CE62-BX61) -> 5.87 | CG62: =(CE62*BZ61) -> 3242.222 | CH62: =(CG62*0.05) -> 162.1111 | CY62: =SUM(CY55:CY61) -> 0 | DA62: =SUM(DA55:DA61) -> 0 | DE62: VALVULA 6103 COM FILTRO | DF62: 13 | DG62: E-MAIL | DI62: 153 | DJ62: MIL | DM62: 44302 | DN62: 44302 | DO62: 14783 | DP62: 153000 | DR62: 25203.08 | DS62: =(DN62+28) -> 44330 | DT62: =(DR62*0.03) -> 756.0924 | DU62: PAGO | EK62: =SUM(EK55:EK61) -> 0 | EM62: =SUM(EM55:EM61) -> 0
AJ63: CUMBUCA 500 G - MA 15 | AK63: 5 | AL63: WHATSAPP | AM63: 44372 | AN63: 30 | AO63: MIL | AP63: 380 | AQ63: 315 | AR63: 44375 | AS63: 44372 | AT63: 15699 | AU63: 30000 | AV63: 0 | AW63: =(AU63*AP63/1000) -> 11400 | AX63: =(AW63*0.05) -> 570 | BA63: CLIENTE | BB63: PRODUTO | BC63: PEDIDO | BD63: DO | BE63: DO | BF63: QUANT | BG63: UND | BH63: POR | BI63: DO | BJ63: DE | BK63: DE | BL63: N F | BM63: QUANT | BN63: SALDO | BO63: VALOR | BP63: COMISSÃO | BQ63: OBSERVAÇÃO | BT63: FILME PVC EST. 60 MM X 40 MICRA | BU63: 31 | BV63: VERBAL | BW63: 43538 | BX63: 400 | BY63: KG | BZ63: 10.6 | CB63: 43536 | CC63: 43538 | CD63: 54196 | CE63: 409.91 | CF63: =(CE63-BX63) -> 9.91 | CG63: =(CE63*BZ61) -> 4345.046 | CH63: =(CG63*0.05) -> 217.2523 | DE63: VALVULA 6103 COM FILTRO | DF63: 14 | DG63: E-MAIL | DI63: 153 | DJ63: MIL | DM63: 44250 | DN63: 44250 | DO63: 14706 | DP63: 153000 | DR63: 12436.15 | DS63: =(DN63+28) -> 44278 | DT63: =(DR63*0.03) -> 373.0845 | DU63: PAGO
AD64: =SUM(AD56:AD63) -> 80390 | AE64: =(AD64*0.05) -> 4019.5 | AJ64: CUMBUCA 500 G - MA 15 | AK64: 6 | AL64: WHATSAPP | AM64: 44421 | AN64: 40 | AO64: MIL | AP64: 360 | AQ64: 315 | AR64: 44424 | AS64: 44421 | AT64: 15969 | AU64: 40000 | AV64: 0 | AW64: =(AU64*AP64/1000) -> 14400 | AX64: =(AW64*0.05) -> 720 | BD64: CLIENTE | BE64: PEDIDO | BH64: UND | BI64: CLIENTE | BJ64: ENTREGA | BK64: FATURA | BP64: R$ | BT64: FILME PVC EST. 60 MM X 40 MICRA | BU64: 32 | BV64: VERBAL | BW64: 43538 | BX64: 400 | BY64: KG | BZ64: 10.6 | CB64: 43546 | CC64: 43546 | CD64: 54257 | CE64: 402.64 | CF64: =(CE64-BX64) -> 2.64 | CG64: =(CE64*BZ62) -> 4267.984 | CH64: =(CG64*0.05) -> 213.3992 | CK64: CCS JULHO 2018 | DE64: VALVULA 6103 COM FILTRO | DF64: 15 | DG64: E-MAIL | DI64: 153 | DJ64: MIL | DM64: 44257 | DN64: 44257 | DO64: 14719 | DP64: 153000 | DR64: 24872.29 | DS64: =(DN64+28) -> 44285 | DT64: =(DR64*0.03) -> 746.1687 | DU64: PAGO | DW64: EDIPRINT FEVEREIRO 2022
AJ65: CUMBUCA 500 G - MA 15 | AK65: 7 | AL65: VERBAL | AM65: 44461 | AN65: 40 | AO65: MIL | AP65: 360 | AQ65: 315 | AR65: 44466 | AS65: 44466 | AT65: 16269 | AU65: 40000 | AV65: 0 | AW65: =(AU65*AP65/1000) -> 14400 | AX65: =(AW65*0.05) -> 720 | BA65: COBREMACK SP | BB65: FILME PVC EST. 60 MM X 40 MICRA | BC65: 2 | BE65: 42905 | BF65: 700 | BG65: KG | BH65: 9.7 | BJ65: 42922 | BK65: 42922 | BL65: 47749 | BM65: 699.56 | BN65: =(BM65-BF65) -> -0.44 | BO65: =(BM65*BH65) -> 6785.732 | BP65: =(BO65*0.06) -> 407.14392 | BT65: FILME PVC EST. 60 MM X 40 MICRA | BU65: 33 | BV65: VERBAL | BW65: 43538 | BX65: 500 | BY65: KG | BZ65: 10.6 | CB65: 43563 | CC65: 43563 | CD65: 54398 | CE65: 506.65 | CF65: =(CE65-BX65) -> 6.65 | CG65: =(CE65*BZ63) -> 5370.49 | CH65: =(CG65*0.05) -> 268.5245 | CN65: OC | CO65: DATA | CR65: PREÇO | CS65: CODIGO | CT65: DATA | CU65: DATA | CZ65: DATA | DA65: VALOR DA | DE65: VALVULA 6103 COM FILTRO | DF65: 16 | DG65: E-MAIL | DI65: 153 | DJ65: MIL | DK65: 261.13 | DM65: 44284 | DN65: 44284 | DO65: 14756 | DP65: 153000 | DR65: 39952.97 | DS65: =(DN65+28) -> 44312 | DT65: =(DR65*0.03) -> 1198.5891 | DU65: PAGO | DZ65: OC | EA65: DATA | ED65: PREÇO | EE65: CODIGO | EF65: DATA | EG65: DATA | EL65: DATA | EM65: VALOR DA
B66: TOTAL | C66: =SUM(C55:C65) -> 7980.7859 | D66: =SUM(D55:D65) -> 13901.442 | E66: =SUM(E55:E65) -> 8705.9695 | F66: =SUM(F55:F65) -> 15162.182 | G66: =SUM(G55:G65) -> 11660.692 | H66: =(H55+H57+H59) -> 20106.018 | I66: =SUM(I55:I65) -> 13031.02 | J66: =SUM(J55:J65) -> 11334.775 | K66: =SUM(K55:K65) -> 14852.843 | L66: =SUM(L55:L65) -> 14448.379 | M66: =SUM(M55:M65) -> 17484.594 | N66: =SUM(N55:N65) -> 15389.335 | O66: =SUM(C66:N66) -> 164058.04 | P66: SERRAPLAST JUNHO 2017 | BA66: GO GREEN | BB66: FILME PVC GA 380 X 10 X 1200 | BC66: 3 | BD66: VERBAL | BE66: 42915 | BF66: 24 | BG66: BOB | BH66: 52.9 | BJ66: 42930 | BK66: 42928 | BL66: 47804 | BM66: 24 | BN66: =(BM66-BF66) -> 0 | BO66: =(BM66*BH66) -> 1269.6 | BP66: =(BO66*0.05) -> 63.48 | BT66: FILME PVC EST. 60 MM X 40 MICRA | BU66: 34 | BV66: VERBAL | BW66: 43538 | BX66: 500 | BY66: KG | BZ66: 10.6 | CB66: 43577 | CC66: 43565 | CD66: 54437 | CE66: 506.28 | CF66: =(CE66-BX66) -> 6.28 | CG66: =(CE66*BZ64) -> 5366.568 | CH66: =(CG66*0.05) -> 268.3284 | CK66: CLIENTE | CL66: PRODUTO | CM66: PEDIDO | CN66: DO | CO66: DO | CP66: QUANT | CQ66: UND | CR66: POR | CS66: DO | CT66: DE | CU66: DE | CV66: N F | CW66: QUANT | CX66: SALDO | CY66: VALOR | CZ66: COMISSÃO | DA66: COMISSÃO | DB66: OBSERVAÇÃO | DE66: VALVULA 6103 COM FILTRO | DF66: 17 | DG66: E-MAIL | DI66: 153 | DJ66: MIL | DK66: 261.13 | DM66: 44308 | DN66: 44308 | DO66: 14786 | DP66: 153000 | DR66: 39952.97 | DS66: =(DN66+28) -> 44336 | DT66: =(DR66*0.03) -> 1198.5891 | DU66: PAGO | DW66: CLIENTE | DX66: PRODUTO | DY66: PEDIDO | DZ66: DO | EA66: DO | EB66: QUANT | EC66: UND | ED66: POR | EE66: DO | EF66: DE | EG66: DE | EH66: N F | EI66: QUANT | EJ66: SALDO | EK66: VALOR | EL66: COMISSÃO | EM66: COMISSÃO | EN66: OBSERVAÇÃO
N67: =(O66) -> 164058.04 | S67: OC | T67: DATA | W67: PREÇO | X67: CODIGO | Y67: DATA | Z67: DATA | AE67: VALOR DA | BA67: INDUSCON | BB67: FILME PVC EST. 60 MM X 40 MICRA | BC67: 1 | BD67: e-mail | BE67: 42921 | BF67: 500 | BG67: KG | BH67: 8.7 | BJ67: 42936 | BK67: 42933 | BL67: 47849 | BM67: 500 | BN67: =(BM67-BF67) -> 0 | BO67: =(BM67*BH67) -> 4350 | BP67: =(BO67*0.035) -> 152.25 | BT67: FILME PVC EST. 60 MM X 40 MICRA | BU67: 35 | BV67: VERBAL | BW67: 43538 | BX67: 500 | BY67: KG | BZ67: 10.6 | CB67: 43581 | CC67: 43571 | CD67: 54491 | CE67: 499.13 | CF67: =(CE67-BX67) -> -0.87 | CG67: =(CE67*BZ65) -> 5290.778 | CH67: =(CG67*0.05) -> 264.5389 | CN67: CLIENTE | CO67: PEDIDO | CR67: UND | CS67: CLIENTE | CT67: ENTREGA | CU67: FATURA | CZ67: 30 DD | DA67: R$ | DE67: VALVULA 6103 COM FILTRO | DF67: 18 | DG67: E-MAIL | DI67: 153 | DJ67: MIL | DK67: 261.13 | DM67: 44354 | DN67: 44354 | DO67: 14826 | DP67: 153000 | DR67: 39952.97 | DS67: =(DN67+28) -> 44382 | DT67: =(DR67*0.03) -> 1198.5891 | DU67: PAGO | DZ67: CLIENTE | EA67: PEDIDO | ED67: UND | EE67: CLIENTE | EF67: ENTREGA | EG67: FATURA | EL67: 30 DD | EM67: R$
P68: CLIENTE | Q68: PRODUTO | R68: PEDIDO | S68: DO | T68: DO | U68: QUANT | V68: UND | W68: POR | X68: DO | Y68: DE | Z68: DE | AA68: N F | AB68: QUANT | AC68: SALDO | AD68: VALOR | AE68: COMISSÃO | AF68: OBSERVAÇÃO | BA68: OTHIL | BB68: FILME GA DUPLO 285 X 14 | BC68: 1 | BD68: VERBAL | BE68: 42940 | BF68: 5 | BG68: BOB | BH68: 70 | BJ68: 42947 | BK68: 42947 | BM68: 5 | BN68: =(BM68-BF68*1) -> 0 | BO68: =(BM68*BH68) -> 350 | BP68: =(BO68*0.05) -> 17.5 | BT68: FILME PVC EST. 60 MM X 40 MICRA | BU68: 36 | BV68: VERBAL | BW68: 43538 | BX68: 500 | BY68: KG | BZ68: 10.6 | CB68: 43591 | CC68: 43587 | CD68: 54649 | CE68: 507.59 | CF68: =(CE68-BX68) -> 7.59 | CG68: =(CE68*BZ66) -> 5380.454 | CH68: =(CG68*0.05) -> 269.0227 | CK68: SUPERBOM | CL68: CONJUNTO ENVASE MEL 200G | CM68: 134 | CO68: 43125 | CP68: 45 | CQ68: MIL | CR68: 922.5 | CT68: 43255 | CU68: 43255 | CV68: 13367 | CW68: 45000 | CX68: =(CP68*1000-CW68) -> 0 | CY68: =(CR68*CW68/1000) -> 41512.5 | CZ68: =(CU68+42) -> 43297 | DA68: =(CY68*0.03) -> 1245.375 | DB68: PAGO | DE68: VALVULA 6103 COM FILTRO | DF68: 19 | DG68: E-MAIL | DI68: 153 | DJ68: MIL | DK68: 261.13 | DM68: 44365 | DN68: 44365 | DO68: 14843 | DP68: 153000 | DR68: 39952.97 | DS68: =(DN68+28) -> 44393 | DT68: =(DR68*0.03) -> 1198.5891 | DU68: PAGO
B69: 2021 | S69: CLIENTE | T69: PEDIDO | W69: UND | X69: CLIENTE | Y69: ENTREGA | Z69: FATURA | AE69: R$ | BT69: FILME PVC EST. 60 MM X 40 MICRA | BU69: 37 | BV69: E-MAIL | BW69: 43566 | BX69: 500 | BY69: KG | BZ69: 10.6 | CB69: 43602 | CC69: 43595 | CD69: 54708 | CE69: 502.48 | CF69: =(CE69-BX69) -> 2.48 | CG69: =(CE69*BZ69) -> 5326.288 | CH69: =(CG69*0.05) -> 266.3144 | DE69: VALVULA 6103 COM FILTRO | DF69: 20 | DG69: E-MAIL | DI69: 153 | DJ69: MIL | DK69: 261.13 | DM69: 44378 | DN69: 44378 | DO69: 14854 | DP69: 153000 | DR69: 39952.97 | DS69: =(DN69+28) -> 44406 | DT69: =(DR69*0.03) -> 1198.5891 | DU69: PAGO
B70: REPRESENTADA | C70: JAN 12 | D70: FEV 01 | E70: MAR 02 | F70: ABR 03 | G70: MAI 04 | H70: JUN 05 | I70: JUL 06 | J70: AGO 07 | K70: SET 08 | L70: OUT 09 | M70: NOV 10 | N70: DEZ 11 | P70: JOSE PAULO LAZZARI | Q70: EMB. OVO GALINHA 10 UND SRG - C10 | R70: 3 | S70: E-MAIL | T70: 42863 | U70: 1 | V70: MIL | W70: 430 | Y70: 42870 | Z70: 42865 | AA70: 1928 | AB70: 1000 | AC70: =(AB70-U70*1000) -> 0 | AD70: =(AB70*W70/1000) -> 430 | AE70: =(AD70*0.05) -> 21.5 | AF70: PAGO | AJ70: CASA DA UVA | AK70: ADMILSON (19) 3246-0184/3746-5120/3746-1200 | AR70: NICO CONTABILIDADE 19 3234-5737 | BO70: =SUM(BO65:BO69) -> 12755.332 | BP70: =SUM(BP65:BP69) -> 640.37392 | BT70: FILME PVC EST. 60 MM X 40 MICRA | BU70: 38 | BV70: E-MAIL | BW70: 43566 | BX70: 500 | BY70: KG | BZ70: 10.6 | CB70: 43609 | CC70: 43599 | CD70: 54733 | CE70: 501.02 | CF70: =(CE70-BX70) -> 1.02 | CG70: =(CE70*BZ68) -> 5310.812 | CH70: =(CG70*0.05) -> 265.5406 | DE70: VALVULA 6103 COM FILTRO | DF70: 21 | DG70: E-MAIL | DH70: 44438 | DI70: 153 | DJ70: MIL | DK70: 261.13 | DM70: 44459 | DN70: 44459 | DP70: 153000 | DQ70: =(DI70*1000-DP70) -> 0 | DR70: 39952.97 | DS70: =(DN70+28) -> 44487 | DT70: =(DR70*0.03) -> 1198.5891
P71: CEU AZUL | Q71: EMBALAGEM TOMATINHO - SRT 07 | R71: 3 | S71: VERBAL | T71: 42866 | U71: 10 | V71: MIL | W71: 154 | Y71: 42870 | Z71: 42867 | AA71: 1931 | AB71: 10500 | AC71: =(AB71-U71*1000) -> 500 | AD71: =(AB71*W71/1000) -> 1617 | AE71: =(AD71*0.05) -> 80.85 | AF71: PAGO | AL71: OC | AM71: DATA | AP71: PREÇO | AQ71: CODIGO | AR71: DATA | AS71: DATA | AX71: VALOR DA | BT71: FILME PVC EST. 60 MM X 40 MICRA | BU71: 39 | BV71: E-MAIL | BW71: 43566 | BX71: 500 | BY71: KG | BZ71: 10.6 | CB71: 43612 | CC71: 43607 | CD71: 54821 | CE71: 500.98 | CF71: =(CE71-BX71) -> 0.98 | CG71: =(CE71*BZ69) -> 5310.388 | CH71: =(CG71*0.05) -> 265.5194 | DE71: VALVULA 6103 COM FILTRO | DF71: 22 | DG71: 26561 | DH71: 44480 | DI71: 160 | DJ71: MIL | DK71: 227.07 | DM71: 44489 | DN71: 44489 | DP71: 160000 | DQ71: =(DI71*1000-DP71) -> 0 | DR71: =(DK71*DP71/1000) -> 36331.2 | DS71: =(DN71+28) -> 44517 | DT71: =(DR71*0.03) -> 1089.936
B72: SERRAPLAST | C72: =(AE969) -> 15339.728 | D72: =(AE1006) -> 10924.025 | E72: =(AE1036) -> 11504.617 | F72: =(AE1085) -> 22925.215 | G72: =(AE1126) -> 14584.42 | H72: =(AE1166) -> 16879.558 | I72: =(AE1197) -> 15555.617 | J72: =(AE1227) -> 15574.319 | K72: =(AE1280) -> 19022.175 | L72: =(AE1317) -> 12684.935 | M72: =(AE1362) -> 15988.838 | N72: =(AE1408) -> 7437.0325 | P72: KORIN | Q72: EMB. OVO GALINHA 10 UND SRG - C10 | R72: 11 | S72: 5719 | T72: 42866 | U72: 130 | V72: MIL | W72: 260 | Y72: 42881 | Z72: 42876 | AA72: 9597 | AB72: 130000 | AC72: =(AB72-U72*1000) -> 0 | AD72: =(AB72*W72/1000) -> 33800 | AE72: =(AD72*0.05) -> 1690 | AF72: PAGO | AJ72: PRODUTO | AK72: PEDIDO | AL72: DO | AM72: DO | AN72: QUANT | AO72: UND | AP72: POR | AQ72: DO | AR72: DE | AS72: DE | AT72: N F | AU72: QUANT | AV72: SALDO | AW72: VALOR | AX72: COMISSÃO | AY72: OBSERVAÇÃO | BA72: BRASIL SUL SETEMBRO 2017 | BT72: FILME PVC EST. 60 MM X 40 MICRA | BU72: 40 | BV72: E-MAIL | BW72: 43566 | BX72: 500 | BY72: KG | BZ72: 10.6 | CB72: 43612 | CC72: 43612 | CD72: 54878 | CE72: 499.4 | CF72: =(CE72-BX72) -> -0.6 | CG72: =(CE72*BZ70) -> 5293.64 | CH72: =(CG72*0.05) -> 264.682
P73: LOSCHI & WATANABE | Q73: CUMBUCA 500 G - MA 15 | R73: 3 | S73: verbal | T73: 42870 | U73: 30 | V73: MIL | W73: 300 | Y73: 42874 | Z73: 42874 | AA73: 1958 | AB73: 30000 | AC73: =(AB73-U73*1000) -> 0 | AD73: =(AB73*W73/1000) -> 9000 | AE73: =(AD73*0.05) -> 450 | AF73: PAGO | AL73: CLIENTE | AM73: PEDIDO | AP73: UND | AQ73: CLIENTE | AR73: ENTREGA | AS73: FATURA | AX73: R$ | BD73: OC | BE73: DATA | BH73: PREÇO | BI73: CODIGO | BJ73: DATA | BK73: DATA | BP73: VALOR DA | BT73: FILME PVC EST. 60 MM X 40 MICRA | BU73: 41 | BV73: E-MAIL | BW73: 43566 | BX73: 500 | BY73: KG | BZ73: 10.6 | CB73: 43616 | CC73: 43616 | CD73: 54935 | CE73: 506.39 | CF73: =(CE73-BX73) -> 6.39 | CG73: =(CE73*BZ71) -> 5367.734 | CH73: =(CG73*0.05) -> 268.3867
B74: CCS | C74: =(DA469) -> 920.754 | D74: =(DA482) -> 0 | E74: =(DA495) -> 2568.9111 | F74: =(DA508) -> 3621.5283 | G74: =(DA521) -> 0 | H74: =(DA534) -> 0 | I74: =(DA547) -> 2084.5 | J74: =(DA560) -> 1042.2513 | K74: =(DA573) -> 0 | L74: =(DA590) -> 1780.0203 | M74: =(DA603) -> 2528.2662 | N74: =(DA618) -> 0 | P74: FAZENDA DA TOCA | Q74: EMB. OVO GALINHA 06 UND SRG - C06 | R74: 5 | T74: 42874 | U74: 15 | V74: MIL | W74: 400 | X74: 1010506 | Y74: 42874 | Z74: 42874 | AA74: 9598 | AB74: 14000 | AC74: =(AB74-U74*1000) -> -1000 | AD74: =(AB74*W74/1000) -> 5600 | AE74: =(AD74*0.05) -> 280 | AF74: PAGO | AJ74: CUMBUCA 500 G - MA 15 | AK74: 1 | AL74: E-MAIL | AM74: 42639 | AN74: 15 | AO74: MIL | AP74: 315 | AR74: 42640 | AS74: 42640 | AT74: 1394 | AU74: 15000 | AV74: =(AU74-AN74*1000) -> 0 | AW74: =(AU74*AP74/1000) -> 4725 | AX74: =(AW74*0.05) -> 236.25 | BA74: CLIENTE | BB74: PRODUTO | BC74: PEDIDO | BD74: DO | BE74: DO | BF74: QUANT | BG74: UND | BH74: POR | BI74: DO | BJ74: DE | BK74: DE | BL74: N F | BM74: QUANT | BN74: SALDO | BO74: VALOR | BP74: COMISSÃO | BQ74: OBSERVAÇÃO | BT74: FILME PVC EST. 60 MM X 40 MICRA | BU74: 42 | BV74: E-MAIL | BW74: 43566 | BX74: 500 | BY74: KG | BZ74: 10.6 | CB74: 43623 | CC74: 43623 | CD74: 55021 | CE74: 509.74 | CF74: =(CE74-BX74) -> 9.74 | CG74: =(CE74*BZ72) -> 5403.244 | CH74: =(CG74*0.05) -> 270.1622
P75: CACO | Q75: CUMBUCA 500 G - MA 15 | R75: 10 | S75: VERBAL | T75: 42879 | U75: 15 | V75: MIL | W75: 310 | Y75: 42886 | Z75: 42888 | AA75: 1999 | AB75: 15000 | AC75: =(AB75-U75*1000) -> 0 | AD75: =(AB75*W75/1000) -> 4650 | AE75: =(AD75*0.05) -> 232.5 | AF75: PAGO | AJ75: CUMBUCA 500 G - MA 15 | AK75: 2 | AL75: VERBAL | AM75: 42709 | AN75: 15 | AO75: MIL | AP75: 315 | AR75: 42714 | AS75: 42716 | AT75: 1564 | AU75: 15000 | AV75: =(AU75-AN75*1000) -> 0 | AW75: =(AU75*AP75/1000) -> 4725 | AX75: =(AW75*0.05) -> 236.25 | BD75: CLIENTE | BE75: PEDIDO | BH75: UND | BI75: CLIENTE | BJ75: ENTREGA | BK75: FATURA | BP75: R$ | BT75: FILME PVC EST. 60 MM X 40 MICRA | BU75: 43 | BV75: E-MAIL | BW75: 43566 | BX75: 500 | BY75: KG | BZ75: 10.6 | CB75: 43630 | CC75: 43628 | CD75: 55075 | CE75: 511.47 | CF75: =(CE75-BX75) -> 11.47 | CG75: =(CE75*BZ73) -> 5421.582 | CH75: =(CG75*0.05) -> 271.0791 | CY75: =SUM(CY68:CY74) -> 41512.5 | DA75: =SUM(DA68:DA74) -> 1245.375 | EK75: =SUM(EK68:EK74) -> 0 | EM75: =SUM(EM68:EM74) -> 0
B76: BRASIL SUL | C76: =(BP517) -> 1282.5666 | D76: =(BP530) -> 2598.0154 | E76: =(BP543) -> 3066.0053 | F76: =(BP556) -> 3339.9808 | G76: =(BP569) -> 5601.3717 | H76: =(BP586) -> 4225.1767 | I76: =(BP599) -> 2980.3585 | J76: =(BP614) -> 3840.3285 | K76: =(BP627) -> 3832.8334 | L76: =(BP640) -> 2874.8067 | M76: =(BP653) -> 478.43902 | N76: =(BP666) -> 1912 | P76: JOSE PAULO LAZZARI | Q76: EMB. OVO GALINHA 10 UND SRG - C10 | R76: 4 | S76: E-MAIL | T76: 42874 | U76: 0.5 | V76: MIL | W76: 430 | Y76: 42878 | Z76: 42884 | AA76: 1988 | AB76: 1000 | AC76: =(AB76-U76*1000) -> 500 | AD76: =(AB76*W76/1000) -> 430 | AE76: =(AD76*0.05) -> 21.5 | AF76: PAGO | AJ76: EMBALAGEM TOMATINHO - SRT 08 | AK76: 3 | AL76: VERBAL | AM76: 42709 | AN76: 10 | AO76: MIL | AP76: 153.7 | AR76: 42714 | AS76: 42716 | AT76: 1564 | AU76: 10000 | AV76: =(AU76-AN76*1000) -> 0 | AW76: =(AU76*AP76/1000) -> 1537 | AX76: =(AW76*0.05) -> 76.85 | BA76: INDUSCON | BB76: FILME PVC EST. 60 MM X 40 MICRA | BC76: 2 | BD76: e-mail | BE76: 42933 | BF76: 500 | BG76: KG | BH76: 8.7 | BJ76: 42936 | BK76: 42950 | BM76: 500 | BN76: =(BM76-BF76) -> 0 | BO76: 0 | BP76: =(BO76*0.05) -> 0 | BQ76: CANCELADO | BT76: FILME PVC EST. 60 MM X 40 MICRA | BU76: 44 | BV76: E-MAIL | BW76: 43566 | BX76: 500 | BY76: KG | BZ76: 10.6 | CB76: 43640 | CC76: 43635 | CD76: 55138 | CE76: 513.09 | CF76: =(CE76-BX76) -> 13.09 | CG76: =(CE76*BZ76) -> 5438.754 | CH76: =(CG76*0.05) -> 271.9377
P77: BIANCHI | Q77: EMB. OVO GALINHA 10 UND SRG - C10 | R77: 7 | S77: E-MAIL | T77: 42879 | U77: 10 | V77: MIL | W77: 270 | Y77: 42886 | Z77: 42881 | AA77: 1979 | AB77: 10000 | AC77: =(AB77-U77*1000) -> 0 | AD77: =(AB77*W77/1000) -> 2700 | AE77: =(AD77*0.05) -> 135 | AF77: PAGO | AJ77: CUMBUCA 500 G - MA 15 | AK77: 4 | AL77: VERBAL | AM77: 43084 | AN77: 5 | AO77: MIL | AP77: 315 | AR77: 43087 | AS77: 43087 | AT77: 2673 | AU77: 5000 | AV77: =(AU77-AN77*1000) -> 0 | AW77: =(AU77*AP77/1000) -> 1575 | AX77: =(AW77*0.05) -> 78.75 | BA77: GO GREEN | BB77: FILME PVC GA 380 X 10 X 1200 | BC77: 5 | BD77: VERBAL | BE77: 42948 | BF77: 40 | BG77: BOB | BH77: 52.9 | BJ77: 42957 | BK77: 42957 | BL77: 48119 | BM77: 40 | BN77: =(BM77-BF77) -> 0 | BO77: =(BM77*BH77) -> 2116 | BP77: =(BO77*0.05) -> 105.8 | BT77: FILME PVC EST. 60 MM X 40 MICRA | BU77: 45 | BV77: E-MAIL | BW77: 43633 | BX77: 1400 | BY77: KG | BZ77: 10.6 | CB77: 43644 | CC77: 43644 | CD77: 55228 | CE77: 994.18 | CF77: =(CE77-BX77) -> -405.82 | CG77: =(CE77*BZ75) -> 10538.308 | CH77: =(CG77*0.05) -> 526.9154 | CK77: CCS AGOSTO 2018 | DW77: EDIPRINT MARÇO 2022
B78: EDIPRINT | M78: =(EM28) -> 174.78 | N78: =(EM49) -> 256.984 | P78: BIANCHI | Q78: EMB. OVO GALINHA 10 UND SRG - C10 | R78: 8 | S78: E-MAIL | T78: 42879 | U78: 10 | V78: MIL | W78: 350 | Y78: 42886 | Z78: 42881 | AA78: 1979 | AB78: 10000 | AC78: =(AB78-U78*1000) -> 0 | AD78: =(AB78*W78/1000) -> 3500 | AE78: =(AD78*0.05) -> 175 | AF78: PAGO | AJ78: CUMBUCA 500 G - MA 15 | AK78: 5 | AL78: VERBAL | AM78: 43123 | AN78: 10 | AO78: MIL | AP78: 300 | AR78: 43126 | AS78: 43126 | AT78: 2747 | AU78: 10000 | AV78: =(AU78-AN78*1000) -> 0 | AW78: =(AU78*AP78/1000) -> 3000 | AX78: =(AW78*0.05) -> 150 | BA78: GO GREEN | BB78: FILME PVC GA 285 X 14 X 1000 | BC78: 4 | BD78: VERBAL | BE78: 42929 | BF78: 5 | BG78: BOB | BH78: 70 | BJ78: 42936 | BK78: 42962 | BL78: 48177 | BM78: 5 | BN78: =(BM78-BF78) -> 0 | BO78: 354.76 | BP78: =(BO78*0.05) -> 17.738 | BT78: FILME PVC EST. 60 MM X 40 MICRA | BU78: 45 | BV78: E-MAIL | BW78: 43633 | BX78: 405 | BY78: KG | BZ78: 10.6 | CB78: 43651 | CC78: 43647 | CD78: 55245 | CE78: 411.97 | CF78: =(CE78-BX78) -> 6.97 | CG78: =(CE78*BZ76) -> 4366.882 | CH78: =(CG78*0.05) -> 218.3441 | CN78: OC | CO78: DATA | CR78: PREÇO | CS78: CODIGO | CT78: DATA | CU78: DATA | CZ78: DATA | DA78: VALOR DA | DZ78: OC | EA78: DATA | ED78: PREÇO | EE78: CODIGO | EF78: DATA | EG78: DATA | EL78: DATA | EM78: VALOR DA
AJ79: CUMBUCA 500 G - MA 15 | AK79: 6 | AL79: VERBAL | AM79: 43206 | AN79: 10 | AO79: MIL | AP79: 300 | AR79: 43213 | AS79: 43210 | AT79: 10136 | AU79: 10000 | AV79: =(AU79-AN79*1000) -> 0 | AW79: =(AU79*AP79/1000) -> 3000 | AX79: =(AW79*0.05) -> 150 | BT79: FILME PVC EST. 60 MM X 40 MICRA | BU79: 46 | BV79: E-MAIL | BW79: 43633 | BX79: 1400 | BY79: KG | BZ79: 10.6 | CB79: 43651 | CC79: 43650 | CD79: 55294 | CE79: 1415.74 | CF79: =(CE79-BX79) -> 15.74 | CG79: =(CE79*BZ77) -> 15006.844 | CH79: =(CG79*0.05) -> 750.3422 | CK79: CLIENTE | CL79: PRODUTO | CM79: PEDIDO | CN79: DO | CO79: DO | CP79: QUANT | CQ79: UND | CR79: POR | CS79: DO | CT79: DE | CU79: DE | CV79: N F | CW79: QUANT | CX79: SALDO | CY79: VALOR | CZ79: COMISSÃO | DA79: COMISSÃO | DB79: OBSERVAÇÃO | DW79: CLIENTE | DX79: PRODUTO | DY79: PEDIDO | DZ79: DO | EA79: DO | EB79: QUANT | EC79: UND | ED79: POR | EE79: DO | EF79: DE | EG79: DE | EH79: N F | EI79: QUANT | EJ79: SALDO | EK79: VALOR | EL79: COMISSÃO | EM79: COMISSÃO | EN79: OBSERVAÇÃO
AD80: =SUM(AD70:AD79) -> 61727 | AE80: =(AD80*0.05) -> 3086.35 | AJ80: CUMBUCA 500 G - MA 15 | AK80: 7 | AL80: VERBAL | AM80: 43307 | AN80: 10 | AO80: MIL | AP80: 300 | AR80: 43311 | AS80: 43308 | AT80: 10398 | AU80: 10000 | AV80: =(AU80-AN80*1000) -> 0 | AW80: =(AU80*AP80/1000) -> 3000 | AX80: =(AW80*0.05) -> 150 | BO80: =SUM(BO76:BO79) -> 2470.76 | BP80: =(BO80*0.05) -> 123.538 | BT80: FILME PVC EST. 60 MM X 40 MICRA | BU80: 47 | BV80: E-MAIL | BW80: 43633 | BX80: 1400 | BY80: KG | BZ80: 10.6 | CB80: 43661 | CC80: 43661 | CD80: 55407 | CE80: 1412.9 | CF80: =(CE80-BX80) -> 12.9 | CG80: =(CE80*BZ78) -> 14976.74 | CH80: =(CG80*0.05) -> 748.837 | CN80: CLIENTE | CO80: PEDIDO | CR80: UND | CS80: CLIENTE | CT80: ENTREGA | CU80: FATURA | CZ80: 30 DD | DA80: R$ | DZ80: CLIENTE | EA80: PEDIDO | ED80: UND | EE80: CLIENTE | EF80: ENTREGA | EG80: FATURA | EL80: 30 DD | EM80: R$
AJ81: CUMBUCA 500 G - MA 15 CRISTAL | AK81: 8 | AL81: E-MAIL | AM81: 43430 | AN81: 10 | AO81: MIL | AP81: 335 | AR81: 43437 | AS81: 43438 | AT81: 10635 | AU81: 10000 | AV81: =(AU81-AN81*1000) -> 0 | AW81: =(AU81*AP81/1000) -> 3350 | AX81: =(AW81*0.05) -> 167.5 | BT81: FILME PVC EST. 60 MM X 40 MICRA | BU81: 48 | BV81: E-MAIL | BW81: 43812 | BX81: 300 | BY81: KG | BZ81: 10.6 | CB81: 43817 | CC81: 43817 | CD81: 57223 | CE81: 309.03 | CF81: =(CE81-BX81) -> 9.03 | CG81: =(CE81*BZ79) -> 3275.718 | CH81: =(CG81*0.05) -> 163.7859 | CK81: SUPERBOM | CL81: CONJUNTO ENVASE MEL 200G | CM81: 135 | CO81: 43125 | CP81: 45 | CQ81: MIL | CR81: 922.5 | CT81: 43285 | CU81: 43291 | CV81: 13424 | CW81: 45000 | CX81: =(CP81*1000-CW81) -> 0 | CY81: =(CR81*CW81/1000) -> 41512.5 | CZ81: =(CU81+42) -> 43333 | DA81: =(CY81*0.03) -> 1245.375 | DB81: PAGO
P82: SERRAPLAST JULHO 2017 | AJ82: CUMBUCA 500 G - MA 15 CRISTAL | AK82: 9 | AL82: VERBAL | AM82: 43504 | AN82: 10 | AO82: MIL | AP82: 335 | AR82: 43508 | AS82: 43524 | AT82: 3662 | AU82: 10000 | AV82: =(AU82-AN82*1000) -> 0 | AW82: =(AU82*AP82/1000) -> 3350 | AX82: =(AW82*0.05) -> 167.5 | BA82: BRASIL SUL OUTUBRO 2017 | BT82: FILME PVC EST. 60 MM X 40 MICRA | BU82: 49 | BV82: E-MAIL | BW82: 43812 | BX82: 1001 | BY82: KG | BZ82: 10.6 | CB82: 43840 | CC82: 43843 | CD82: 57292 | CE82: 1014.39 | CF82: =(CE82-BX82) -> 13.39 | CG82: =(CE82*BZ80) -> 10752.534 | CH82: =(CG82*0.05) -> 537.6267
B83: TOTAL | C83: =SUM(C72:C82) -> 17543.048 | D83: =SUM(D72:D82) -> 13522.04 | E83: =SUM(E72:E82) -> 17139.533 | F83: =SUM(F72:F82) -> 29886.724 | G83: =SUM(G72:G82) -> 20185.792 | H83: =(H72+H74+H76) -> 21104.734 | I83: =SUM(I72:I82) -> 20620.475 | J83: =SUM(J72:J82) -> 20456.898 | K83: =SUM(K72:K82) -> 22855.008 | L83: =SUM(L72:L82) -> 17339.762 | M83: =SUM(M72:M82) -> 19170.323 | N83: =SUM(N72:N82) -> 9606.0165 | O83: =SUM(C83:N83) -> 229430.35 | S83: OC | T83: DATA | W83: PREÇO | X83: CODIGO | Y83: DATA | Z83: DATA | AE83: VALOR DA | AJ83: CUMBUCA 500 G - MA 15 CRISTAL | AK83: 10 | AL83: VERBAL | AM83: 43676 | AN83: 10 | AO83: MIL | AP83: 335 | AR83: 43679 | AS83: 43679 | AT83: 3874 | AU83: 10000 | AV83: =(AU83-AN83*1000) -> 0 | AW83: =(AU83*AP83/1000) -> 3350 | AX83: =(AW83*0.05) -> 167.5 | BD83: OC | BE83: DATA | BH83: PREÇO | BI83: CODIGO | BJ83: DATA | BK83: DATA | BP83: VALOR DA
N84: =(O83) -> 229430.35 | AJ84: CUMBUCA 500 G - MA 15 CRISTAL | AK84: 11 | AL84: WHATSAPP | AM84: 43768 | AN84: 10 | AO84: MIL | AP84: 335 | AR84: 43773 | AS84: 43770 | AT84: 3968 | AU84: 10000 | AV84: =(AU84-AN84*1000) -> 0 | AW84: =(AU84*AP84/1000) -> 3350 | AX84: =(AW84*0.05) -> 167.5
AJ85: CUMBUCA 500 G - MA 15 CRISTAL | AK85: 12 | AL85: WHATSAPP | AM85: 43803 | AN85: 10 | AO85: MIL | AP85: 335 | AR85: 43815 | AS85: 43816 | AT85: 12294 | AU85: 10000 | AV85: =(AU85-AN85*1000) -> 0 | AW85: =(AU85*AP85/1000) -> 3350 | AX85: =(AW85*0.05) -> 167.5
P86: CLIENTE | Q86: PRODUTO | R86: PEDIDO | S86: DO | T86: DO | U86: QUANT | V86: UND | W86: POR | X86: DO | Y86: DE | Z86: DE | AA86: N F | AB86: QUANT | AC86: SALDO | AD86: VALOR | AE86: COMISSÃO | AF86: OBSERVAÇÃO | AJ86: CUMBUCA 500 G - MA 15 CRISTAL | AK86: 13 | AL86: WHATSAPP | AM86: 43965 | AN86: 10 | AO86: MIL | AP86: 335 | AR86: 43969 | AS86: 43966 | AT86: 13173 | AU86: 10000 | AV86: =(AU86-AN86*1000) -> 0 | AW86: =(AU86*AP86/1000) -> 3350 | AX86: =(AW86*0.05) -> 167.5
S87: CLIENTE | T87: PEDIDO | W87: UND | X87: CLIENTE | Y87: ENTREGA | Z87: FATURA | AE87: R$ | AJ87: CUMBUCA 500 G - MA 15 CRISTAL | AK87: 14 | AL87: WHATSAPP | AM87: 44054 | AN87: 10 | AO87: MIL | AP87: 335 | AR87: 44060 | AS87: 44055 | AT87: 13640 | AU87: 10000 | AV87: =(AU87-AN87*1000) -> 0 | AW87: =(AU87*AP87/1000) -> 3350 | AX87: =(AW87*0.05) -> 167.5 | BA87: CLIENTE | BB87: PRODUTO | BC87: PEDIDO | BD87: DO | BE87: DO | BF87: QUANT | BG87: UND | BH87: POR | BI87: DO | BJ87: DE | BK87: DE | BL87: N F | BM87: QUANT | BN87: SALDO | BO87: VALOR | BP87: COMISSÃO | BQ87: OBSERVAÇÃO
P88: KORIN | Q88: EMB. OVO GALINHA 10 UND SRG - C10 | R88: 12 | S88: 6691 | T88: 42891 | U88: 140 | V88: MIL | W88: 270 | Y88: 42914 | Z88: 42909 | AA88: 9629 | AB88: 140000 | AC88: =(AB88-U88*1000) -> 0 | AD88: =(AB88*W88/1000) -> 37800 | AE88: =(AD88*0.05) -> 1890 | AF88: PAGO | AJ88: CUMBUCA 500 G - MA 15 CRISTAL | AK88: 15 | AL88: WHATSAPP | AM88: 44123 | AN88: 10 | AO88: MIL | AP88: 335 | AR88: 44125 | AS88: 44127 | AT88: 14173 | AU88: 10000 | AV88: =(AU88-AN88*1000) -> 0 | AW88: =(AU88*AP88/1000) -> 3350 | AX88: =(AW88*0.05) -> 167.5 | BD88: CLIENTE | BE88: PEDIDO | BH88: UND | BI88: CLIENTE | BJ88: ENTREGA | BK88: FATURA | BP88: R$
P89: JOSE PAULO LAZZARI | Q89: EMB. OVO GALINHA 10 UND SRG - C10 | R89: 5 | S89: E-MAIL | T89: 42892 | U89: 1 | V89: MIL | W89: 430 | Y89: 42893 | Z89: 42892 | AA89: 2006 | AB89: 1000 | AC89: =(AB89-U89*1000) -> 0 | AD89: =(AB89*W89/1000) -> 430 | AE89: =(AD89*0.05) -> 21.5 | AF89: PAGO | AJ89: CUMBUCA 500 G - MA 15 CRISTAL | AK89: 16 | AL89: VERBAL | AM89: 44165 | AN89: 10 | AO89: MIL | AP89: 355 | AR89: 44172 | AS89: 44173 | AT89: 14478 | AU89: 10000 | AV89: =(AU89-AN89*1000) -> 0 | AW89: =(AU89*AP89/1000) -> 3550 | AX89: =(AW89*0.05) -> 177.5 | BA89: COBREMACK BAHIA | BB89: FILME PVC EST. 60 MM X 40 MICRA | BC89: 3 | BD89: 20318/1 | BE89: 42979 | BF89: 1000 | BG89: KG | BH89: 9.7 | BJ89: 42989 | BK89: 42989 | BM89: 1000 | BN89: =(BM89-BF89) -> 0 | BO89: =(BM89*BH89) -> 9700 | BP89: =(BO89*0.05) -> 485
P90: JOSE PAULO LAZZARI | Q90: EMB. OVO GALINHA 10 UND SRG - C10 | R90: 6 | S90: E-MAIL | T90: 42914 | U90: 3 | V90: MIL | W90: 383.33 | Y90: 42916 | Z90: 42916 | AB90: 3000 | AC90: =(AB90-U90*1000) -> 0 | AD90: 0 | AE90: 0 | AF90: CANCELADO | AJ90: CUMBUCA 500 G - MA 15 CRISTAL | AK90: 17 | AL90: VERBAL | AM90: 44166 | AN90: 15 | AO90: MIL | AP90: 355 | AR90: 44182 | AS90: 44182 | AT90: 14739 | AU90: 15000 | AV90: =(AU90-AN90*1000) -> 0 | AW90: =(AU90*AP90/1000) -> 5325 | AX90: =(AW90*0.05) -> 266.25 | BA90: GO GREEN | BB90: FILME PVC GA 285 X 14 X 1000 | BC90: 6 | BD90: VERBAL | BE90: 42983 | BF90: 100 | BG90: BOB | BH90: 70 | BJ90: 42998 | BK90: 42998 | BM90: 100 | BN90: =(BM90-BF90) -> 0 | BO90: =(BM90*BH90) -> 7000 | BP90: 0 | CY90: =SUM(CY81:CY89) -> 41512.5 | DA90: =SUM(DA81:DA89) -> 1245.375 | EK90: =SUM(EK81:EK89) -> 0 | EM90: =SUM(EM81:EM89) -> 0
P91: JOSE PAULO LAZZARI | Q91: EMB. OVO GALINHA 10 UND SRG - C10 | R91: 7 | S91: E-MAIL | T91: 42914 | U91: 1 | V91: MIL | W91: 430 | Y91: 42916 | Z91: 42915 | AA91: 2052 | AB91: 1000 | AC91: =(AB91-U91*1000) -> 0 | AD91: =(AB91*W91/1000) -> 430 | AE91: =(AD91*0.05) -> 21.5 | AF91: PAGO | BA91: IRMÃOS GONÇALVES | BB91: FILME PVC STRETCH 500 MM X 25 MICRA | BC91: 1 | BD91: e-mail | BE91: 42984 | BF91: 110 | BG91: KG | BH91: 9.4 | BJ91: 43003 | BK91: 43003 | BM91: 110 | BN91: =(BM91-BF91) -> 0 | BO91: =(BM91*BH91) -> 1034 | BP91: =(BO91*0.05) -> 51.7 | BT91: COBREMACK SÃO PAULO | BV91: ANDREIA (11) 4156-5531 (11) 98449-7780 | CB91: JULIANA | CC91: DANILO
BA92: GO GREEN | BB92: FILME PVC GA 380 X 10 X 1200 | BC92: 7 | BD92: VERBAL | BE92: 42989 | BF92: 100 | BG92: BOB | BH92: 52.9 | BJ92: 42998 | BK92: 42998 | BM92: 100 | BN92: =(BM92-BF92) -> 0 | BO92: =(BM92*BH92) -> 5290 | BP92: =(BO92*0.05) -> 264.5 | BV92: OC | BW92: DATA | BZ92: PREÇO | CA92: CODIGO | CB92: DATA | CC92: DATA | CH92: VALOR DA | CK92: CCS SETEMBRO 2018
AD93: =SUM(AD88:AD92) -> 38660 | AE93: =(AD93*0.05) -> 1933 | BA93: INDUSCON | BB93: FILME PVC EST. 60 MM X 40 MICRA | BC93: 3 | BD93: 43488 | BE93: 42990 | BF93: 500 | BG93: KG | BH93: 8.7 | BJ93: 43000 | BK93: 42998 | BL93: 48576 | BM93: 507.22 | BN93: =(BM93-BF93) -> 7.22 | BO93: =(BM93*BH93) -> 4412.814 | BP93: =(BO93*0.035) -> 154.44849 | BT93: PRODUTO | BU93: PEDIDO | BV93: DO | BW93: DO | BX93: QUANT | BY93: UND | BZ93: POR | CA93: DO | CB93: DE | CC93: DE | CD93: N F | CE93: QUANT | CF93: SALDO | CG93: VALOR | CH93: COMISSÃO | CI93: OBSERVAÇÃO | CN93: OC | CO93: DATA | CR93: PREÇO | CS93: CODIGO | CT93: DATA | CU93: DATA | CZ93: DATA | DA93: VALOR DA
BA94: COBREFLEX | BB94: FILME PVC EST. 60 MM X 40 MICRA | BC94: 1 | BD94: E-MAIL | BE94: 42995 | BF94: 500 | BG94: KG | BH94: 8.7 | BJ94: 42998 | BK94: 43000 | BL94: 48618 | BM94: 504 | BN94: =(BM94-BF94) -> 4 | BO94: =(BM94*BH94) -> 4384.8 | BP94: =(BO94*0.05) -> 219.24 | BV94: CLIENTE | BW94: PEDIDO | BZ94: UND | CA94: CLIENTE | CB94: ENTREGA | CC94: FATURA | CH94: R$ | CK94: CLIENTE | CL94: PRODUTO | CM94: PEDIDO | CN94: DO | CO94: DO | CP94: QUANT | CQ94: UND | CR94: POR | CS94: DO | CT94: DE | CU94: DE | CV94: N F | CW94: QUANT | CX94: SALDO | CY94: VALOR | CZ94: COMISSÃO | DA94: COMISSÃO | DB94: OBSERVAÇÃO
P95: SERRAPLAST AGOSTO 2017 | BT95: FILME PVC EST. 60 MM X 40 MICRA | BU95: 1 | BW95: 42824 | BX95: 1000 | BY95: KG | BZ95: 9.7 | CB95: 42830 | CC95: 42830 | CD95: 46764 | CE95: 272.3 | CF95: =(CE95-BX95) -> -727.7 | CG95: =(CE95*BZ95) -> 2641.31 | CH95: =(CG95*0.06) -> 158.4786 | CN95: CLIENTE | CO95: PEDIDO | CR95: UND | CS95: CLIENTE | CT95: ENTREGA | CU95: FATURA | CZ95: 30 DD | DA95: R$
S96: OC | T96: DATA | W96: PREÇO | X96: CODIGO | Y96: DATA | Z96: DATA | AE96: VALOR DA | BO96: =SUM(BO89:BO95) -> 31821.614 | BP96: =SUM(BP89:BP95) -> 1174.8885 | BX96: 727.7 | BY96: KG | BZ96: 9.7 | CB96: 42830 | CC96: 42842 | CD96: 46850 | CE96: 757.04 | CF96: =(CE96-BX96) -> 29.34 | CG96: =(CE96*BZ96) -> 7343.288 | CH96: =(CG96*0.06) -> 440.59728 | CK96: SUPERBOM | CL96: CONJUNTO ENVASE MEL 200G | CM96: 136 | CO96: 43125 | CP96: 45 | CQ96: MIL | CR96: 922.5 | CT96: 43318 | CU96: 43313 | CV96: 13457 | CW96: 45000 | CX96: =(CP96*1000-CW96) -> 0 | CY96: =(CR96*CW96/1000) -> 41512.5 | CZ96: =(CU96+42) -> 43355 | DA96: =(CY96*0.03) -> 1245.375 | DB96: PAGO
P97: CLIENTE | Q97: PRODUTO | R97: PEDIDO | S97: DO | T97: DO | U97: QUANT | V97: UND | W97: POR | X97: DO | Y97: DE | Z97: DE | AA97: N F | AB97: QUANT | AC97: SALDO | AD97: VALOR | AE97: COMISSÃO | AF97: OBSERVAÇÃO | AY97: DESTACAR IPI | BT97: FILME PVC EST. 60 MM X 40 MICRA | BU97: 2 | BW97: 42905 | BX97: 700 | BY97: KG | BZ97: 9.7 | CB97: 42922 | CC97: 42922 | CD97: 47749 | CE97: 699.56 | CF97: =(CE97-BX97) -> -0.44 | CG97: =(CE97*BZ97) -> 6785.732 | CH97: =(CG97*0.06) -> 407.14392
S98: CLIENTE | T98: PEDIDO | W98: UND | X98: CLIENTE | Y98: ENTREGA | Z98: FATURA | AE98: R$ | BA98: BRASIL SUL NOVEMBRO 2017 | BT98: FILME PVC EST. 60 MM X 40 MICRA | BU98: 3 | BV98: 26551 | BW98: 43525 | BX98: 400 | BY98: KG | BZ98: 10.8 | CB98: 43532 | CC98: 43545 | CD98: 54241 | CE98: 408.64 | CF98: =(CE98-BX98) -> 8.64 | CG98: =(CE98*BZ98) -> 4413.312 | CH98: =(CG98*0.05) -> 220.6656
P99: KORIN | Q99: EMB. OVO GALINHA 10 UND SRG - C10 | R99: 13 | S99: 6691 | T99: 42891 | U99: 140 | V99: MIL | W99: 270 | Y99: 42944 | Z99: 42937 | AA99: 9659 | AB99: 140000 | AC99: =(AB99-U99*1000) -> 0 | AD99: =(AB99*W99/1000) -> 37800 | AE99: =(AD99*0.05) -> 1890 | AF99: PAGO | AJ99: CACO | AK99: JOÃO LUIZ AGORRETA (19) 99763-7618 (19) 3746-1406 | BD99: OC | BE99: DATA | BH99: PREÇO | BI99: CODIGO | BJ99: DATA | BK99: DATA | BP99: VALOR DA | BT99: FILME PVC EST. 60 MM X 40 MICRA | BU99: 4 | BV99: 28058 | BW99: 43664 | BX99: 450 | BY99: KG | BZ99: 10.8 | CB99: 43668 | CC99: 43668 | CD99: 55503 | CE99: 452.89 | CF99: =(CE99-BX99) -> 2.89 | CG99: =(CE99*BZ99) -> 4891.212 | CH99: =(CG99*0.05) -> 244.5606
P100: FAZENDA DA TOCA | Q100: EMB. OVO GALINHA 06 UND SRG - C06 | R100: 6 | S100: 17586 | T100: 42913 | U100: 45 | V100: MIL | W100: 400 | X100: 1010506 | Y100: 42931 | Z100: 42923 | AA100: 9645 | AB100: 45000 | AC100: =(AB100-U100*1000) -> 0 | AD100: =(AB100*W100/1000) -> 18000 | AE100: =(AD100*0.05) -> 900 | AF100: PAGO | AL100: OC | AM100: DATA | AP100: PREÇO | AQ100: CODIGO | AR100: DATA | AS100: DATA | AX100: VALOR DA | BA100: CLIENTE | BB100: PRODUTO | BC100: PEDIDO | BD100: DO | BE100: DO | BF100: QUANT | BG100: UND | BH100: POR | BI100: DO | BJ100: DE | BK100: DE | BL100: N F | BM100: QUANT | BN100: SALDO | BO100: VALOR | BP100: COMISSÃO | BQ100: OBSERVAÇÃO
P101: BENASSI CAMPINAS | Q101: CUMBUCA 500 G - MA15 | R101: 5 | S101: VERBAL | T101: 42916 | U101: 30 | V101: MIL | W101: 300 | Y101: 42922 | Z101: 42919 | AA101: 2066 | AB101: 30000 | AC101: =(AB101-U101*1000) -> 0 | AD101: =(AB101*W101/1000) -> 9000 | AE101: =(AD101*0.05) -> 450 | AF101: PAGO | AJ101: PRODUTO | AK101: PEDIDO | AL101: DO | AM101: DO | AN101: QUANT | AO101: UND | AP101: POR | AQ101: DO | AR101: DE | AS101: DE | AT101: N F | AU101: QUANT | AV101: SALDO | AW101: VALOR | AX101: COMISSÃO | AY101: OBSERVAÇÃO | BD101: CLIENTE | BE101: PEDIDO | BH101: UND | BI101: CLIENTE | BJ101: ENTREGA | BK101: FATURA | BP101: R$
...

Sheet 2025.
B5: 2025
Q6: SERRAPLAST JANEIRO 2025 | BC6: BRASIL SUL JANEIRO 2025 | BU6: ANA BEATRIZ / JOSÉ AILTON | CL6: CCS JANEIRO 2025 | DD6: PLASTRELA | DE6: RUDIMAR SULZBACH 51 3736-1122 | DU6: EDIPRINT JANEIRO 2025 | EM6: SERRAPLAST | FD6: COPOBRAS JANEIRO 2024 | FV6: KORIN AGROPECUARIA - JOSINEIS RODRIGUES - 19 3576-9510 | GM6: STANG - JANEIRO 2025 | HF6: CACO DE MARCHI | HW6: LING PACKING - JANEIRO 2025 | IP6: BACI TRANSPORTES - ANDRÉ DIAS
B7: REPRESENTADAS | C7: JAN 01 | D7: FEV 02 | E7: MAR 03 | F7: ABR 04 | G7: MAI 05 | H7: JUN 06 | I7: JUL 07 | J7: AGO 08 | K7: SET 09 | L7: OUT 10 | M7: NOV 11 | N7: DEZ 12 | T7: OC | U7: DATA | Y7: PREÇO | Z7: DATA | AA7: DATA | AF7: VALOR | AJ7: CASA DA UVA | AK7: ADMILSON (19) 3246-0184/3746-5120/3746-1200 | BF7: OC | BG7: DATA | BJ7: PREÇO | BK7: DATA | BL7: DATA | BQ7: VALOR | BW7: OC | BX7: DATA | CA7: PREÇO | CB7: DATA | CC7: DATA | CH7: VALOR | CO7: OC | CP7: DATA | CS7: PREÇO | CT7: DATA | CU7: DATA | CZ7: VALOR | DF7: OC | DG7: DATA | DJ7: PREÇO | DK7: DATA | DL7: DATA | DQ7: VALOR | DX7: OC | DY7: DATA | EB7: PREÇO | EC7: DATA | ED7: DATA | EI7: VALOR | EO7: OC | EP7: DATA | ES7: PREÇO | ET7: DATA | EU7: DATA | EZ7: VALOR | FG7: OC | FH7: DATA | FK7: PREÇO | FL7: DATA | FM7: DATA | FR7: VALOR | FX7: OC | FY7: DATA | GB7: PREÇO | GC7: DATA | GD7: DATA | GI7: VALOR | GP7: OC | GQ7: DATA | GT7: PREÇO | GU7: DATA | GV7: DATA | HA7: VALOR | HH7: OC | HI7: DATA | HL7: PREÇO | HM7: DATA | HN7: DATA | HS7: VALOR | HZ7: OC | IA7: DATA | ID7: PREÇO | IE7: DATA | IF7: DATA | IK7: VALOR | IR7: OC | IS7: DATA | IV7: PREÇO | IW7: DATA | IX7: DATA | JC7: VALOR
Q8: CLIENTE | R8: PRODUTO | S8: PEDIDO | T8: DO | U8: DO | V8: QUANT | W8: UND | X8: CAIXAS | Y8: POR | Z8: DE | AA8: DE | AB8: NF | AC8: QUANT | AD8: SALDO | AE8: VALOR | AF8: DA | AG8: C | AH8: OBSERVAÇÃO | AL8: OC | AM8: DATA | AQ8: PREÇO | AR8: DATA | AS8: DATA | AX8: VALOR | BC8: CLIENTE | BD8: PRODUTO | BE8: PEDIDO | BF8: DO | BG8: DO | BH8: QUANT | BI8: UND | BJ8: POR | BK8: DE | BL8: DE | BM8: NF | BN8: QUANT | BO8: SALDO | BP8: VALOR | BQ8: DA | BR8: C | BS8: OBSERVAÇÃO | BU8: PRODUTO | BV8: PEDIDO | BW8: DO | BX8: DO | BY8: QUANT | BZ8: UND | CA8: POR | CB8: DE | CC8: DE | CD8: N F | CE8: QUANT | CF8: SALDO | CG8: VALOR | CH8: DA | CI8: C | CJ8: OBSERVAÇÃO | CL8: CLIENTE | CM8: PRODUTO | CN8: PEDIDO | CO8: DO | CP8: DO | CQ8: QUANT | CR8: UND | CS8: POR | CT8: DE | CU8: DE | CV8: NF | CW8: QUANT | CX8: SALDO | CY8: VALOR | CZ8: DA | DA8: C | DB8: OBSERVAÇÃO | DD8: PRODUTO | DE8: PEDIDO | DF8: DO | DG8: DO | DH8: QUANT | DI8: UND | DJ8: POR | DK8: DE | DL8: DE | DM8: N F | DN8: QUANT | DO8: SALDO | DP8: VALOR | DQ8: DA | DR8: C | DS8: OBSERVAÇÃO | DU8: CLIENTE | DV8: PRODUTO | DW8: PEDIDO | DX8: DO | DY8: DO | DZ8: QUANT | EA8: UND | EB8: POR | EC8: DE | ED8: DE | EE8: NF | EF8: QUANT | EG8: SALDO | EH8: VALOR | EI8: DA | EJ8: C | EK8: OBSERVAÇÃO | EM8: PRODUTO | EN8: PEDIDO | EO8: DO | EP8: DO | EQ8: QUANT | ER8: UND | ES8: POR | ET8: DE | EU8: DE | EV8: N F | EW8: QUANT | EX8: SALDO | EY8: VALOR | EZ8: DA | FA8: C | FB8: OBSERVAÇÃO | FD8: CLIENTE | FE8: PRODUTO | FF8: PEDIDO | FG8: DO | FH8: DO | FI8: QUANT | FJ8: UND | FK8: POR | FL8: DE | FM8: DE | FN8: NF | FO8: QUANT | FP8: SALDO | FQ8: VALOR | FR8: DA | FT8: OBSERVAÇÃO | FV8: PRODUTO | FW8: PEDIDO | FX8: DO | FY8: DO | FZ8: QUANT | GA8: UND | GB8: POR | GC8: DE | GD8: DE | GE8: N F | GF8: QUANT | GG8: SALDO | GH8: VALOR | GI8: DA | GJ8: C | GK8: OBSERVAÇÃO | GM8: CLIENTE | GN8: PRODUTO | GO8: PEDIDO | GP8: DO | GQ8: DO | GR8: QUANT | GS8: UND | GT8: POR | GU8: DE | GV8: DE | GW8: NF | GX8: QUANT | GY8: SALDO | GZ8: VALOR | HA8: DA | HB8: C | HC8: CLAUDIA | HD8: OBSERVAÇÃO | HF8: PRODUTO | HG8: PEDIDO | HH8: DO | HI8: DO | HJ8: QUANT | HK8: UND | HL8: POR | HM8: DE | HN8: DE | HO8: N F | HP8: QUANT | HQ8: SALDO | HR8: VALOR | HS8: DA | HT8: C | HU8: OBSERVAÇÃO | HW8: CLIENTE | HX8: PRODUTO | HY8: PEDIDO | HZ8: DO | IA8: DO | IB8: QUANT | IC8: UND | ID8: POR | IE8: DE | IF8: DE | IG8: NF | IH8: QUANT | II8: SALDO | IJ8: VALOR | IK8: DA | IM8: CLAUDIA | IN8: OBSERVAÇÃO | IP8: PRODUTO | IQ8: PEDIDO | IR8: DO | IS8: DO | IT8: QUANT | IU8: UND | IV8: POR | IW8: DE | IX8: DE | IY8: N F | IZ8: QUANT | JA8: SALDO | JB8: VALOR | JC8: DA | JD8: C | JE8: OBSERVAÇÃO
B9: SERRAPLAST | C9: =SERRAPLAST!Q25 -> 28437.878 | D9: =SERRAPLAST!Q52 -> 21569.998 | E9: =SERRAPLAST!Q79 -> 37396.585 | F9: =SERRAPLAST!Q129 -> 41104.831 | G9: =SERRAPLAST!Q167 -> 38411.626 | H9: =SERRAPLAST!Q212 -> 37688.772 | I9: =SERRAPLAST!Q240 -> 29597.325 | J9: =SERRAPLAST!Q267 -> 30523.975 | K9: =SERRAPLAST!Q295 -> 27209.52 | L9: =SERRAPLAST!Q342 -> 37664.205 | M9: =SERRAPLAST!Q384 -> 571 | N9: =SERRAPLAST!Q417 -> 0 | T9: CLIENTE | U9: PEDIDO | Y9: UND | Z9: ENTREGA | AA9: FATURA | AF9: COMISSÃO | AJ9: PRODUTO | AK9: PEDIDO | AL9: DO | AM9: DO | AN9: QUANT | AO9: UND | AP9: CAIXAS | AQ9: POR | AR9: DE | AS9: DE | AT9: N F | AU9: QUANT | AV9: SALDO | AW9: VALOR | AX9: DA | AY9: C | AZ9: OBSERVAÇÃO | BF9: CLIENTE | BG9: PEDIDO | BJ9: UND | BK9: ENTREGA | BL9: FATURA | BQ9: COMISSÃO | BW9: CLIENTE | BX9: PEDIDO | CA9: UND | CB9: ENTREGA | CC9: FATURA | CH9: COMISSÃO | CO9: CLIENTE | CP9: PEDIDO | CS9: UND | CT9: ENTREGA | CU9: FATURA | CZ9: COMISSÃO | DF9: CLIENTE | DG9: PEDIDO | DJ9: UND | DK9: ENTREGA | DL9: FATURA | DQ9: COMISSÃO | DX9: CLIENTE | DY9: PEDIDO | EB9: UND | EC9: ENTREGA | ED9: FATURA | EI9: COMISSÃO | EO9: CLIENTE | EP9: PEDIDO | ES9: UND | ET9: ENTREGA | EU9: FATURA | EZ9: COMISSÃO | FG9: CLIENTE | FH9: PEDIDO | FK9: UND | FL9: ENTREGA | FM9: FATURA | FR9: COMISSÃO | FX9: CLIENTE | FY9: PEDIDO | GB9: UND | GC9: ENTREGA | GD9: FATURA | GI9: COMISSÃO | GP9: CLIENTE | GQ9: PEDIDO | GT9: UND | GU9: ENTREGA | GV9: FATURA | HA9: COMISSÃO | HH9: CLIENTE | HI9: PEDIDO | HL9: UND | HM9: ENTREGA | HN9: FATURA | HS9: COMISSÃO | HZ9: CLIENTE | IA9: PEDIDO | ID9: UND | IE9: ENTREGA | IF9: FATURA | IK9: COMISSÃO | IR9: CLIENTE | IS9: PEDIDO | IV9: UND | IW9: ENTREGA | IX9: FATURA | JC9: COMISSÃO
Q10: ROZENDO | R10: BANDEJA OVO GALINHA 10 UND - ROZENDO | S10: 102 | T10: WTSAPP | U10: 45582 | V10: 56 | W10: MIL | X10: 112 | Y10: 515 | Z10: 45593 | AA10: 45664 | AB10: 24028 | AC10: 56000 | AD10: =(AC10-V10*1000) -> 0 | AE10: =(AC10*Y10/1000) -> 28840 | AF10: =(AE10*0.05) -> 1442 | AG10: 5 | AH10: PAGO | AL10: CLIENTE | AM10: PEDIDO | AQ10: UND | AR10: ENTREGA | AS10: FATURA | AX10: COMISSÃO | DU10: RAIAR ORGÂNICOS | DV10: ETIQUETA BANDEJA OVOS GALINHA 20 UND - NAT. DA TERRA | DW10: 14 | DX10: E-MAIL | DY10: 45643 | DZ10: 100 | EA10: MIL | EB10: 95.82 | EC10: 45664 | ED10: 45673 | EE10: 41222 | EF10: 100010 | EG10: =(DZ10*1000-EF10) -> -10 | EH10: =(EB10*EF10/1000) -> 9582.9582 | EI10: =(EH10*0.04) -> 383.31833 | EJ10: 4 | EK10: PAGO | EM10: ETIQUETA HORTA VITAE 20 UND - ITO | EN10: 26 | EO10: VERBAL | EP10: 45715 | EQ10: 100 | ER10: MIL | ES10: 105.25 | ET10: 45728 | EU10: 45726 | EV10: 41462 | EW10: 106980 | EX10: 0 | EY10: =(ES10*EW10/1000) -> 11259.645 | EZ10: =(EY10*0.04) -> 450.3858 | FA10: 4 | GM10: DAY BRASIL | GN10: FILME STRECH TRANSPARENTE - 500MM x 23 MICRAS | GO10: 14 | GP10: 311005 | GQ10: 45665 | GR10: 500 | GS10: KGS | GT10: 12.5 | GU10: 45672 | GV10: 45671 | GW10: 4313 | GX10: 496 | GY10: =(GR10-GX10) -> 4 | GZ10: =GT10*GX10/1 -> 6200 | HA10: =(GZ10*0.05) -> 310 | HB10: 5 | HC10: =(GZ10*0.02) -> 124 | HD10: PAGO | HW10: CASA DA UVA | HX10: FILME STRECH TRANSP.C/TUBETE - 500MM x 25 MICRAS | HY10: 11 | HZ10: WHATSAPP | IA10: 45666 | IB10: 250 | IC10: KGS | ID10: 12.7 | IE10: 45672 | IF10: 45671 | IG10: 359 | IH10: 256.3 | II10: =(IB10-IH10) -> -6.3 | IJ10: =(IH10*ID10/1) -> 3255.01 | IK10: =(IJ10*0.05) -> 162.7505 | IL10: 5 | IM10: =(IJ10*0.02) -> 65.1002 | IN10: PAGO
B11: LING PACKING | C11: =(IK26) -> 424.552 | D11: =(IK46) -> 161.036 | E11: =(IK64) -> 0 | F11: =(IK85) -> 77.9805 | G11: =(IK103) -> 236.0935 | H11: =(IK123) -> 0 | I11: =(IK148) -> 0 | J11: =(IK166) -> 0 | K11: =(IK184) -> 0 | L11: =(IK202) -> 0 | M11: =(IK221) -> 0 | N11: =(IK239) -> 0 | Q11: ROZENDO | R11: BANDEJA OVO GALINHA 10 UND - ROZENDO | S11: 106 | T11: VERBAL | U11: 45622 | V11: 200 | W11: MIL | X11: 400 | Y11: 515 | Z11: 45639 | AA11: 45664 | AB11: 24028 | AC11: 119000 | AD11: =(AC11-V11*1000) -> -81000 | AE11: =(AC11*Y11/1000) -> 61285 | AF11: =(AE11*0.05) -> 3064.25 | AG11: 5 | AH11: PAGO | AJ11: xxx | DU11: RAIAR ORGÂNICOS | DV11: ROTULO OVO GALINHA 20 UND - OBA BEM QUERER - RAIAR | DW11: 15 | DX11: E-MAIL | DY11: 45643 | DZ11: 100 | EA11: MIL | EB11: 92.84 | EC11: 45664 | ED11: 45673 | EE11: 41222 | EF11: 101140 | EG11: =(DZ11*1000-EF11) -> -1140 | EH11: =(EB11*EF11/1000) -> 9389.8376 | EI11: =(EH11*0.04) -> 375.5935 | EJ11: 4 | EK11: PAGO | EM11: ETIQUETA HORTA VITAE 20 UND - ITO | EN11: 27 | EO11: VERBAL | EP11: 45803 | EQ11: 100 | ER11: MIL | ES11: 104.58 | ET11: 45820 | EU11: 45818 | EV11: 41933 | EW11: 100000 | EX11: 0 | EY11: =(ES11*EW11/1000) -> 10458 | EZ11: =(EY11*0.04) -> 418.32 | FA11: 4 | HW11: TORRES CABRAL | HX11: FILME STRECH TRANSP.S/TUBETE - 500MM x 25 MICRAS | HY11: 8 | HZ11: WHATSAPP | IA11: 45680 | IB11: 121 | IC11: KGS | ID11: 12.9 | IE11: 45685 | IF11: 45680 | IG11: 374 | IH11: 121.7 | II11: =(IB11-IH11) -> -0.7 | IJ11: =(IH11*ID11/1) -> 1569.93 | IK11: =(IJ11*0.05) -> 78.4965 | IL11: 5 | IM11: =(IJ11*0.02) -> 31.3986 | IN11: PAGO
Q12: ROZENDO | R12: BANDEJA OVO GALINHA 12 UND - ROZENDO | S12: 107 | T12: VERBAL | U12: 45622 | V12: 60 | W12: MIL | X12: 120 | Y12: 613 | Z12: 45639 | AA12: 45664 | AB12: 24028 | AC12: 64000 | AD12: =(AC12-V12*1000) -> 4000 | AE12: =(AC12*Y12/1000) -> 39232 | AF12: =(AE12*0.05) -> 1961.6 | AG12: 5 | AH12: PAGO | EM12: ETIQUETA HORTA VITAE 20 UND - ITO | EN12: 28 | EO12: VERBAL | EP12: 45916 | EQ12: 100 | ER12: MIL | ES12: 104.58 | ET12: 45929 | EU12: 45936 | EV12: 42577 | EW12: 106400 | EX12: 0 | EY12: =(ES12*EW12/1000) -> 11127.312 | EZ12: =(EY12*0.04) -> 445.09248 | FA12: 4 | HW12: RAIAR ORGÂNICOS | HX12: FILME STRECH TRANSP.S/TUBETE - 500MM x 25 MICRAS | HY12: 4 | HZ12: WHATSAPP | IA12: 45679 | IB12: 300 | IC12: KGS | ID12: 12.2 | IE12: 45698 | IF12: 45680 | IG12: 373 | IH12: 300.5 | IJ12: =(IH12*ID12/1) -> 3666.1 | IK12: =(IJ12*0.05) -> 183.305 | IL12: 5 | IM12: =(IJ12*0.02) -> 73.322 | IN12: PAGO
B13: BRASIL SUL | C13: =(BQ26) -> 0 | D13: =(BQ46) -> 0 | E13: =(BQ64) -> 3443.1234 | F13: =(BQ80) -> 2462.2384 | G13: =(BQ99) -> 0 | H13: =(BQ111) -> 0 | I13: =(BQ127) -> 3896.7785 | J13: =(BQ152) -> 2286.8036 | K13: =(BQ170) -> 580.59573 | L13: =(BQ188) -> 299.25 | M13: =(BQ206) -> 0 | N13: =(BQ225) -> 0 | Q13: ROZENDO | R13: BANDEJA OVO GALINHA 20 UND - ROZENDO | S13: 108 | T13: VERBAL | U13: 45622 | V13: 35 | W13: MIL | X13: 87.5 | Y13: 1027 | Z13: 45639 | AA13: 45664 | AB13: 24028 | AC13: 33000 | AD13: =(AC13-V13*1000) -> -2000 | AE13: =(AC13*Y13/1000) -> 33891 | AF13: =(AE13*0.05) -> 1694.55 | AG13: 5 | AH13: PAGO
Q14: RAIAR | R14: BANDEJA OVO GALINHA 20 UND - OVO GRANDE - RAIAR | S14: 39 | T14: 930 | U14: 45602 | V14: 23.2 | W14: MIL | X14: 58 | Y14: 1182.3 | Z14: 45649 | AA14: 45673 | AB14: 24114 | AC14: 23200 | AD14: =(AC14-V14*1000) -> 0 | AE14: =(AC14*Y14/1000) -> 27429.36 | AF14: =(AE14*0.05) -> 1371.468 | AG14: 5 | AH14: PAGO
B15: CCS | C15: =(CZ26) -> 0 | D15: =(CZ48) -> 0 | E15: =(CZ66) -> 0 | F15: =(CZ87) -> 0 | G15: =(CZ105) -> 1579.68 | H15: =(CZ116) -> 0 | I15: =(CZ130) -> 0 | J15: =(CZ153) -> 1579.68 | K15: =(CZ171) -> 0 | L15: =(CZ191) -> 0 | M15: =(CZ210) -> 0 | N15: =(CZ228) -> 0 | Q15: RAIAR | R15: BANDEJA OVO GALINHA 20 UND - OVO GRANDE - RAIAR | S15: 40 | T15: 932 | U15: 45602 | V15: 23.2 | W15: MIL | X15: 58 | Y15: 1327 | Z15: 45667 | AA15: 45673 | AB15: 24114 | AC15: 23200 | AD15: =(AC15-V15*1000) -> 0 | AE15: =(AC15*Y15/1000) -> 30786.4 | AF15: =(AE15*0.05) -> 1539.32 | AG15: 5 | AH15: PAGO | BU15: FILME PVC AMARELO 380MM X 9 MICRA | BV15: 4 | BW15: VERBAL | BX15: 45575 | BY15: 20 | BZ15: BOB | CA15: 83.8 | CB15: 45596 | CC15: 45588 | CD15: 76305 | CE15: 22 | CF15: 0 | CG15: =(CA15*CE15) -> 1843.6 | CH15: =(CG15*0.05) -> 92.18 | CI15: 5
Q16: YABUTA | R16: TAMPA OVO GALINHA 20 UND PEQUENA - FAZENDA CARU - YABUTA | S16: 13 | T16: WTSAPP | U16: 45559 | V16: 150 | W16: MIL | X16: 150 | Y16: 147 | Z16: 45589 | AA16: 45570 | AB16: 23435 | AC16: 150000 | AD16: =(AC16-V16*1000) -> 0 | AE16: =(AC16*Y16/1000) -> 22050 | AF16: =(AE16*0.05) -> 1102.5 | AG16: 2.5 | AH16: PAGO | BU16: FILME PVC AMARELO 400MM X 9 MICRA | BV16: 4 | BW16: VERBAL | BX16: 45575 | BY16: 20 | BZ16: BOB | CA16: 88.51 | CB16: 45596 | CC16: 45588 | CD16: 76305 | CE16: 20 | CF16: 0 | CG16: =(CA16*CE16) -> 1770.2 | CH16: =(CG16*0.05) -> 88.51 | CI16: 5
B17: EDIPRINT | C17: =(EI25) -> 758.91183 | D17: =(EI45) -> 0 | E17: =(EI63) -> 450.3858 | F17: =(EI84) -> 1416.6094 | G17: =(EI102) -> 944.92771 | H17: =(EI114) -> 282.3296 | I17: =(EI126) -> 0 | J17: =(EI150) -> 0 | K17: =(EI169) -> 174.312 | L17: =(EI188) -> 3330.2748 | M17: =(EI206) -> 0 | N17: =(EI225) -> 0 | Q17: YABUTA | R17: TAMPA OVO GALINHA 20 UND PEQUENA - GRANJA YABUTA BASTOS | S17: 17 | T17: WTSAPP | U17: 45559 | V17: 500 | W17: MIL | X17: =(V17) -> 500 | Y17: 159 | Z17: 45670 | AA17: 45673 | AB17: 24113 | AC17: 300000 | AD17: =(AC17-V17*1000) -> -200000 | AE17: =(AC17*Y17/1000) -> 47700 | AF17: =(AE17*0.025) -> 1192.5 | AG17: 2.5 | AH17: PAGO
Q18: HORTA VITAE | R18: BANDEJA OVO GALINHA 20 UND - NATURAL DA TERRA - HORTA VITAE | S18: 496 | T18: E-MAIL | U18: 45618 | V18: 17.6 | W18: MIL | X18: 44 | Y18: 1328 | Z18: 45625 | AA18: 45660 | AB18: 24004 | AC18: 17600 | AD18: =(AC18-V18*1000) -> 0 | AE18: =(Y18*V18) -> 23372.8 | AF18: =(AE18*0.05) -> 1168.64 | AG18: 5 | AH18: PAGO | BU18: CABELAUTO | BV18: THIAGO NUNES - 35 3629-2500 / 2544
B19: STANG | C19: =(HA25) -> 0 | D19: =(HA43) -> 0 | E19: =(HA61) -> 0 | F19: =(HA77) -> 0 | G19: =(HA96) -> 0 | H19: =(HA116) -> 0 | I19: =(HA141) -> 0 | J19: =(HA159) -> 0 | K19: =(HA177) -> 0 | L19: =(HA195) -> 0 | M19: =(HA213) -> 0 | N19: =(HA231) -> 0 | Q19: HORTA VITAE | R19: BANDEJA OVO GALINHA 10 UND - HORTA VITAE | S19: 498 | T19: E-MAIL | U19: 45637 | V19: 105 | W19: MIL | X19: 210 | Y19: 544 | Z19: 45644 | AA19: 45660 | AB19: 24004 | AC19: 105000 | AD19: =(AC19-V19*1000) -> 0 | AE19: =(AC19*Y19/1000) -> 57120 | AF19: =(AE19*0.05) -> 2856 | AG19: 5 | AH19: PAGO | BW19: OC | BX19: DATA | CA19: PREÇO | CB19: DATA | CC19: DATA | CH19: VALOR
Q20: HORTA VITAE | R20: BANDEJA OVO GALINHA 6 UND - DUPLA - HORTA VITAE | S20: 503 | T20: E-MAIL | U20: 45672 | V20: 16 | W20: MIL | X20: 32 | Y20: 615 | Z20: 45681 | AA20: 45681 | AB20: 24166 | AC20: 16000 | AD20: =(AC20-V20*1000) -> 0 | AE20: =(AC20*Y20/1000) -> 9840 | AF20: =(AE20*0.05) -> 492 | AG20: 5 | AH20: PAGO | BU20: PRODUTO | BV20: PEDIDO | BW20: DO | BX20: DO | BY20: QUANT | BZ20: UND | CA20: POR | CB20: DE | CC20: DE | CD20: N F | CE20: QUANT | CF20: SALDO | CG20: VALOR | CH20: DA | CI20: C | CJ20: OBSERVAÇÃO
B21: MAET | C21: 0 | D21: 0 | E21: 0 | F21: 0 | G21: =(IK102) -> 0 | H21: =(IK122) -> 0 | I21: =(IK147) -> 0 | J21: =(IK165) -> 0 | K21: =(IK183) -> 0 | L21: =(IK201) -> 0 | M21: =(IK220) -> 0 | N21: =(IK238) -> 0 | Q21: HORTA VITAE | R21: BANDEJA OVO GALINHA 10 UND - HORTA VITAE | S21: 504 | T21: E-MAIL | U21: 45672 | V21: 270 | W21: MIL | X21: =(V21*1000/500) -> 540 | Y21: 544 | Z21: 45681 | AA21: 45681 | AB21: 24166 | AC21: 221000 | AD21: =(AC21-V21*1000) -> -49000 | AE21: =(AC21*Y21/1000) -> 120224 | AF21: =(AE21*0.05) -> 6011.2 | AG21: 5 | AH21: PAGO | AJ21: CUMBUCA 500 G - MA 15 | AK21: 25 | AL21: WHATSAPP | AM21: 45336 | AN21: 15 | AO21: MIL | AP21: =(AU21/1000) -> 15 | AQ21: 411 | AR21: 45341 | AS21: 45341 | AU21: 15000 | AV21: =(AU21-AN21*1000) -> 0 | AW21: =(AU21*AQ21/1000) -> 6165 | AX21: =(AW21*0.05) -> 308.25 | AY21: 5 | BW21: CLIENTE | BX21: PEDIDO | CA21: UND | CB21: ENTREGA | CC21: FATURA | CH21: COMISSÃO
Q22: HORTA VITAE | R22: BANDEJA OVO GALINHA 12 UND - HORTA VITAE | S22: 505 | T22: E-MAIL | U22: 45672 | V22: 4 | W22: MIL | X22: 8 | Y22: 655 | Z22: 45681 | AA22: 45681 | AB22: 24166 | AC22: 4000 | AD22: =(AC22-V22*1000) -> 0 | AE22: =(AC22*Y22/1000) -> 2620 | AF22: =(AE22*0.05) -> 131 | AG22: 5 | AH22: PAGO
Q23: HORTA VITAE | R23: BANDEJA OVO GALINHA 20 UND - ITO COUTRY - HORTA VITAE | S23: 506 | T23: E-MAIL | U23: 45672 | V23: 32 | W23: MIL | X23: 80 | Y23: 1328 | Z23: 45681 | AA23: 45681 | AB23: 24166 | AC23: 32000 | AD23: =(AC23-V23*1000) -> 0 | AE23: =(AC23*Y23/1000) -> 42496 | AF23: =(AE23*0.05) -> 2124.8 | AG23: 5 | AH23: PAGO
B24: TOTAL | C24: =SUM(C9:C23) -> 29621.342 | D24: =SUM(D9:D23) -> 21731.034 | E24: =SUM(E9:E23) -> 41290.094 | F24: =SUM(F9:F23) -> 45061.659 | G24: =SUM(G9:G23) -> 41172.327 | H24: =SUM(H9:H23) -> 37971.102 | I24: =SUM(I9:I23) -> 33494.103 | J24: =SUM(J9:J23) -> 34390.459 | ... N24: =SUM(N9:N23) -> 0 | Q24: HORTA VITAE | R24: BANDEJA OVO CODORNA 30 UND - HORTA VITAE | S24: 507 | T24: E-MAIL | U24: 45672 | V24: 45 | W24: MIL | X24: =(V24*1000/500) -> 90 | Y24: 427 | Z24: 45681 | AA24: 45681 | AB24: 24166 | AC24: 45000 | AD24: =(AC24-V24*1000) -> 0 | AE24: =(AC24*Y24/1000) -> 19215 | AF24: =(AE24*0.05) -> 960.75 | AG24: 5 | AH24: PAGO | HR24: =SUM(HR10:HR23) -> 0 | HS24: =SUM(HS10:HS23) -> 0
P25: =SUM(C24:N24) -> 354561.28 | Q25: HORTA VITAE | R25: BANDEJA OVO GALINHA 20 UND - OBA BEM QUERER - HORTA VITAE | S25: 508 | T25: E-MAIL | U25: 45672 | V25: 2 | W25: MIL | X25: 5 | Y25: 1328 | Z25: 45681 | AA25: 45681 | AB25: 24166 | AC25: 2000 | AD25: =(AC25-V25*1000) -> 0 | AE25: =(AC25*Y25/1000) -> 2656 | AF25: =(AE25*0.05) -> 132.8 | AG25: 5 | AH25: PAGO | EH25: =SUM(EH10:EH24) -> 18972.796 | EI25: =SUM(EI10:EI24) -> 758.91183
M26: TOTAL ANO | N26: =(P25) -> 354561.28 | AJ26: CACO - DE MARCHI | AK26: JOÃO LUIZ AGORRETA (19) 99763-7618 (19) 3746-1406 | BP26: =SUM(BP10:BP25) -> 0 | BQ26: =SUM(BQ10:BQ25) -> 0 | CY26: =SUM(CY10:CY25) -> 0 | CZ26: =SUM(CZ10:CZ25) -> 0 | HA26: =SUM(HA10:HA25) -> 310 | IK26: =SUM(IK10:IK25) -> 424.552 | JB26: =SUM(JB10:JB25) -> 0 | JC26: =SUM(JC10:JC25) -> 0
AL27: OC | AM27: DATA | AQ27: PREÇO | AR27: DATA | AS27: DATA | AX27: VALOR
AE28: =SUM(AE10:AE27) -> 568757.56 | AF28: =(AE28*0.05) -> 28437.878 | AJ28: PRODUTO | AK28: PEDIDO | AL28: DO | AM28: DO | AN28: QUANT | AO28: UND | AP28: CAIXAS | AQ28: POR | AR28: DE | AS28: DE | AT28: N F | AU28: QUANT | AV28: SALDO | AW28: VALOR | AX28: DA | AY28: C | AZ28: OBSERVAÇÃO | HF28: CASA DA UVA
AL29: CLIENTE | AM29: PEDIDO | AQ29: UND | AR29: ENTREGA | AS29: FATURA | AX29: COMISSÃO | DU29: EDIPRINT FEVEREIRO 2025 | HH29: OC | HI29: DATA | HL29: PREÇO | HM29: DATA | HN29: DATA | HS29: VALOR
M30: 2017 | N30: 58042.33 | Q30: SERRAPLAST FEVEREIRO 2025 | BC30: BRASIL SUL FEVEREIRO 2025 | CL30: CCS FEVEREIRO 2025 | DX30: OC | DY30: DATA | EB30: PREÇO | EC30: DATA | ED30: DATA | EI30: VALOR | FD30: COPOBRAS FEVEREIRO 2024 | GM30: STANG - FEVEREIRO 2025 | HF30: PRODUTO | HG30: PEDIDO | HH30: DO | HI30: DO | HJ30: QUANT | HK30: UND | HL30: POR | HM30: DE | HN30: DE | HO30: N F | HP30: QUANT | HQ30: SALDO | HR30: VALOR | HS30: DA | HU30: OBSERVAÇÃO | HW30: LING PACKING - FEVEREIRO 2025 | IP30: CACO DE MARCHI
M31: 2018 | N31: 90853.36 | T31: OC | U31: DATA | Y31: PREÇO | Z31: DATA | AA31: DATA | AF31: VALOR | BF31: OC | BG31: DATA | BJ31: PREÇO | BK31: DATA | BL31: DATA | BQ31: VALOR | CO31: OC | CP31: DATA | CS31: PREÇO | CT31: DATA | CU31: DATA | CZ31: VALOR | DU31: CLIENTE | DV31: PRODUTO | DW31: PEDIDO | DX31: DO | DY31: DO | DZ31: QUANT | EA31: UND | EB31: POR | EC31: DE | ED31: DE | EE31: NF | EF31: QUANT | EG31: SALDO | EH31: VALOR | EI31: DA | EJ31: C | EK31: OBSERVAÇÃO | EM31: RAIAR ORGÂNICOS | FG31: OC | FH31: DATA | FK31: PREÇO | FL31: DATA | FM31: DATA | FR31: VALOR | GP31: OC | GQ31: DATA | GT31: PREÇO | GU31: DATA | GV31: DATA | HA31: VALOR | HH31: CLIENTE | HI31: PEDIDO | HL31: UND | HM31: ENTREGA | HN31: FATURA | HS31: COMISSÃO | HZ31: OC | IA31: DATA | ID31: PREÇO | IE31: DATA | IF31: DATA | IK31: VALOR | IR31: OC | IS31: DATA | IV31: PREÇO | IW31: DATA | IX31: DATA | JC31: VALOR
M32: 2019 | N32: 104259.5 | Q32: CLIENTE | R32: PRODUTO | S32: PEDIDO | T32: DO | U32: DO | V32: QUANT | W32: UND | X32: CAIXAS | Y32: POR | Z32: DE | AA32: DE | AB32: NF | AC32: QUANT | AD32: SALDO | AE32: VALOR | AF32: DA | AG32: C | AH32: OBSERVAÇÃO | BC32: CLIENTE | BD32: PRODUTO | BE32: PEDIDO | BF32: DO | BG32: DO | BH32: QUANT | BI32: UND | BJ32: POR | BK32: DE | BL32: DE | BM32: NF | BN32: QUANT | BO32: SALDO | BP32: VALOR | BQ32: DA | BR32: C | BS32: OBSERVAÇÃO | CL32: CLIENTE | CM32: PRODUTO | CN32: PEDIDO | CO32: DO | CP32: DO | CQ32: QUANT | CR32: UND | CS32: POR | CT32: DE | CU32: DE | CV32: NF | CW32: QUANT | CX32: SALDO | CY32: VALOR | CZ32: DA | DA32: C | DB32: OBSERVAÇÃO | DX32: CLIENTE | DY32: PEDIDO | EB32: UND | EC32: ENTREGA | ED32: FATURA | EI32: COMISSÃO | EO32: OC | EP32: DATA | ES32: PREÇO | ET32: DATA | EU32: DATA | EZ32: VALOR | FD32: CLIENTE | FE32: PRODUTO | FF32: PEDIDO | FG32: DO | FH32: DO | FI32: QUANT | FJ32: UND | FK32: POR | FL32: DE | FM32: DE | FN32: NF | FO32: QUANT | FP32: SALDO | FQ32: VALOR | FR32: DA | FT32: OBSERVAÇÃO | GM32: CLIENTE | GN32: PRODUTO | GO32: PEDIDO | GP32: DO | GQ32: DO | GR32: QUANT | GS32: UND | GT32: POR | GU32: DE | GV32: DE | GW32: NF | GX32: QUANT | GY32: SALDO | GZ32: VALOR | HA32: DA | HB32: C | HC32: CLAUDIA | HD32: OBSERVAÇÃO | HW32: CLIENTE | HX32: PRODUTO | HY32: PEDIDO | HZ32: DO | IA32: DO | IB32: QUANT | IC32: UND | ID32: POR | IE32: DE | IF32: DE | IG32: NF | IH32: QUANT | II32: SALDO | IJ32: VALOR | IK32: DA | IN32: OBSERVAÇÃO | IP32: PRODUTO | IQ32: PEDIDO | IR32: DO | IS32: DO | IT32: QUANT | IU32: UND | IV32: POR | IW32: DE | IX32: DE | IY32: N F | IZ32: QUANT | JA32: SALDO | JB32: VALOR | JC32: DA | JE32: OBSERVAÇÃO
M33: 2020 | N33: 164058.04 | T33: CLIENTE | U33: PEDIDO | Y33: UND | Z33: ENTREGA | AA33: FATURA | AF33: COMISSÃO | BF33: CLIENTE | BG33: PEDIDO | BJ33: UND | BK33: ENTREGA | BL33: FATURA | BQ33: COMISSÃO | EM33: PRODUTO | EN33: PEDIDO | EO33: DO | EP33: DO | EQ33: QUANT | ER33: UND | ES33: POR | ET33: DE | EU33: DE | EV33: N F | EW33: QUANT | EX33: SALDO | EY33: VALOR | EZ33: DA | FB33: OBSERVAÇÃO | GP33: CLIENTE | GQ33: PEDIDO | GT33: UND | GU33: ENTREGA | GV33: FATURA | HA33: COMISSÃO | IM33: CLAUDIA | IR33: CLIENTE | IS33: PEDIDO | IV33: UND | IW33: ENTREGA | IX33: FATURA | JC33: COMISSÃO
M34: 2021 | N34: 229430.35 | Q34: RAIAR | R34: BANDEJA OVO GALINHA 20 UND - OVO GRANDE - RAIAR | S34: 41 | T34: 932 | U34: 45602 | V34: 23.2 | W34: MIL | X34: 58 | Y34: 1327 | Z34: 45681 | AA34: 45696 | AB34: 24298 | AC34: 23200 | AD34: =(AC34-V34*1000) -> 0 | AE34: =(AC34*Y34/1000) -> 30786.4 | AF34: =(AE34*0.05) -> 1539.32 | AG34: 5 | AH34: PAGO | EO34: CLIENTE | EP34: PEDIDO | ES34: UND | ET34: ENTREGA | EU34: FATURA | EZ34: COMISSÃO | GM34: TACTAPE | GN34: FILME STRECH TRANSPARENTE - 500MM x 23 MICRAS | GO34: 4 | GP34: 987 | GQ34: 45707 | GR34: 500 | GS34: KGS | GT34: 12.5 | GU34: 45713 | GV34: 45713 | GW34: 4509 | GX34: 506 | GY34: =(GR34-GX34) -> -6 | GZ34: =GT34*GX34/1 -> 6325 | HA34: =(GZ34*0.05) -> 316.25 | HB34: 5 | HC34: =(GZ34*0.02) -> 126.5 | HD34: PAGO
M35: 2022 | N35: 222796.05 | Q35: RAIAR | R35: BANDEJA OVO GALINHA 20 UND - OVO GRANDE - RAIAR | S35: 44 | T35: WHATSAPP | U35: 45684 | V35: 23.2 | W35: MIL | X35: 58 | Y35: 1327 | Z35: 45691 | AA35: 45696 | AB35: 24298 | AC35: 23200 | AD35: =(AC35-V35*1000) -> 0 | AE35: =(AC35*Y35/1000) -> 30786.4 | AF35: =(AE35*0.05) -> 1539.32 | AG35: 5 | AH35: PAGO | CO35: CLIENTE | CP35: PEDIDO | CS35: UND | CT35: ENTREGA | CU35: FATURA | CZ35: COMISSÃO | EM35: ROTULO OVO GALINHA 20 UND - RAIAR - NATURAL DA TERRA | EN35: 14 | EO35: E-MAIL | EP35: 45643 | EQ35: 100 | ER35: MIL | ES35: 95.82 | ET35: 45664 | EU35: 45673 | EV35: 41222 | EW35: 100010 | EX35: =(EQ35*1000-EW35) -> -10 | EY35: =(ES35*EW35/1000) -> 9582.9582 | EZ35: =(EY35*0.04) -> 383.31833 | FA35: 4 | FB35: ENTREGAR NA SERRAPLAST | FG35: CLIENTE | FH35: PEDIDO | FK35: UND | FL35: ENTREGA | FM35: FATURA | FR35: COMISSÃO | HZ35: CLIENTE | IA35: PEDIDO | ID35: UND | IE35: ENTREGA | IF35: FATURA | IK35: COMISSÃO
M36: 2023 | N36: =([1]Planilha5!P22) -> 273068.19 | Q36: YABUTA | R36: BANDEJA OVO CODORNA 30 UND - SRC01 | S36: 18 | T36: WTSAPP | U36: 45685 | V36: 300 | W36: MIL | X36: 600 | Y36: 398 | Z36: 45691 | AA36: 45710 | AB36: 24393 | AC36: 85000 | AD36: =(AC36-V36*1000) -> -215000 | AE36: =(AC36*Y36/1000) -> 33830 | AF36: =(AE36*0.025) -> 845.75 | AG36: 2.5 | AH36: PAGO | BU36: FILME PVC ENCOLHIVEL 370 MM X 40 MICRA | BV36: 23 | BW36: 4500058267 | BX36: 45470 | BY36: 100 | BZ36: KG | CA36: 15.65 | CB36: 45491 | CC36: 45478 | CD36: 74830 | CE36: 110.72 | CF36: 0 | CG36: =(CA36*CE36) -> 1732.768 | CH36: =(CG36*0.05) -> 86.6384 | CI36: 5 | EM36: ROTULO OVO GALINHA 20 UND - RAIAR - OBA BEM QUERER | EN36: 15 | EO36: E-MAIL | EP36: 45643 | EQ36: 100 | ER36: MIL | ES36: 92.84 | ET36: 45664 | EU36: 45673 | EV36: 41222 | EW36: 101140 | EX36: =(EQ36*1000-EW36) -> -1140 | EY36: =(ES36*EW36/1000) -> 9389.8376 | EZ36: =(EY36*0.04) -> 375.5935 | FA36: 4 | FB36: ENTREGAR NA SERRAPLAST | GH36: =SUM(GH10:GH35) -> 0 | GI36: =SUM(GI10:GI35) -> 0 | HW36: CASA DA UVA | HX36: FILME STRECH TRANSP.C/TUBETE - 500MM x 25 MICRAS | HY36: 12 | HZ36: WHATSAPP | IA36: 45714 | IB36: 250 | IC36: KGS | ID36: 12.7 | IE36: 45721 | IF36: 45715 | IG36: 416 | IH36: 253.6 | II36: =(IB36-IH36) -> -3.6 | IJ36: =(IH36*ID36/1) -> 3220.72 | IK36: =(IJ36*0.05) -> 161.036 | IL36: 5 | IM36: =(IJ36*0.02) -> 64.4144 | IN36: PAGO
M37: 2024 | N37: 314643.16 | Q37: ROZENDO | R37: BANDEJA OVO GALINHA 10 UND - ROZENDO | S37: 109 | T37: VERBAL | U37: 45622 | V37: 149.5 | W37: MIL | X37: 299 | Y37: 515 | Z37: 45667 | AA37: 45691 | AB37: 24245 | AC37: 26500 | AD37: =(AC37-V37*1000) -> -123000 | AE37: =(AC37*Y37/1000) -> 13647.5 | AF37: =(AE37*0.05) -> 682.375 | AG37: 5 | AH37: PAGO | BU37: FILME PVC ENCOLHIVEL 550 MM X 40 MICRA | BV37: 25 | BW37: 4500058267 | BX37: 45470 | BY37: 100 | BZ37: KG | CA37: 15.65 | CB37: 45491 | CC37: 45478 | CD37: 74830 | CE37: 104.53 | CF37: 0 | CG37: =(CA37*CE37) -> 1635.8945 | CH37: =(CG37*0.05) -> 81.794725 | CI37: 5 | EM37: ROTULO OVO GALINHA 20 UND - RAIAR - OVO GRANDE | EN37: 16 | EO37: 3787 | EP37: 45749 | EQ37: 200 | ER37: MIL | ES37: 89.45 | ET37: 45763 | EU37: 45769 | EV37: 41652 | EW37: 205000 | EX37: =(EQ37*1000-EW37) -> -5000 | EY37: =(ES37*EW37/1000) -> 18337.25 | EZ37: =(EY37*0.04) -> 733.49 | FA37: 4 | FB37: ENTREGAR NA SERRAPLAST
